Workbook

Sheet Cover
B2: TITAN COMPANY LIMITED
B3: Institutional Financial Statement & Valuation Model | Ind AS Architecture
B5: Filing Basis | C5: Consolidated Financial Statements | Fiscal Year Ending 31 March
B6: Reporting Currency | C6: Indian Rupees (INR) in Crore
B7: Historical Horizon | C7: FY 2021-22A to FY 2025-26A (Audited Annual Reports)
B8: Forecast Horizon | C8: FY 2026-27E to FY 2030-31E (Driver-Based Projections)
B9: Fade Horizon | C9: FY 2031-32E to FY 2035-36E (5-Year Value-Driver Fade Period in DCF)
B10: Active Scenario | C10: =Inputs!$C$6 -> Base
B11: Workbook Audit Status | C11: =Checks!$C$32 -> ALL CHECKS PASSED
B12: Valuation Methodology | C12: Unlevered DCF (WACC, CAPM, Gordon Growth & Exit EV/EBITDA Multiples)
B14: WORKBOOK STRUCTURE & NAVIGATION
B15: Summary | C15: Executive dashboard, valuation summary, key credit metrics, and visual charts
B16: Inputs | C16: Assumption drivers, scenario selector (Bear/Base/Bull), WACC and valuation parameters
B17: IS | C17: Consolidated Statement of Profit and Loss (audited historicals and projected drivers)
B18: BS | C18: Consolidated Balance Sheet (self-balancing, zero artificial plug, cash sweep)
B19: CF | C19: Consolidated Statement of Cash Flows (Ind AS indirect method with Ind AS 116 retail leases)
B20: Schedules | C20: Supporting schedules: Working Capital, Capex/FA, Debt Revolver, Leases, Equity, Ratios
B21: Earnings_Quality | C21: Forensic accounting suite: Sloan accruals, DuPont 3-stage, CCC, Altman Z''-score
B22: DCF | C22: Discounted Cash Flow: 10-year UFCF, CAPM WACC, terminal value, equity bridge
B23: Sensitivity | C23: 2D live formula sensitivity tables: WACC vs Terminal Growth g, WACC vs Exit Multiple
B24: Scenarios | C24: Scenario comparative matrix (Bear vs Base vs Bull)
B25: Checks | C25: Automated system audit suite testing internal mathematical identities
B26: PowerBI_Export | C26: Flat unpivoted dataset with standardized headers for Power BI / Python ingest
... B28: Notes | C28: Detailed documentation of methodology, calibration notes, and Ind AS accounting policies

Sheet Summary
A1: TITAN COMPANY LIMITED: EXECUTIVE VALUATION DASHBOARD
A2: Integrated Financial Model | FY22A-FY26A Audited Actuals, FY27E-FY31E Projections | INR Crore
A4: Active Model Scenario | C4: =Inputs!$C$6 -> Base | E4: Model Methodology & Principles
A5: Workbook Integrity Status | C5: =Checks!$C$32 -> ALL CHECKS PASSED | E5: Operating EBITDA/EBIT strictly exclude non-operating treasury income. Net Debt incorporates Gold on Loan and Ind AS 116 Leases.
A6: Current Market Price (CMP, INR) | C6: =Inputs!$C$9 -> 4798.5
A7: Weighted Average Cost of Capital (WACC) | C7: =DCF!$C$15 -> 0.112695
A8: Perpetual Terminal Growth Rate (g) | C8: =Inputs!$C$18 -> 0.05
A9: DCF Target Value per Share (Gordon Growth, INR) | C9: =DCF!$C$62 -> 995.47082
A10: Gordon Growth DCF Upside / (Downside) | C10: =DCF!$C$64 -> -0.79254542
A11: Target Value per Share (Exit Multiple, INR) | C11: =DCF!$C$73 -> 2861.2805
A12: Exit Multiple Upside / (Downside) | C12: =DCF!$C$74 -> -0.40371355
A13: Enterprise Value (Gordon Growth, INR cr) | C13: =DCF!$C$52 -> 97505.899
A14: PV of Terminal Value % Enterprise Value | C14: =DCF!$C$77 -> 0.68507887
A17: KPI Overview (INR crore unless stated) | B17: Unit | C17: FY22A | D17: FY23A | E17: FY24A | F17: FY25A | G17: FY26A | H17: FY27E | I17: FY28E | J17: FY29E | K17: FY30E | L17: FY31E
A18: Revenue from operations | B18: cr | C18: =IS!C5 -> 28799 | D18: =IS!D5 -> 40575 | E18: =IS!E5 -> 51084 | F18: =IS!F5 -> 60456 | G18: =IS!G5 -> 87584 | H18: =IS!H5 -> 103349.12 | I18: =IS!I5 -> 118851.49 | J18: =IS!J5 -> 134302.18 | ... L18: =IS!L5 -> 166964.47
A19: y/y revenue growth rate | B19: % | D19: =IS!D6 -> 0.40890309 | E19: =IS!E6 -> 0.25900185 | F19: =IS!F6 -> 0.18346253 | G19: =IS!G6 -> 0.44872304 | H19: =IS!H6 -> 0.18 | I19: =IS!I6 -> 0.15 | J19: =IS!J6 -> 0.13 | K19: =IS!K6 -> 0.12 | L19: =IS!L6 -> 0.11
A20: Gross margin | B20: % | C20: =IS!C9 -> 0.2485503 | D20: =IS!D9 -> 0.25187924 | E20: =IS!E9 -> 0.2280949 | F20: =IS!F9 -> 0.21503242 | G20: =IS!G9 -> 0.19726206 | H20: =IS!H9 -> 0.197 | I20: =IS!I9 -> 0.198 | J20: =IS!J9 -> 0.199 | ... L20: =IS!L9 -> 0.2
A21: Operating EBITDA | B21: cr | C21: =IS!C14 -> 3341 | D21: =IS!D14 -> 4879 | E21: =IS!E14 -> 5292 | F21: =IS!F14 -> 5694 | G21: =IS!G14 -> 8355 | H21: =IS!H14 -> 9921.5155 | I21: =IS!I14 -> 11647.446 | J21: =IS!J14 -> 13430.218 | ... L21: =IS!L14 -> 17030.376
A22: EBITDA margin | B22: % | C22: =IS!C15 -> 0.11601097 | D22: =IS!D15 -> 0.12024646 | E22: =IS!E15 -> 0.10359408 | F22: =IS!F15 -> 0.0941842 | G22: =IS!G15 -> 0.095394136 | H22: =IS!H15 -> 0.096 | I22: =IS!I15 -> 0.098 | J22: =IS!J15 -> 0.1 | ... L22: =IS!L15 -> 0.102
A23: Operating EBIT | B23: cr | C23: =IS!C17 -> 2942 | D23: =IS!D17 -> 4438 | E23: =IS!E17 -> 4708 | F23: =IS!F17 -> 5001 | G23: =IS!G17 -> 7529 | H23: =IS!H17 -> 8785.9555 | I23: =IS!I17 -> 10291.254 | J23: =IS!J17 -> 11832.33 | ... L23: =IS!L17 -> 14898.547
A24: EBIT margin | B24: % | C24: =IS!C18 -> 0.10215632 | D24: =IS!D18 -> 0.1093777 | E24: =IS!E18 -> 0.092161929 | F24: =IS!F18 -> 0.082721318 | G24: =IS!G18 -> 0.08596319 | H24: =IS!H18 -> 0.085012388 | I24: =IS!I18 -> 0.086589189 | J24: =IS!J18 -> 0.088102289 | ... L24: =IS!L18 -> 0.089231843
A25: Profit After Tax (PAT) | B25: cr | C25: =IS!C27 -> 2198 | D25: =IS!D27 -> 3274 | E25: =IS!E27 -> 3496 | F25: =IS!F27 -> 3337 | G25: =IS!G27 -> 5073 | H25: =IS!H27 -> 5865.4261 | I25: =IS!I27 -> 6934.2101 | J25: =IS!J27 -> 8081.8267 | ... L25: =IS!L27 -> 10454.444
A26: PAT margin | B26: % | C26: =IS!C28 -> 0.076322095 | D26: =IS!D28 -> 0.08069008 | E26: =IS!E28 -> 0.068436301 | F26: =IS!F28 -> 0.055197168 | G26: =IS!G28 -> 0.057921538 | H26: =IS!H28 -> 0.056753518 | I26: =IS!I28 -> 0.058343486 | J26: =IS!J28 -> 0.060176437 | ... L26: =IS!L28 -> 0.06261478
A27: Basic EPS (INR) | B27: INR | C27: =IS!C31 -> 24.757828 | D27: =IS!D31 -> 36.877675 | E27: =IS!E31 -> 39.378238 | F27: =IS!F31 -> 37.587294 | G27: =IS!G31 -> 57.141248 | H27: =IS!H31 -> 66.066976 | I27: =IS!I31 -> 78.105543 | J27: =IS!J31 -> 91.032065 | ... L27: =IS!L31 -> 117.75674
A28: Cash flow from operations (CFO) | B28: cr | C28: =CF!C17 -> -724 | D28: =CF!D17 -> 1370 | E28: =CF!E17 -> 1695 | F28: =CF!F17 -> -541 | G28: =CF!G17 -> 5590 | H28: =CF!H17 -> 4433.9242 | I28: =CF!I17 -> 6352.1374 | J28: =CF!J17 -> 7764.5457 | ... L28: =CF!L17 -> 10312.795
A29: Capital expenditures | B29: cr | C29: =Schedules!C32 -> 224 | D29: =Schedules!D32 -> 432 | E29: =Schedules!E32 -> 691 | F29: =Schedules!F32 -> 494 | G29: =Schedules!G32 -> 902 | H29: =Schedules!H32 -> 1240.1894 | I29: =Schedules!I32 -> 1426.2179 | J29: =Schedules!J32 -> 1611.6262 | ... L29: =Schedules!L32 -> 2003.5737
A30: Free Cash Flow (FCF) | B30: cr | C30: =CF!C37 -> -948 | D30: =CF!D37 -> 938 | E30: =CF!E37 -> 1004 | F30: =CF!F37 -> -1035 | G30: =CF!G37 -> 4688 | H30: =CF!H37 -> 3193.7348 | I30: =CF!I37 -> 4925.9196 | J30: =CF!J37 -> 6152.9195 | ... L30: =CF!L37 -> 8309.2217
A31: Net debt (incl. GoL & Leases) | B31: cr | C31: =Schedules!C95 -> 5687 | D31: =Schedules!D95 -> 5860 | E31: =Schedules!E95 -> 12336 | F31: =Schedules!F95 -> 17856 | G31: =Schedules!G95 -> 26455 | H31: =Schedules!H95 -> 29025.681 | I31: =Schedules!I95 -> 30617.666 | J31: =Schedules!J95 -> 31412.3 | ... L31: =Schedules!L95 -> 31379.188
A32: Net debt / EBITDA | B32: x | C32: =Schedules!C96 -> 1.702185 | D32: =Schedules!D96 -> 1.2010658 | E32: =Schedules!E96 -> 2.3310658 | F32: =Schedules!F96 -> 3.1359326 | G32: =Schedules!G96 -> 3.1663674 | H32: =Schedules!H96 -> 2.9255289 | I32: =Schedules!I96 -> 2.6287021 | J32: =Schedules!J96 -> 2.338927 | ... L32: =Schedules!L96 -> 1.8425423
A33: Return on Equity (ROE) | B33: % | D33: =Schedules!D93 -> 0.3083298 | E33: =Schedules!E93 -> 0.32830915 | F33: =Schedules!F93 -> 0.31755246 | G33: =Schedules!G93 -> 0.37128115 | H33: =Schedules!H93 -> 0.32674907 | I33: =Schedules!I93 -> 0.30314827 | J33: =Schedules!J93 -> 0.28204826 | K33: =Schedules!K93 -> 0.26169625 | L33: =Schedules!L93 -> 0.24431241
A34: Return on Invested Capital (ROIC) | B34: % | D34: =Schedules!D94 -> 0.19932735 | E34: =Schedules!E94 -> 0.18029922 | F34: =Schedules!F94 -> 0.14372075 | G34: =Schedules!G94 -> 0.15678912 | H34: =Schedules!H94 -> 0.14344826 | I34: =Schedules!I94 -> 0.14569084 | J34: =Schedules!J94 -> 0.14793129 | K34: =Schedules!K94 -> 0.1488501 | L34: =Schedules!L94 -> 0.14953587
A35: Days Inventory Outstanding (DIO) | B35: days | C35: =Schedules!C8 -> 229.53121 | D35: =Schedules!D8 -> 199.41229 | E35: =Schedules!E8 -> 176.34447 | F35: =Schedules!F8 -> 216.77259 | G35: =Schedules!G8 -> 221.90102 | H35: =Schedules!H8 -> 220 | I35: =Schedules!I8 -> 220 | J35: =Schedules!J8 -> 220 | ... L35: =Schedules!L8 -> 220

Sheet Inputs
A1: ASSUMPTIONS & DYNAMIC SCENARIO CONTROL
A2: Institutional driver console. Blue = input | Black = formula | Green = link. Yellow fill = key decision cell.
A4: 1. GLOBAL CONTROLS & SCENARIO SWITCHES
A5: Active Scenario Selector (1 = Bear, 2 = Base, 3 = Bull) | C5: 2
A6: Active Scenario Label | C6: =CHOOSE($C$5,"Bear","Base","Bull") -> Base
A7: Gold-on-Loan Accounting Mode (1 = Operating, 2 = Debt-like) | C7: 1 | D7: =IF($C$7=1,"Operating: Netted in NWC, interest in EBIT, NOT in EV bridge","Debt-like: Excluded from NWC, DEDUCTED in EV bridge, interest in financing") -> Operating: Netted in NWC, interest in EBIT, NOT in EV bridge
A8: Valuation Date (Audited Balance Sheet Cutoff) | C8: 31-Mar-2026
A9: Current Market Price (INR per share) | C9: 4798.5 | D9: NSE Closing Price as of Sep-2026 (Kotak Neo/NSE)
A10: Diluted Shares Outstanding (crore) | C10: 88.78
A12: 2. VALUATION & CAPITAL STRUCTURE ASSUMPTIONS
A13: Risk-free rate (10-year Indian G-Sec) | C13: 0.065
A14: Equity risk premium (ERP) | C14: 0.06
A15: Equity beta | C15: 0.9
A16: Pre-tax marginal cost of debt (Kd) | C16: 0.075
A17: Target debt ratio (D / (D + E)) | C17: 0.1
A18: Terminal growth rate (nominal, INR) | C18: 0.05
A19: Terminal Return on New Invested Capital (RONIC) | C19: 0.2
A21: Exit EV/EBITDA Multiple Cross-Check | C21: Bear | D21: Base | E21: Bull | F21: Active Live
A22: Terminal EV / EBITDA Exit Multiple | C22: 20 | D22: 25 | E22: 30 | F22: =CHOOSE($C$5,C22,D22,E22) -> 25
A24: 3. OPERATIONAL SCENARIOS (FY27E - FY31E)
A25: Driver | Historical vs Projections | C25: FY22A | D25: FY23A | E25: FY24A | F25: FY25A | G25: FY26A | H25: FY27E | I25: FY28E | J25: FY29E | K25: FY30E | L25: FY31E
A26: Revenue growth (y/y) - ACTIVE | C26: =IS!C6 -> 0 | D26: =IS!D6 -> 0.40890309 | E26: =IS!E6 -> 0.25900185 | F26: =IS!F6 -> 0.18346253 | G26: =IS!G6 -> 0.44872304 | H26: =CHOOSE($C$5,H27,H28,H29) -> 0.18 | I26: =CHOOSE($C$5,I27,I28,I29) -> 0.15 | J26: =CHOOSE($C$5,J27,J28,J29) -> 0.13 | K26: =CHOOSE($C$5,K27,K28,K29) -> 0.12 | L26: =CHOOSE($C$5,L27,L28,L29) -> 0.11
A27: [Bear] | H27: 0.1 | I27: 0.08 | J27: 0.08 | K27: 0.07 | L27: 0.07
A28: [Base] | H28: 0.18 | I28: 0.15 | J28: 0.13 | K28: 0.12 | L28: 0.11
A29: [Bull] | H29: 0.22 | I29: 0.18 | J29: 0.16 | K29: 0.14 | L29: 0.13
A31: Gross margin (revenue less materials, purchases, inventory change) - ACTIVE | C31: =IS!C9 -> 0.2485503 | D31: =IS!D9 -> 0.25187924 | E31: =IS!E9 -> 0.2280949 | F31: =IS!F9 -> 0.21503242 | G31: =IS!G9 -> 0.19726206 | H31: =CHOOSE($C$5,H32,H33,H34) -> 0.197 | I31: =CHOOSE($C$5,I32,I33,I34) -> 0.198 | J31: =CHOOSE($C$5,J32,J33,J34) -> 0.199 | K31: =CHOOSE($C$5,K32,K33,K34) -> 0.2 | L31: =CHOOSE($C$5,L32,L33,L34) -> 0.2
A32: [Bear] | H32: 0.19 | I32: 0.189 | J32: 0.188 | K32: 0.187 | L32: 0.187
A33: [Base] | H33: 0.197 | I33: 0.198 | J33: 0.199 | K33: 0.2 | L33: 0.2
A34: [Bull] | H34: 0.2 | I34: 0.203 | J34: 0.206 | K34: 0.208 | L34: 0.21
A36: Employee cost % revenue - ACTIVE | C36: =IS!C11 -> 0.046841904 | D36: =IS!D11 -> 0.040591497 | E36: =IS!E11 -> 0.03648892 | F36: =IS!F11 -> 0.0356623 | G36: =IS!G11 -> 0.030610614 | H36: =CHOOSE($C$5,H37,H38,H39) -> 0.03 | I36: =CHOOSE($C$5,I37,I38,I39) -> 0.0295 | J36: =CHOOSE($C$5,J37,J38,J39) -> 0.029 | K36: =CHOOSE($C$5,K37,K38,K39) -> 0.029 | L36: =CHOOSE($C$5,L37,L38,L39) -> 0.0285
A37: [Bear] | H37: 0.031 | I37: 0.031 | J37: 0.031 | K37: 0.031 | L37: 0.031
A38: [Base] | H38: 0.03 | I38: 0.0295 | J38: 0.029 | K38: 0.029 | L38: 0.0285
A39: [Bull] | H39: 0.0295 | I39: 0.029 | J39: 0.0285 | K39: 0.028 | L39: 0.028
A41: Other expenses % revenue - ACTIVE | C41: =IS!C13 -> 0.08569742 | D41: =IS!D13 -> 0.091041282 | E41: =IS!E13 -> 0.088011902 | F41: =IS!F13 -> 0.08518592 | G41: =IS!G13 -> 0.071257307 | H41: =CHOOSE($C$5,H42,H43,H44) -> 0.071 | I41: =CHOOSE($C$5,I42,I43,I44) -> 0.0705 | J41: =CHOOSE($C$5,J42,J43,J44) -> 0.07 | K41: =CHOOSE($C$5,K42,K43,K44) -> 0.07 | L41: =CHOOSE($C$5,L42,L43,L44) -> 0.0695
A42: [Bear] | H42: 0.0725 | I42: 0.0725 | J42: 0.0725 | K42: 0.0725 | L42: 0.0725
A43: [Base] | H43: 0.071 | I43: 0.0705 | J43: 0.07 | K43: 0.07 | L43: 0.0695
A44: [Bull] | H44: 0.07 | I44: 0.0695 | J44: 0.069 | K44: 0.0685 | L44: 0.068
A46: Capex % revenue (PP&E + intangibles) - ACTIVE | C46: =Schedules!C30 -> 0.0077780478 | D46: =Schedules!D30 -> 0.01064695 | E46: =Schedules!E30 -> 0.01352674 | F46: =Schedules!F30 -> 0.008171232 | G46: =Schedules!G30 -> 0.010298685 | H46: =CHOOSE($C$5,H47,H48,H49) -> 0.012 | I46: =CHOOSE($C$5,I47,I48,I49) -> 0.012 | J46: =CHOOSE($C$5,J47,J48,J49) -> 0.012 | K46: =CHOOSE($C$5,K47,K48,K49) -> 0.012 | L46: =CHOOSE($C$5,L47,L48,L49) -> 0.012
A47: [Bear] | H47: 0.01 | I47: 0.01 | J47: 0.01 | K47: 0.01 | L47: 0.01
A48: [Base] | H48: 0.012 | I48: 0.012 | J48: 0.012 | K48: 0.012 | L48: 0.012
A49: [Bull] | H49: 0.014 | I49: 0.014 | J49: 0.014 | K49: 0.014 | L49: 0.014
A51: Inventory days (on COGS) - ACTIVE | C51: =Schedules!C8 -> 229.53121 | D51: =Schedules!D8 -> 199.41229 | E51: =Schedules!E8 -> 176.34447 | F51: =Schedules!F8 -> 216.77259 | G51: =Schedules!G8 -> 221.90102 | H51: =CHOOSE($C$5,H52,H53,H54) -> 220 | I51: =CHOOSE($C$5,I52,I53,I54) -> 220 | J51: =CHOOSE($C$5,J52,J53,J54) -> 220 | K51: =CHOOSE($C$5,K52,K53,K54) -> 220 | L51: =CHOOSE($C$5,L52,L53,L54) -> 220
A52: [Bear] | H52: 235 | I52: 238 | J52: 240 | K52: 240 | L52: 240
A53: [Base] | H53: 220 | I53: 220 | J53: 220 | K53: 220 | L53: 220
A54: [Bull] | H54: 215 | I54: 215 | J54: 215 | K54: 215 | L54: 215
A56: Payable days (on COGS) - ACTIVE | C56: =Schedules!C10 -> 21.824777 | D56: =Schedules!D10 -> 14.597595 | E56: =Schedules!E10 -> 13.051582 | F56: =Schedules!F10 -> 15.098091 | G56: =Schedules!G10 -> 14.868505 | H56: =CHOOSE($C$5,H57,H58,H59) -> 15 | I56: =CHOOSE($C$5,I57,I58,I59) -> 15 | J56: =CHOOSE($C$5,J57,J58,J59) -> 15 | K56: =CHOOSE($C$5,K57,K58,K59) -> 15 | L56: =CHOOSE($C$5,L57,L58,L59) -> 15
A57: [Bear] | H57: 13 | I57: 13 | J57: 13 | K57: 13 | L57: 13
A58: [Base] | H58: 15 | I58: 15 | J58: 15 | K58: 15 | L58: 15
A59: [Bull] | H59: 16 | I59: 16 | J59: 16 | K59: 16 | L59: 16
A61: Gold on loan % of inventories - ACTIVE | C61: =Schedules!C22 -> 0.39664928 | D61: =Schedules!D22 -> 0.31952484 | E61: =Schedules!E22 -> 0.28035274 | F61: =Schedules!F22 -> 0.27710758 | G61: =Schedules!G22 -> 0.37596799 | H61: =CHOOSE($C$5,H62,H63,H64) -> 0.37 | I61: =CHOOSE($C$5,I62,I63,I64) -> 0.37 | J61: =CHOOSE($C$5,J62,J63,J64) -> 0.37 | K61: =CHOOSE($C$5,K62,K63,K64) -> 0.37 | L61: =CHOOSE($C$5,L62,L63,L64) -> 0.37
A62: [Bear] | H62: 0.33 | I62: 0.33 | J62: 0.33 | K62: 0.33 | L62: 0.33
A63: [Base] | H63: 0.37 | I63: 0.37 | J63: 0.37 | K63: 0.37 | L63: 0.37
A64: [Bull] | H64: 0.38 | I64: 0.38 | J64: 0.38 | K64: 0.38 | L64: 0.38
A66: Interest rate on borrowings (on opening balance) - ACTIVE | C66: =Schedules!C71 -> 0 | D66: =Schedules!D71 -> 0 | E66: =Schedules!E71 -> 0 | F66: =Schedules!F71 -> 0.070298546 | G66: =Schedules!G71 -> 0.059303908 | H66: =CHOOSE($C$5,H67,H68,H69) -> 0.058 | I66: =CHOOSE($C$5,I67,I68,I69) -> 0.058 | J66: =CHOOSE($C$5,J67,J68,J69) -> 0.058 | K66: =CHOOSE($C$5,K67,K68,K69) -> 0.058 | L66: =CHOOSE($C$5,L67,L68,L69) -> 0.058
A67: [Bear] | H67: 0.066 | I67: 0.066 | J67: 0.066 | K67: 0.066 | L67: 0.066
A68: [Base] | H68: 0.058 | I68: 0.058 | J68: 0.058 | K68: 0.058 | L68: 0.058
A69: [Bull] | H69: 0.052 | I69: 0.052 | J69: 0.052 | K69: 0.052 | L69: 0.052
A72: 4. COMMON OPERATIONAL DRIVERS (IDENTICAL ACROSS SCENARIOS)
A73: Receivable days (on revenue) | C73: =Schedules!C9 -> 7.1608389 | D73: =Schedules!D9 -> 6.063093 | E73: =Schedules!E9 -> 7.2737061 | F73: =Schedules!F9 -> 6.4479952 | G73: =Schedules!G9 -> 3.8173639 | H73: 4 | I73: 4 | J73: 4 | K73: 4 | L73: 4
A74: Other current assets % revenue | C74: =Schedules!C14 -> 0.05875204 | D74: =Schedules!D14 -> 0.040468269 | E74: =Schedules!E14 -> 0.045943935 | F74: =Schedules!F14 -> 0.0373991 | G74: =Schedules!G14 -> 0.033750457 | H74: 0.034 | I74: 0.034 | J74: 0.034 | K74: 0.034 | L74: 0.034
A75: Other current liabilities % revenue | C75: =Schedules!C16 -> 0.087607209 | D75: =Schedules!D16 -> 0.08667899 | E75: =Schedules!E16 -> 0.080103359 | F75: =Schedules!F16 -> 0.073458383 | G75: =Schedules!G16 -> 0.071165966 | H75: 0.071 | I75: 0.071 | J75: 0.071 | K75: 0.071 | L75: 0.071
A76: Other financial liabilities % revenue | C76: =Schedules!C18 -> 0.015417202 | D76: =Schedules!D18 -> 0.014097351 | E76: =Schedules!E18 -> 0.013272257 | F76: =Schedules!F18 -> 0.022098716 | G76: =Schedules!G18 -> 0.050305992 | H76: 0.046 | I76: 0.046 | J76: 0.046 | K76: 0.046 | L76: 0.046
A77: Provisions % revenue | C77: =Schedules!C20 -> 0.008194729 | D77: =Schedules!D20 -> 0.009168207 | E77: =Schedules!E20 -> 0.0073212748 | F77: =Schedules!F20 -> 0.0075095938 | G77: =Schedules!G20 -> 0.0080151626 | H77: 0.008 | I77: 0.008 | J77: 0.008 | K77: 0.008 | L77: 0.008
A78: Treasury investments & bank balances % revenue | C78: =Schedules!C79 -> 0.047536373 | D78: =Schedules!D79 -> 0.080714726 | E78: =Schedules!E79 -> 0.054478898 | F78: =Schedules!F79 -> 0.041583962 | G78: =Schedules!G79 -> 0.037598191 | H78: 0.035 | I78: 0.035 | J78: 0.035 | K78: 0.035 | L78: 0.035
A79: Minimum operating cash % revenue (revolver trigger) | C79: =Schedules!C57 -> 0.0076044307 | D79: =Schedules!D57 -> 0.0057178065 | E79: =Schedules!E57 -> 0.0080064208 | F79: =Schedules!F57 -> 0.0067321689 | G79: =Schedules!G57 -> 0.009967574 | H79: 0.01 | I79: 0.01 | J79: 0.01 | K79: 0.01 | L79: 0.01
A80: Effective tax rate | C80: =IS!C26 -> 0.24311295 | D80: =IS!D26 -> 0.26377333 | E80: =IS!E26 -> 0.24378109 | F80: =IS!F26 -> 0.26416759 | G80: =IS!G26 -> 0.25408028 | H80: 0.254 | I80: 0.254 | J80: 0.254 | K80: 0.254 | L80: 0.254
A81: Dividend paid % prior-year PAT | C81: =Schedules!C86 -> 0 | D81: =Schedules!D86 -> 0.30300273 | E81: =Schedules!E86 -> 0.27122786 | F81: =Schedules!F86 -> 0.2791762 | G81: =Schedules!G86 -> 0.29247827 | H81: 0.27 | I81: 0.27 | J81: 0.27 | K81: 0.27 | L81: 0.27
A82: PP&E depreciation % opening PP&E/CWIP/inv. property | C82: =Schedules!C35 -> 0 | D82: =Schedules!D35 -> 0 | E82: =Schedules!E35 -> 0 | F82: =Schedules!F35 -> 0.14895947 | G82: =Schedules!G35 -> 0.16940452 | H82: 0.16 | I82: 0.16 | J82: 0.16 | K82: 0.16 | L82: 0.16
A83: ROU depreciation % opening ROU assets | C83: =Schedules!C41 -> 0 | D83: =Schedules!D41 -> 0 | E83: =Schedules!E41 -> 0 | F83: =Schedules!F41 -> 0.23331173 | G83: =Schedules!G41 -> 0.24069899 | H83: 0.24 | I83: 0.24 | J83: 0.24 | K83: 0.24 | L83: 0.24
A84: Intangible amortisation % opening intangibles | C84: =Schedules!C46 -> 0 | D84: =Schedules!D46 -> 0 | E84: =Schedules!E46 -> 0 | F84: =Schedules!F46 -> 0.19426752 | G84: =Schedules!G46 -> 0.21428571 | H84: 0.12 | I84: 0.12 | J84: 0.12 | K84: 0.12 | L84: 0.12
A85: Share of capex that is intangible | H85: 0.15 | I85: 0.15 | J85: 0.15 | K85: 0.15 | L85: 0.15
A86: New leases (ROU additions) % revenue | C86: =Schedules!C40 -> 0 | D86: =Schedules!D40 -> 0 | E86: =Schedules!E40 -> 0 | F86: =Schedules!F40 -> 0.013398174 | G86: =Schedules!G40 -> 0.012673548 | H86: 0.01 | I86: 0.01 | J86: 0.01 | K86: 0.01 | L86: 0.01
A87: Lease payments % opening lease liability | C87: =Schedules!C65 -> 0 | D87: =Schedules!D65 -> 0.18690213 | E87: =Schedules!E65 -> 0.1697811 | F87: =Schedules!F65 -> 0.29799915 | G87: =Schedules!G65 -> 0.32264081 | H87: 0.32 | I87: 0.32 | J87: 0.32 | K87: 0.32 | L87: 0.32
A88: Lease interest rate (on opening balance) | C88: =Schedules!C64 -> 0 | D88: =Schedules!D64 -> 0 | E88: =Schedules!E64 -> 0 | F88: =Schedules!F64 -> 0.094508301 | G88: =Schedules!G64 -> 0.092129802 | H88: 0.09 | I88: 0.09 | J88: 0.09 | K88: 0.09 | L88: 0.09
A89: Gold-on-loan interest rate (on opening balance) | C89: =Schedules!C72 -> 0 | D89: =Schedules!D72 -> 0 | E89: =Schedules!E72 -> 0 | F89: =Schedules!F72 -> 0.032578169 | G89: =Schedules!G72 -> 0.040973111 | H89: 0.029 | I89: 0.029 | J89: 0.029 | K89: 0.029 | L89: 0.029
A90: Other income yield on opening cash + treasury + NC investments | C90: =Schedules!C81 -> 0 | D90: =Schedules!D81 -> 0.16497054 | E90: =Schedules!E81 -> 0.13815448 | F90: =Schedules!F81 -> 0.12554895 | G90: =Schedules!G81 -> 0.15453527 | H90: 0.09 | I90: 0.09 | J90: 0.09 | K90: 0.09 | L90: 0.09
A91: Scheduled repayment of long-term borrowings (INR cr) | H91: 93 | I91: 0 | J91: 0 | K91: 0 | L91: 0

Sheet IS
A1: CONSOLIDATED STATEMENT OF PROFIT & LOSS
A2: Historical audited financials (FY22A-FY26A) & driver-based projections (FY27E-FY31E)
A4: Line Item (INR crore unless stated) | B4: Unit | C4: FY22A | D4: FY23A | E4: FY24A | F4: FY25A | G4: FY26A | H4: FY27E | I4: FY28E | J4: FY29E | K4: FY30E | L4: FY31E
A5: Revenue from operations | C5: =Hist_Data!C6 -> 28799 | D5: =Hist_Data!D6 -> 40575 | E5: =Hist_Data!E6 -> 51084 | F5: =Hist_Data!F6 -> 60456 | G5: =Hist_Data!G6 -> 87584 | H5: =G5*(1+H6) -> 103349.12 | I5: =H5*(1+I6) -> 118851.49 | J5: =I5*(1+J6) -> 134302.18 | K5: =J5*(1+K6) -> 150418.44 | L5: =K5*(1+L6) -> 166964.47
A6: y/y revenue growth rate | B6: % | D6: =D5/C5-1 -> 0.40890309 | E6: =E5/D5-1 -> 0.25900185 | F6: =F5/E5-1 -> 0.18346253 | G6: =G5/F5-1 -> 0.44872304 | H6: =Inputs!H26 -> 0.18 | I6: =Inputs!I26 -> 0.15 | J6: =Inputs!J26 -> 0.13 | K6: =Inputs!K26 -> 0.12 | L6: =Inputs!L26 -> 0.11
A7: Cost of goods sold (raw material, purchases, inventory change) | C7: =Hist_Data!C9+Hist_Data!C10+Hist_Data!C11 -> 21641 | D7: =Hist_Data!D9+Hist_Data!D10+Hist_Data!D11 -> 30355 | E7: =Hist_Data!E9+Hist_Data!E10+Hist_Data!E11 -> 39432 | F7: =Hist_Data!F9+Hist_Data!F10+Hist_Data!F11 -> 47456 | G7: =Hist_Data!G9+Hist_Data!G10+Hist_Data!G11 -> 70307 | H7: =H5*(1-H9) -> 82989.343 | I7: =I5*(1-I9) -> 95318.893 | J7: =J5*(1-J9) -> 107576.05 | K7: =K5*(1-K9) -> 120334.75 | L7: =L5*(1-L9) -> 133571.58
A8: Gross profit | C8: =C5-C7 -> 7158 | D8: =D5-D7 -> 10220 | E8: =E5-E7 -> 11652 | F8: =F5-F7 -> 13000 | G8: =G5-G7 -> 17277 | H8: =H5-H7 -> 20359.777 | I8: =I5-I7 -> 23532.595 | J8: =J5-J7 -> 26726.134 | ... L8: =L5-L7 -> 33392.894
A9: gross margin | B9: % | C9: =C8/C5 -> 0.2485503 | D9: =D8/D5 -> 0.25187924 | E9: =E8/E5 -> 0.2280949 | F9: =F8/F5 -> 0.21503242 | G9: =G8/G5 -> 0.19726206 | H9: =Inputs!H31 -> 0.197 | I9: =Inputs!I31 -> 0.198 | J9: =Inputs!J31 -> 0.199 | K9: =Inputs!K31 -> 0.2 | L9: =Inputs!L31 -> 0.2
A10: Employee benefits expense | C10: =Hist_Data!C12 -> 1349 | D10: =Hist_Data!D12 -> 1647 | E10: =Hist_Data!E12 -> 1864 | F10: =Hist_Data!F12 -> 2156 | G10: =Hist_Data!G12 -> 2681 | H10: =H5*H11 -> 3100.4736 | I10: =I5*I11 -> 3506.1189 | J10: =J5*J11 -> 3894.7633 | K10: =K5*K11 -> 4362.1349 | L10: =L5*L11 -> 4758.4875
A11: employee cost % revenue | B11: % | C11: =C10/C5 -> 0.046841904 | D11: =D10/D5 -> 0.040591497 | E11: =E10/E5 -> 0.03648892 | F11: =F10/F5 -> 0.0356623 | G11: =G10/G5 -> 0.030610614 | H11: =Inputs!H36 -> 0.03 | I11: =Inputs!I36 -> 0.0295 | J11: =Inputs!J36 -> 0.029 | K11: =Inputs!K36 -> 0.029 | L11: =Inputs!L36 -> 0.0285
A12: Other operating expenses | C12: =Hist_Data!C15 -> 2468 | D12: =Hist_Data!D15 -> 3694 | E12: =Hist_Data!E15 -> 4496 | F12: =Hist_Data!F15 -> 5150 | G12: =Hist_Data!G15 -> 6241 | H12: =H5*H13 -> 7337.7875 | I12: =I5*I13 -> 8379.0299 | J12: =J5*J13 -> 9401.1527 | K12: =K5*K13 -> 10529.291 | L12: =L5*L13 -> 11604.031
A13: other expenses % revenue | B13: % | C13: =C12/C5 -> 0.08569742 | D13: =D12/D5 -> 0.091041282 | E13: =E12/E5 -> 0.088011902 | F13: =F12/F5 -> 0.08518592 | G13: =G12/G5 -> 0.071257307 | H13: =Inputs!H41 -> 0.071 | I13: =Inputs!I41 -> 0.0705 | J13: =Inputs!J41 -> 0.07 | K13: =Inputs!K41 -> 0.07 | L13: =Inputs!L41 -> 0.0695
A14: Operating EBITDA (excl. other income) | C14: =C8-C10-C12 -> 3341 | D14: =D8-D10-D12 -> 4879 | E14: =E8-E10-E12 -> 5292 | F14: =F8-F10-F12 -> 5694 | G14: =G8-G10-G12 -> 8355 | H14: =H8-H10-H12 -> 9921.5155 | I14: =I8-I10-I12 -> 11647.446 | J14: =J8-J10-J12 -> 13430.218 | ... L14: =L8-L10-L12 -> 17030.376
A15: EBITDA margin | B15: % | C15: =C14/C5 -> 0.11601097 | D15: =D14/D5 -> 0.12024646 | E15: =E14/E5 -> 0.10359408 | F15: =F14/F5 -> 0.0941842 | G15: =G14/G5 -> 0.095394136 | H15: =H14/H5 -> 0.096 | I15: =I14/I5 -> 0.098 | J15: =J14/J5 -> 0.1 | ... L15: =L14/L5 -> 0.102
A16: Depreciation & amortisation | C16: =Hist_Data!C14 -> 399 | D16: =Hist_Data!D14 -> 441 | E16: =Hist_Data!E14 -> 584 | F16: =Hist_Data!F14 -> 693 | G16: =Hist_Data!G14 -> 826 | H16: =Schedules!H51 -> 1135.56 | I16: =Schedules!I51 -> 1356.1919 | J16: =Schedules!J51 -> 1597.8885 | K16: =Schedules!K51 -> 1856.5236 | L16: =Schedules!L51 -> 2131.8287
A17: Operating EBIT (operating profit) | C17: =C14-C16 -> 2942 | D17: =D14-D16 -> 4438 | E17: =E14-E16 -> 4708 | F17: =F14-F16 -> 5001 | G17: =G14-G16 -> 7529 | H17: =H14-H16 -> 8785.9555 | I17: =I14-I16 -> 10291.254 | J17: =J14-J16 -> 11832.33 | ... L17: =L14-L16 -> 14898.547
A18: EBIT margin | B18: % | C18: =C17/C5 -> 0.10215632 | D18: =D17/D5 -> 0.1093777 | E18: =E17/E5 -> 0.092161929 | F18: =F17/F5 -> 0.082721318 | G18: =G17/G5 -> 0.08596319 | H18: =H17/H5 -> 0.085012388 | I18: =I17/I5 -> 0.086589189 | J18: =J17/J5 -> 0.088102289 | ... L18: =L17/L5 -> 0.089231843
A20: Other income | C20: =Hist_Data!C7 -> 234 | D20: =Hist_Data!D7 -> 308 | E20: =Hist_Data!E7 -> 533 | F20: =Hist_Data!F7 -> 486 | G20: =Hist_Data!G7 -> 552 | H20: =Schedules!H83 -> 488.07 | I20: =Schedules!I83 -> 531.69394 | J20: =Schedules!J83 -> 594.47853 | K20: =Schedules!K83 -> 657.05383 | L20: =Schedules!L83 -> 722.3247
A21: Finance costs | C21: =Hist_Data!C13 -> 218 | D21: =Hist_Data!D13 -> 300 | E21: =Hist_Data!E13 -> 619 | F21: =Hist_Data!F13 -> 953 | G21: =Hist_Data!G13 -> 1180 | H21: =Schedules!H75 -> 1411.524 | I21: =Schedules!I75 -> 1527.7601 | J21: =Schedules!J75 -> 1593.2602 | K21: =Schedules!K75 -> 1614.9295 | L21: =Schedules!L75 -> 1606.8726
A22: Share of profit of associate / JV | C22: =Hist_Data!C18 -> 0 | D22: =Hist_Data!D18 -> 1 | E22: =Hist_Data!E18 -> 1 | F22: =Hist_Data!F18 -> 1 | G22: =Hist_Data!G18 -> 1 | H22: 0 | I22: 0 | J22: 0 | K22: 0 | L22: 0
A23: Exceptional items | C23: =Hist_Data!C20 -> 54 | D23: =Hist_Data!D20 -> 0 | E23: =Hist_Data!E20 -> 0 | F23: =Hist_Data!F20 -> 0 | G23: =Hist_Data!G20 -> 101 | H23: 0 | I23: 0 | J23: 0 | K23: 0 | L23: 0
A24: Profit before tax (PBT) | C24: =C17+C20-C21+C22-C23 -> 2904 | D24: =D17+D20-D21+D22-D23 -> 4447 | E24: =E17+E20-E21+E22-E23 -> 4623 | F24: =F17+F20-F21+F22-F23 -> 4535 | G24: =G17+G20-G21+G22-G23 -> 6801 | H24: =H17+H20-H21+H22-H23 -> 7862.5015 | I24: =I17+I20-I21+I22-I23 -> 9295.1878 | J24: =J17+J20-J21+J22-J23 -> 10833.548 | ... L24: =L17+L20-L21+L22-L23 -> 14014
A25: Income tax expense | C25: =Hist_Data!C24 -> 706 | D25: =Hist_Data!D24 -> 1173 | E25: =Hist_Data!E24 -> 1127 | F25: =Hist_Data!F24 -> 1198 | G25: =Hist_Data!G24 -> 1728 | H25: =MAX(0,H24)*Inputs!H80 -> 1997.0754 | I25: =MAX(0,I24)*Inputs!I80 -> 2360.9777 | J25: =MAX(0,J24)*Inputs!J80 -> 2751.7212 | K25: =MAX(0,K24)*Inputs!K80 -> 3143.9773 | L25: =MAX(0,L24)*Inputs!L80 -> 3559.5559
A26: effective tax rate | B26: % | C26: =C25/C24 -> 0.24311295 | D26: =D25/D24 -> 0.26377333 | E26: =E25/E24 -> 0.24378109 | F26: =F25/F24 -> 0.26416759 | G26: =G25/G24 -> 0.25408028 | H26: =H25/H24 -> 0.254 | I26: =I25/I24 -> 0.254 | J26: =J25/J24 -> 0.254 | ... L26: =L25/L24 -> 0.254
A27: Profit for the year (PAT) | C27: =C24-C25 -> 2198 | D27: =D24-D25 -> 3274 | E27: =E24-E25 -> 3496 | F27: =F24-F25 -> 3337 | G27: =G24-G25 -> 5073 | H27: =H24-H25 -> 5865.4261 | I27: =I24-I25 -> 6934.2101 | J27: =J24-J25 -> 8081.8267 | ... L27: =L24-L25 -> 10454.444
A28: PAT margin | B28: % | C28: =C27/C5 -> 0.076322095 | D28: =D27/D5 -> 0.08069008 | E28: =E27/E5 -> 0.068436301 | F28: =F27/F5 -> 0.055197168 | G28: =G27/G5 -> 0.057921538 | H28: =H27/H5 -> 0.056753518 | I28: =I27/I5 -> 0.058343486 | J28: =J27/J5 -> 0.060176437 | ... L28: =L27/L5 -> 0.06261478
A30: Diluted weighted shares (crore) | B30: cr | C30: =Inputs!$C$10 -> 88.78 | D30: =Inputs!$C$10 -> 88.78 | E30: =Inputs!$C$10 -> 88.78 | F30: =Inputs!$C$10 -> 88.78 | G30: =Inputs!$C$10 -> 88.78 | H30: =Inputs!$C$10 -> 88.78 | I30: =Inputs!$C$10 -> 88.78 | J30: =Inputs!$C$10 -> 88.78 | ... L30: =Inputs!$C$10 -> 88.78
A31: Basic & Diluted EPS (INR) | B31: INR | C31: =C27/C30 -> 24.757828 | D31: =D27/D30 -> 36.877675 | E31: =E27/E30 -> 39.378238 | F31: =F27/F30 -> 37.587294 | G31: =G27/G30 -> 57.141248 | H31: =H27/H30 -> 66.066976 | I31: =I27/I30 -> 78.105543 | J31: =J27/J30 -> 91.032065 | ... L31: =L27/L30 -> 117.75674

Sheet BS
A1: CONSOLIDATED BALANCE SHEET
A2: Grouped assets and liabilities; cash flows tie directly to cash balance, zero artificial plug
A4: Line Item (INR crore unless stated) | B4: Unit | C4: FY22A | D4: FY23A | E4: FY24A | F4: FY25A | G4: FY26A | H4: FY27E | I4: FY28E | J4: FY29E | K4: FY30E | L4: FY31E
A5: I. ASSETS
A6: PP&E, CWIP & Investment property | C6: =Hist_Data!C28+Hist_Data!C29+Hist_Data!C31 -> 1288 | D6: =Hist_Data!D28+Hist_Data!D29+Hist_Data!D31 -> 1477 | E6: =Hist_Data!E28+Hist_Data!E29+Hist_Data!E31 -> 1826 | F6: =Hist_Data!F28+Hist_Data!F29+Hist_Data!F31 -> 1948 | G6: =Hist_Data!G28+Hist_Data!G29+Hist_Data!G31 -> 2955 | H6: =Schedules!H39 -> 3536.361 | I6: =Schedules!I39 -> 4182.8284 | J6: =Schedules!J39 -> 4883.4581 | K6: =Schedules!K39 -> 5636.373 | L6: =Schedules!L39 -> 6437.5909
A7: Right-of-use assets (Ind AS 116) | C7: =Hist_Data!C30 -> 973 | D7: =Hist_Data!D30 -> 1285 | E7: =Hist_Data!E30 -> 1543 | F7: =Hist_Data!F30 -> 1774 | G7: =Hist_Data!G30 -> 2195 | H7: =Schedules!H45 -> 2701.6912 | I7: =Schedules!I45 -> 3241.8002 | J7: =Schedules!J45 -> 3806.79 | K7: =Schedules!K45 -> 4397.3448 | L7: =Schedules!L45 -> 5011.6268
A8: Goodwill | C8: =Hist_Data!C32 -> 123 | D8: =Hist_Data!D32 -> 123 | E8: =Hist_Data!E32 -> 123 | F8: =Hist_Data!F32 -> 123 | G8: =Hist_Data!G32 -> 758 | H8: =G8 -> 758 | I8: =H8 -> 758 | J8: =I8 -> 758 | K8: =J8 -> 758 | L8: =K8 -> 758
A9: Other intangible assets | C9: =Hist_Data!C33+Hist_Data!C34 -> 245 | D9: =Hist_Data!D33+Hist_Data!D34 -> 257 | E9: =Hist_Data!E33+Hist_Data!E34 -> 314 | F9: =Hist_Data!F33+Hist_Data!F34 -> 322 | G9: =Hist_Data!G33+Hist_Data!G34 -> 1133 | H9: =Schedules!H50 -> 1183.0684 | I9: =Schedules!I50 -> 1255.0329 | J9: =Schedules!J50 -> 1346.1729 | K9: =Schedules!K50 -> 1455.3853 | L9: =Schedules!L50 -> 1581.2751
A10: Non-current investments | C10: =Hist_Data!C35+Hist_Data!C36 -> 279 | D10: =Hist_Data!D35+Hist_Data!D36 -> 351 | E10: =Hist_Data!E35+Hist_Data!E36 -> 679 | F10: =Hist_Data!F35+Hist_Data!F36 -> 651 | G10: =Hist_Data!G35+Hist_Data!G36 -> 1257 | H10: =G10 -> 1257 | I10: =H10 -> 1257 | J10: =I10 -> 1257 | K10: =J10 -> 1257 | L10: =K10 -> 1257
A11: Other non-current assets | C11: =Hist_Data!C37+Hist_Data!C38+Hist_Data!C39+Hist_Data!C40+Hist_Data!C41 -> 832 | D11: =Hist_Data!D37+Hist_Data!D38+Hist_Data!D39+Hist_Data!D40+Hist_Data!D41 -> 1123 | E11: =Hist_Data!E37+Hist_Data!E38+Hist_Data!E39+Hist_Data!E40+Hist_Data!E41 -> 1457 | F11: =Hist_Data!F37+Hist_Data!F38+Hist_Data!F39+Hist_Data!F40+Hist_Data!F41 -> 1395 | G11: =Hist_Data!G37+Hist_Data!G38+Hist_Data!G39+Hist_Data!G40+Hist_Data!G41 -> 1482 | H11: =G11 -> 1482 | I11: =H11 -> 1482 | J11: =I11 -> 1482 | K11: =J11 -> 1482 | L11: =K11 -> 1482
A12: Total non-current assets | C12: =SUM(C6:C11) -> 3740 | D12: =SUM(D6:D11) -> 4616 | E12: =SUM(E6:E11) -> 5942 | F12: =SUM(F6:F11) -> 6213 | G12: =SUM(G6:G11) -> 9780 | H12: =SUM(H6:H11) -> 10918.121 | I12: =SUM(I6:I11) -> 12176.662 | J12: =SUM(J6:J11) -> 13533.421 | ... L12: =SUM(L6:L11) -> 16527.493
A13: Inventories | C13: =Hist_Data!C42 -> 13609 | D13: =Hist_Data!D42 -> 16584 | E13: =Hist_Data!E42 -> 19051 | F13: =Hist_Data!F42 -> 28184 | G13: =Hist_Data!G42 -> 42743 | H13: =Schedules!H11 -> 50020.974 | I13: =Schedules!I11 -> 57452.484 | J13: =Schedules!J11 -> 64840.357 | K13: =Schedules!K11 -> 72530.537 | L13: =Schedules!L11 -> 80508.896
A14: Trade receivables | C14: =Hist_Data!C44 -> 565 | D14: =Hist_Data!D44 -> 674 | E14: =Hist_Data!E44 -> 1018 | F14: =Hist_Data!F44 -> 1068 | G14: =Hist_Data!G44 -> 916 | H14: =Schedules!H12 -> 1132.5931 | I14: =Schedules!I12 -> 1302.4821 | J14: =Schedules!J12 -> 1471.8047 | K14: =Schedules!K12 -> 1648.4213 | L14: =Schedules!L12 -> 1829.7476
A15: Other current assets | C15: =Hist_Data!C47+Hist_Data!C48+Hist_Data!C49+Hist_Data!C50 -> 1692 | D15: =Hist_Data!D47+Hist_Data!D48+Hist_Data!D49+Hist_Data!D50 -> 1642 | E15: =Hist_Data!E47+Hist_Data!E48+Hist_Data!E49+Hist_Data!E50 -> 2347 | F15: =Hist_Data!F47+Hist_Data!F48+Hist_Data!F49+Hist_Data!F50 -> 2261 | G15: =Hist_Data!G47+Hist_Data!G48+Hist_Data!G49+Hist_Data!G50 -> 2956 | H15: =Schedules!H15 -> 3513.8701 | I15: =Schedules!I15 -> 4040.9506 | J15: =Schedules!J15 -> 4566.2742 | K15: =Schedules!K15 -> 5114.2271 | L15: =Schedules!L15 -> 5676.792
A16: Treasury investments & bank balances | C16: =Hist_Data!C43+Hist_Data!C46 -> 1369 | D16: =Hist_Data!D43+Hist_Data!D46 -> 3275 | E16: =Hist_Data!E43+Hist_Data!E46 -> 2783 | F16: =Hist_Data!F43+Hist_Data!F46 -> 2514 | G16: =Hist_Data!G43+Hist_Data!G46 -> 3293 | H16: =Schedules!H80 -> 3617.2192 | I16: =Schedules!I80 -> 4159.8021 | J16: =Schedules!J80 -> 4700.5764 | K16: =Schedules!K80 -> 5264.6455 | L16: =Schedules!L80 -> 5843.7565
A17: Cash & cash equivalents | C17: =Hist_Data!C45 -> 219 | D17: =Hist_Data!D45 -> 232 | E17: =Hist_Data!E45 -> 409 | F17: =Hist_Data!F45 -> 407 | G17: =Hist_Data!G45 -> 873 | H17: =CF!H34 -> 1033.4912 | I17: =CF!I34 -> 1188.5149 | J17: =CF!J34 -> 1343.0218 | K17: =CF!K34 -> 1504.1844 | L17: =CF!L34 -> 1669.6447
A18: Total current assets | C18: =SUM(C13:C17) -> 17454 | D18: =SUM(D13:D17) -> 22407 | E18: =SUM(E13:E17) -> 25608 | F18: =SUM(F13:F17) -> 34434 | G18: =SUM(G13:G17) -> 50781 | H18: =SUM(H13:H17) -> 59318.148 | I18: =SUM(I13:I17) -> 68144.233 | J18: =SUM(J13:J17) -> 76922.034 | ... L18: =SUM(L13:L17) -> 95528.837
A19: TOTAL ASSETS | C19: =C12+C18 -> 21194 | D19: =D12+D18 -> 27023 | E19: =E12+E18 -> 31550 | F19: =F12+F18 -> 40647 | G19: =G12+G18 -> 60561 | H19: =H12+H18 -> 70236.268 | I19: =I12+I18 -> 80320.895 | J19: =J12+J18 -> 90455.455 | ... L19: =L12+L18 -> 112056.33
A21: II. EQUITY & LIABILITIES
A22: Equity share capital | C22: =Hist_Data!C51 -> 89 | D22: =Hist_Data!D51 -> 89 | E22: =Hist_Data!E51 -> 89 | F22: =Hist_Data!F51 -> 89 | G22: =Hist_Data!G51 -> 89 | H22: =G22 -> 89 | I22: =H22 -> 89 | J22: =I22 -> 89 | K22: =J22 -> 89 | L22: =K22 -> 89
A23: Other equity (reserves & surplus) | C23: =Hist_Data!C52+Hist_Data!C53 -> 9244 | D23: =Hist_Data!D52+Hist_Data!D53 -> 11815 | E23: =Hist_Data!E52+Hist_Data!E53 -> 9304 | F23: =Hist_Data!F52+Hist_Data!F53 -> 11535 | G23: =Hist_Data!G52+Hist_Data!G53 -> 15614 | H23: =Schedules!H90 -> 20109.716 | I23: =Schedules!I90 -> 25460.261 | J23: =Schedules!J90 -> 31669.851 | K23: =Schedules!K90 -> 38721.644 | L23: =Schedules!L90 -> 46682.939
A24: Total equity | C24: =C22+C23 -> 9333 | D24: =D22+D23 -> 11904 | E24: =E22+E23 -> 9393 | F24: =F22+F23 -> 11624 | G24: =G22+G23 -> 15703 | H24: =H22+H23 -> 20198.716 | I24: =I22+I23 -> 25549.261 | J24: =J22+J23 -> 31758.851 | ... L24: =L22+L23 -> 46771.939
A25: Borrowings (term debt & credit facility) | C25: =Hist_Data!C54+Hist_Data!C60 -> 518 | D25: =Hist_Data!D54+Hist_Data!D60 -> 2195 | E25: =Hist_Data!E54+Hist_Data!E60 -> 7838 | F25: =Hist_Data!F54+Hist_Data!F60 -> 10286 | G25: =Hist_Data!G54+Hist_Data!G60 -> 11378 | H25: =Schedules!H63 -> 11691.93 | I25: =Schedules!I63 -> 10842.989 | J25: =Schedules!J63 -> 9145.4514 | K25: =Schedules!K63 -> 6791.3958 | L25: =Schedules!L63 -> 3715.391
A26: Gold on loan | C26: =Hist_Data!C61 -> 5398 | D26: =Hist_Data!D61 -> 5299 | E26: =Hist_Data!E61 -> 5341 | F26: =Hist_Data!F61 -> 7810 | G26: =Hist_Data!G61 -> 16070 | H26: =Schedules!H23 -> 18507.76 | I26: =Schedules!I23 -> 21257.419 | J26: =Schedules!J23 -> 23990.932 | K26: =Schedules!K23 -> 26836.299 | L26: =Schedules!L23 -> 29788.292
A27: Lease liabilities (non-current + current) | C27: =Hist_Data!C55+Hist_Data!C62 -> 1359 | D27: =Hist_Data!D55+Hist_Data!D62 -> 1873 | E27: =Hist_Data!E55+Hist_Data!E62 -> 2349 | F27: =Hist_Data!F55+Hist_Data!F62 -> 2681 | G27: =Hist_Data!G55+Hist_Data!G62 -> 3173 | H27: =Schedules!H70 -> 3476.7012 | I27: =Schedules!I70 -> 3865.5748 | J27: =Schedules!J70 -> 4319.5144 | K27: =Schedules!K70 -> 4830.2105 | L27: =Schedules!L70 -> 5388.9068
A28: Trade payables | C28: =Hist_Data!C63+Hist_Data!C64 -> 1294 | D28: =Hist_Data!D63+Hist_Data!D64 -> 1214 | E28: =Hist_Data!E63+Hist_Data!E64 -> 1410 | F28: =Hist_Data!F63+Hist_Data!F64 -> 1963 | G28: =Hist_Data!G63+Hist_Data!G64 -> 2864 | H28: =Schedules!H13 -> 3410.521 | I28: =Schedules!I13 -> 3917.2148 | J28: =Schedules!J13 -> 4420.9335 | K28: =Schedules!K13 -> 4945.2639 | L28: =Schedules!L13 -> 5489.2429
A29: Other financial liabilities | C29: =Hist_Data!C56+Hist_Data!C65 -> 444 | D29: =Hist_Data!D56+Hist_Data!D65 -> 572 | E29: =Hist_Data!E56+Hist_Data!E65 -> 678 | F29: =Hist_Data!F56+Hist_Data!F65 -> 1336 | G29: =Hist_Data!G56+Hist_Data!G65 -> 4406 | H29: =Schedules!H19 -> 4754.0595 | I29: =Schedules!I19 -> 5467.1684 | J29: =Schedules!J19 -> 6177.9003 | K29: =Schedules!K19 -> 6919.2484 | L29: =Schedules!L19 -> 7680.3657
A30: Other current liabilities | C30: =Hist_Data!C66 -> 2523 | D30: =Hist_Data!D66 -> 3517 | E30: =Hist_Data!E66 -> 4092 | F30: =Hist_Data!F66 -> 4441 | G30: =Hist_Data!G66 -> 6233 | H30: =Schedules!H17 -> 7337.7875 | I30: =Schedules!I17 -> 8438.4556 | J30: =Schedules!J17 -> 9535.4549 | K30: =Schedules!K17 -> 10679.709 | L30: =Schedules!L17 -> 11854.478
A31: Provisions (non-current & current) | C31: =Hist_Data!C57+Hist_Data!C67 -> 236 | D31: =Hist_Data!D57+Hist_Data!D67 -> 372 | E31: =Hist_Data!E57+Hist_Data!E67 -> 374 | F31: =Hist_Data!F57+Hist_Data!F67 -> 454 | G31: =Hist_Data!G57+Hist_Data!G67 -> 702 | H31: =Schedules!H21 -> 826.79296 | I31: =Schedules!I21 -> 950.8119 | J31: =Schedules!J21 -> 1074.4175 | K31: =Schedules!K21 -> 1203.3475 | L31: =Schedules!L21 -> 1335.7158
A32: Other liabilities (tax & deferred) | C32: =Hist_Data!C58+Hist_Data!C59+Hist_Data!C68+Hist_Data!C69 -> 89 | D32: =Hist_Data!D58+Hist_Data!D59+Hist_Data!D68+Hist_Data!D69 -> 77 | E32: =Hist_Data!E58+Hist_Data!E59+Hist_Data!E68+Hist_Data!E69 -> 75 | F32: =Hist_Data!F58+Hist_Data!F59+Hist_Data!F68+Hist_Data!F69 -> 52 | G32: =Hist_Data!G58+Hist_Data!G59+Hist_Data!G68+Hist_Data!G69 -> 32 | H32: =G32 -> 32 | I32: =H32 -> 32 | J32: =I32 -> 32 | K32: =J32 -> 32 | L32: =K32 -> 32
A33: Total liabilities | C33: =SUM(C25:C32) -> 11861 | D33: =SUM(D25:D32) -> 15119 | E33: =SUM(E25:E32) -> 22157 | F33: =SUM(F25:F32) -> 29023 | G33: =SUM(G25:G32) -> 44858 | H33: =SUM(H25:H32) -> 50037.552 | I33: =SUM(I25:I32) -> 54771.634 | J33: =SUM(J25:J32) -> 58696.604 | ... L33: =SUM(L25:L32) -> 65284.391
A34: TOTAL EQUITY & LIABILITIES | C34: =C24+C33 -> 21194 | D34: =D24+D33 -> 27023 | E34: =E24+E33 -> 31550 | F34: =F24+F33 -> 40647 | G34: =G24+G33 -> 60561 | H34: =H24+H33 -> 70236.268 | I34: =I24+I33 -> 80320.895 | J34: =J24+J33 -> 90455.455 | ... L34: =L24+L33 -> 112056.33
A36: Balance check: Assets - Liabilities & Equity (must be 0.00) | C36: =ROUND(C19-C34,2) -> 0 | D36: =ROUND(D19-D34,2) -> 0 | E36: =ROUND(E19-E34,2) -> 0 | F36: =ROUND(F19-F34,2) -> 0 | G36: =ROUND(G19-G34,2) -> 0 | H36: =ROUND(H19-H34,2) -> 0 | I36: =ROUND(I19-I34,2) -> 0 | J36: =ROUND(J19-J34,2) -> 0 | ... L36: =ROUND(L19-L34,2) -> 0

Sheet CF
A1: CONSOLIDATED CASH FLOW STATEMENT
A2: Ind AS indirect cash flow statement with explicit Ind AS 116 retail lease & gold-on-loan handling
A4: Line Item (INR crore unless stated) | B4: Unit | C4: FY22A | D4: FY23A | E4: FY24A | F4: FY25A | G4: FY26A | H4: FY27E | I4: FY28E | J4: FY29E | K4: FY30E | L4: FY31E
A5: Profit before tax (PBT) | C5: =IS!C24 -> 2904 | D5: =IS!D24 -> 4447 | E5: =IS!E24 -> 4623 | F5: =IS!F24 -> 4535 | G5: =IS!G24 -> 6801 | H5: =IS!H24 -> 7862.5015 | I5: =IS!I24 -> 9295.1878 | J5: =IS!J24 -> 10833.548 | ... L5: =IS!L24 -> 14014
A6: Add: Depreciation & amortisation | C6: =IS!C16 -> 399 | D6: =IS!D16 -> 441 | E6: =IS!E16 -> 584 | F6: =IS!F16 -> 693 | G6: =IS!G16 -> 826 | H6: =IS!H16 -> 1135.56 | I6: =IS!I16 -> 1356.1919 | J6: =IS!J16 -> 1597.8885 | ... L6: =IS!L16 -> 2131.8287
A7: Add: Finance costs | C7: =IS!C21 -> 218 | D7: =IS!D21 -> 300 | E7: =IS!E21 -> 619 | F7: =IS!F21 -> 953 | G7: =IS!G21 -> 1180 | H7: =IS!H21 -> 1411.524 | I7: =IS!I21 -> 1527.7601 | J7: =IS!J21 -> 1593.2602 | ... L7: =IS!L21 -> 1606.8726
A8: Other non-cash & non-operating adjustments | C8: =Hist_Data!C94-C5-C6-C7-C10-C11-C12-C13-C14-C15-C16 -> -222 | D8: =Hist_Data!D94-D5-D6-D7-D10-D11-D12-D13-D14-D15-D16 -> -251 | E8: =Hist_Data!E94-E5-E6-E7-E10-E11-E12-E13-E14-E15-E16 -> -422 | F8: =Hist_Data!F94-F5-F6-F7-F10-F11-F12-F13-F14-F15-F16 -> -407 | G8: =Hist_Data!G94-G5-G6-G7-G10-G11-G12-G13-G14-G15-G16 -> -360 | H8: =-IS!H20-IS!H22 -> -488.07 | I8: =-IS!I20-IS!I22 -> -531.69394 | J8: =-IS!J20-IS!J22 -> -594.47853 | K8: =-IS!K20-IS!K22 -> -657.05383 | L8: =-IS!L20-IS!L22 -> -722.3247
A9: Operating cash profit before working capital changes | C9: =SUM(C5:C8) -> 3299 | D9: =SUM(D5:D8) -> 4937 | E9: =SUM(E5:E8) -> 5404 | F9: =SUM(F5:F8) -> 5774 | G9: =SUM(G5:G8) -> 8447 | H9: =SUM(H5:H8) -> 9921.5155 | I9: =SUM(I5:I8) -> 11647.446 | J9: =SUM(J5:J8) -> 13430.218 | ... L9: =SUM(L5:L8) -> 17030.376
A10: (Increase) / decrease in trade receivables | C10: =Hist_Data!C83 -> -207 | D10: =Hist_Data!D83 -> -112 | E10: =Hist_Data!E83 -> -348 | F10: =Hist_Data!F83 -> -95 | G10: =Hist_Data!G83 -> 210 | H10: =-(BS!H14-BS!G14) -> -216.5931 | I10: =-(BS!I14-BS!H14) -> -169.88896 | J10: =-(BS!J14-BS!I14) -> -169.32267 | K10: =-(BS!K14-BS!J14) -> -176.61657 | L10: =-(BS!L14-BS!K14) -> -181.32634
A11: (Increase) / decrease in inventories | C11: =Hist_Data!C84 -> -5199 | D11: =Hist_Data!D84 -> -2977 | E11: =Hist_Data!E84 -> -2462 | F11: =Hist_Data!F84 -> -9072 | G11: =Hist_Data!G84 -> -11592 | H11: =-(BS!H13-BS!G13) -> -7277.9741 | I11: =-(BS!I13-BS!H13) -> -7431.5096 | J11: =-(BS!J13-BS!I13) -> -7387.8736 | K11: =-(BS!K13-BS!J13) -> -7690.1797 | L11: =-(BS!L13-BS!K13) -> -7978.3591
A12: (Increase) / decrease in other operating assets | C12: =Hist_Data!C85+Hist_Data!C86+Hist_Data!C87 -> -255 | D12: =Hist_Data!D85+Hist_Data!D86+Hist_Data!D87 -> -307 | E12: =Hist_Data!E85+Hist_Data!E86+Hist_Data!E87 -> -632 | F12: =Hist_Data!F85+Hist_Data!F86+Hist_Data!F87 -> -156 | G12: =Hist_Data!G85+Hist_Data!G86+Hist_Data!G87 -> -469 | H12: =-(BS!H15-BS!G15) -> -557.87008 | I12: =-(BS!I15-BS!H15) -> -527.08051 | J12: =-(BS!J15-BS!I15) -> -525.32358 | K12: =-(BS!K15-BS!J15) -> -547.9529 | L12: =-(BS!L15-BS!K15) -> -562.56498
A13: Increase / (decrease) in gold on loan | C13: =Hist_Data!C88 -> 1188 | D13: =Hist_Data!D88 -> -99 | E13: =Hist_Data!E88 -> 42 | F13: =Hist_Data!F88 -> 2468 | G13: =Hist_Data!G88 -> 7304 | H13: =BS!H26-BS!G26 -> 2437.7604 | I13: =BS!I26-BS!H26 -> 2749.6586 | J13: =BS!J26-BS!I26 -> 2733.5132 | K13: =BS!K26-BS!J26 -> 2845.3665 | L13: =BS!L26-BS!K26 -> 2951.9929
A14: Increase / (decrease) in trade payables | C14: =Hist_Data!C89 -> 504 | D14: =Hist_Data!D89 -> -89 | E14: =Hist_Data!E89 -> 196 | F14: =Hist_Data!F89 -> 564 | G14: =Hist_Data!G89 -> 472 | H14: =BS!H28-BS!G28 -> 546.52096 | I14: =BS!I28-BS!H28 -> 506.69384 | J14: =BS!J28-BS!I28 -> 503.71866 | K14: =BS!K28-BS!J28 -> 524.33043 | L14: =BS!L28-BS!K28 -> 543.97903
A15: Increase / (decrease) in other liabilities & provisions | C15: =Hist_Data!C90+Hist_Data!C91+Hist_Data!C92 -> 748 | D15: =Hist_Data!D90+Hist_Data!D91+Hist_Data!D92 -> 1171 | E15: =Hist_Data!E90+Hist_Data!E91+Hist_Data!E92 -> 668 | F15: =Hist_Data!F90+Hist_Data!F91+Hist_Data!F92 -> 1065 | G15: =Hist_Data!G90+Hist_Data!G91+Hist_Data!G92 -> 2955 | H15: =(BS!H29-BS!G29)+(BS!H30-BS!G30)+(BS!H31-BS!G31)+(BS!H32-BS!G32) -> 1577.64 | I15: =(BS!I29-BS!H29)+(BS!I30-BS!H30)+(BS!I31-BS!H31)+(BS!I32-BS!H32) -> 1937.796 | J15: =(BS!J29-BS!I29)+(BS!J30-BS!I30)+(BS!J31-BS!I31)+(BS!J32-BS!I32) -> 1931.3367 | K15: =(BS!K29-BS!J29)+(BS!K30-BS!J30)+(BS!K31-BS!J31)+(BS!K32-BS!J32) -> 2014.5327 | L15: =(BS!L29-BS!K29)+(BS!L30-BS!K30)+(BS!L31-BS!K31)+(BS!L32-BS!K32) -> 2068.2536
A16: Direct taxes paid | C16: =Hist_Data!C93 -> -802 | D16: =Hist_Data!D93 -> -1154 | E16: =Hist_Data!E93 -> -1173 | F16: =Hist_Data!F93 -> -1089 | G16: =Hist_Data!G93 -> -1737 | H16: =-IS!H25 -> -1997.0754 | I16: =-IS!I25 -> -2360.9777 | J16: =-IS!J25 -> -2751.7212 | K16: =-IS!K25 -> -3143.9773 | L16: =-IS!L25 -> -3559.5559
A17: Cash flow from operations (CFO) | C17: =SUM(C9:C16) -> -724 | D17: =SUM(D9:D16) -> 1370 | E17: =SUM(E9:E16) -> 1695 | F17: =SUM(F9:F16) -> -541 | G17: =SUM(G9:G16) -> 5590 | H17: =SUM(H9:H16) -> 4433.9242 | I17: =SUM(I9:I16) -> 6352.1374 | J17: =SUM(J9:J16) -> 7764.5457 | ... L17: =SUM(L9:L16) -> 10312.795
A19: Capital expenditure (PP&E, CWIP, Intangibles) | C19: =Hist_Data!C95 -> -224 | D19: =Hist_Data!D95 -> -432 | E19: =Hist_Data!E95 -> -691 | F19: =Hist_Data!F95 -> -494 | G19: =Hist_Data!G95 -> -902 | H19: =-Schedules!H32 -> -1240.1894 | I19: =-Schedules!I32 -> -1426.2179 | J19: =-Schedules!J32 -> -1611.6262 | K19: =-Schedules!K32 -> -1805.0213 | L19: =-Schedules!L32 -> -2003.5737
A20: Other investing cash flows (treasury, yield, acquisitions) | C20: =Hist_Data!C96-C19 -> 1388 | D20: =Hist_Data!D96-D19 -> -1379 | E20: =Hist_Data!E96-E19 -> 502 | F20: =Hist_Data!F96-F19 -> 1040 | G20: =Hist_Data!G96-G19 -> -2032 | H20: =-(BS!H16-BS!G16)-(BS!H10-BS!G10)-(BS!H11-BS!G11)-(BS!H8-BS!G8)+IS!H20+IS!H22 -> 163.8508 | I20: =-(BS!I16-BS!H16)-(BS!I10-BS!H10)-(BS!I11-BS!H11)-(BS!I8-BS!H8)+IS!I20+IS!I22 -> -10.888944 | J20: =-(BS!J16-BS!I16)-(BS!J10-BS!I10)-(BS!J11-BS!I11)-(BS!J8-BS!I8)+IS!J20+IS!J22 -> 53.704256 | K20: =-(BS!K16-BS!J16)-(BS!K10-BS!J10)-(BS!K11-BS!J11)-(BS!K8-BS!J8)+IS!K20+IS!K22 -> 92.984673 | L20: =-(BS!L16-BS!K16)-(BS!L10-BS!K10)-(BS!L11-BS!K11)-(BS!L8-BS!K8)+IS!L20+IS!L22 -> 143.21369
A21: Cash flow from investing (CFI) | C21: =C19+C20 -> 1164 | D21: =D19+D20 -> -1811 | E21: =E19+E20 -> -189 | F21: =F19+F20 -> 546 | G21: =G19+G20 -> -2934 | H21: =H19+H20 -> -1076.3386 | I21: =I19+I20 -> -1437.1068 | J21: =J19+J20 -> -1557.9219 | ... L21: =L19+L20 -> -1860.36
A23: Long-term borrowings proceeds / (repayment) | C23: =Hist_Data!C101+Hist_Data!C102 -> -7 | D23: =Hist_Data!D101+Hist_Data!D102 -> -7 | E23: =Hist_Data!E101+Hist_Data!E102 -> 3301 | F23: =Hist_Data!F101+Hist_Data!F102 -> -308 | G23: =Hist_Data!G101+Hist_Data!G102 -> -2632 | H23: =-Schedules!H55 -> -93 | I23: =-Schedules!I55 -> 0 | J23: =-Schedules!J55 -> 0 | K23: =-Schedules!K55 -> 0 | L23: =-Schedules!L55 -> 0
A24: Short-term debt & revolver drawdown / (repayment) | C24: =Hist_Data!C103 -> 349 | D24: =Hist_Data!D103 -> 1684 | E24: =Hist_Data!E103 -> 2328 | F24: =Hist_Data!F103 -> 2529 | G24: =Hist_Data!G103 -> 3314 | H24: =Schedules!H61 -> 406.92959 | I24: =Schedules!I61 -> -848.94054 | J24: =Schedules!J61 -> -1697.5377 | K24: =Schedules!K61 -> -2354.0556 | L24: =Schedules!L61 -> -3076.0048
A25: Dividends paid | C25: =Hist_Data!C104 -> -355 | D25: =Hist_Data!D104 -> -666 | E25: =Hist_Data!E104 -> -888 | F25: =Hist_Data!F104 -> -976 | G25: =Hist_Data!G104 -> -976 | H25: =-Schedules!H89 -> -1369.71 | I25: =-Schedules!I89 -> -1583.6651 | J25: =-Schedules!J89 -> -1872.2367 | K25: =-Schedules!K89 -> -2182.0932 | L25: =-Schedules!L89 -> -2493.1493
A26: Lease liabilities principal & interest repayment | C26: =Hist_Data!C105 -> -172 | D26: =Hist_Data!D105 -> -254 | E26: =Hist_Data!E105 -> -318 | F26: =Hist_Data!F105 -> -700 | G26: =Hist_Data!G105 -> -865 | H26: =-Schedules!H69 -> -1015.36 | I26: =-Schedules!I69 -> -1112.5444 | J26: =-Schedules!J69 -> -1236.9839 | K26: =-Schedules!K69 -> -1382.2446 | L26: =-Schedules!L69 -> -1545.6674
A27: Finance costs paid (borrowings & gold on loan) | C27: =Hist_Data!C106 -> -218 | D27: =Hist_Data!D106 -> -300 | E27: =Hist_Data!E106 -> -619 | F27: =Hist_Data!F106 -> -538 | G27: =Hist_Data!G106 -> -1000 | H27: =-Schedules!H76 -> -1125.954 | I27: =-Schedules!I76 -> -1214.857 | J27: =-Schedules!J76 -> -1245.3585 | K27: =-Schedules!K76 -> -1226.1732 | L27: =-Schedules!L76 -> -1172.1536
A28: Other financing transactions | C28: =Hist_Data!C97-SUM(C23:C27) -> 0 | D28: =Hist_Data!D97-SUM(D23:D27) -> 0 | E28: =Hist_Data!E97-SUM(E23:E27) -> -5133 | F28: =Hist_Data!F97-SUM(F23:F27) -> -14 | G28: =Hist_Data!G97-SUM(G23:G27) -> 0 | H28: 0 | I28: 0 | J28: 0 | K28: 0 | L28: 0
A29: Cash flow from financing (CFF) | C29: =SUM(C23:C28) -> -403 | D29: =SUM(D23:D28) -> 457 | E29: =SUM(E23:E28) -> -1329 | F29: =SUM(F23:F28) -> -7 | G29: =SUM(G23:G28) -> -2159 | H29: =SUM(H23:H28) -> -3197.0944 | I29: =SUM(I23:I28) -> -4760.0069 | J29: =SUM(J23:J28) -> -6052.1168 | ... L29: =SUM(L23:L28) -> -8286.9751
A31: Net change in cash & equivalents | C31: =C17+C21+C29 -> 37 | D31: =D17+D21+D29 -> 16 | E31: =E17+E21+E29 -> 177 | F31: =F17+F21+F29 -> -2 | G31: =G17+G21+G29 -> 497 | H31: =H17+H21+H29 -> 160.4912 | I31: =I17+I21+I29 -> 155.02368 | J31: =J17+J21+J29 -> 154.50693 | ... L31: =L17+L21+L29 -> 165.46029
A32: Opening cash balance | C32: =Hist_Data!C99 -> 181 | D32: =Hist_Data!D99 -> 219 | E32: =Hist_Data!E99 -> 232 | F32: =Hist_Data!F99 -> 409 | G32: =Hist_Data!G99 -> 407 | H32: =G34 -> 873 | I32: =H34 -> 1033.4912 | J32: =I34 -> 1188.5149 | K32: =J34 -> 1343.0218 | L32: =K34 -> 1504.1844
A33: Foreign exchange / other adjustments | C33: =Hist_Data!C100-C32-C31 -> 1 | D33: =Hist_Data!D100-D32-D31 -> -3 | E33: =Hist_Data!E100-E32-E31 -> 0 | F33: =Hist_Data!F100-F32-F31 -> 0 | G33: =Hist_Data!G100-G32-G31 -> -31 | H33: 0 | I33: 0 | J33: 0 | K33: 0 | L33: 0
A34: Closing cash balance | C34: =C32+C31+C33 -> 219 | D34: =D32+D31+D33 -> 232 | E34: =E32+E31+E33 -> 409 | F34: =F32+F31+F33 -> 407 | G34: =G32+G31+G33 -> 873 | H34: =H32+H31+H33 -> 1033.4912 | I34: =I32+I31+I33 -> 1188.5149 | J34: =J32+J31+J33 -> 1343.0218 | ... L34: =L32+L31+L33 -> 1669.6447
A35: Check: Closing cash vs Balance Sheet cash (must be 0.00) | C35: =ROUND(C34-BS!C17,2) -> 0 | D35: =ROUND(D34-BS!D17,2) -> 0 | E35: =ROUND(E34-BS!E17,2) -> 0 | F35: =ROUND(F34-BS!F17,2) -> 0 | G35: =ROUND(G34-BS!G17,2) -> 0 | H35: =ROUND(H34-BS!H17,2) -> 0 | I35: =ROUND(I34-BS!I17,2) -> 0 | J35: =ROUND(J34-BS!J17,2) -> 0 | ... L35: =ROUND(L34-BS!L17,2) -> 0
A37: Free cash flow to firm (CFO + Capex) | C37: =C17+C19 -> -948 | D37: =D17+D19 -> 938 | E37: =E17+E19 -> 1004 | F37: =F17+F19 -> -1035 | G37: =G17+G19 -> 4688 | H37: =H17+H19 -> 3193.7348 | I37: =I17+I19 -> 4925.9196 | J37: =J17+J19 -> 6152.9195 | ... L37: =L17+L19 -> 8309.2217
A38: Free cash flow excluding Gold on Loan movement | C38: =C37-C13 -> -2136 | D38: =D37-D13 -> 1037 | E38: =E37-E13 -> 962 | F38: =F37-F13 -> -3503 | G38: =G37-G13 -> -2616 | H38: =H37-H13 -> 755.9744 | I38: =I37-I13 -> 2176.261 | J38: =J37-J13 -> 3419.4063 | ... L38: =L37-L13 -> 5357.2288

Sheet Schedules
A1: SUPPORTING OPERATIONAL SCHEDULES
A2: Working capital, fixed assets, debt revolver, leases, treasury, equity & operational ratios
A4: Line Item (INR crore unless stated) | B4: Unit | C4: FY22A | D4: FY23A | E4: FY24A | F4: FY25A | G4: FY26A | H4: FY27E | I4: FY28E | J4: FY29E | K4: FY30E | L4: FY31E
A5: A. WORKING CAPITAL & GOLD-ON-LOAN SCHEDULE
A6: Revenue from operations | C6: =IS!C5 -> 28799 | D6: =IS!D5 -> 40575 | E6: =IS!E5 -> 51084 | F6: =IS!F5 -> 60456 | G6: =IS!G5 -> 87584 | H6: =IS!H5 -> 103349.12 | I6: =IS!I5 -> 118851.49 | J6: =IS!J5 -> 134302.18 | ... L6: =IS!L5 -> 166964.47
A7: Cost of goods sold | C7: =IS!C7 -> 21641 | D7: =IS!D7 -> 30355 | E7: =IS!E7 -> 39432 | F7: =IS!F7 -> 47456 | G7: =IS!G7 -> 70307 | H7: =IS!H7 -> 82989.343 | I7: =IS!I7 -> 95318.893 | J7: =IS!J7 -> 107576.05 | ... L7: =IS!L7 -> 133571.58
A8: Inventory days (on COGS) | B8: days | C8: =C11/C7*365 -> 229.53121 | D8: =D11/D7*365 -> 199.41229 | E8: =E11/E7*365 -> 176.34447 | F8: =F11/F7*365 -> 216.77259 | G8: =G11/G7*365 -> 221.90102 | H8: =Inputs!H51 -> 220 | I8: =Inputs!I51 -> 220 | J8: =Inputs!J51 -> 220 | K8: =Inputs!K51 -> 220 | L8: =Inputs!L51 -> 220
A9: Receivable days (on Revenue) | B9: days | C9: =C12/C6*365 -> 7.1608389 | D9: =D12/D6*365 -> 6.063093 | E9: =E12/E6*365 -> 7.2737061 | F9: =F12/F6*365 -> 6.4479952 | G9: =G12/G6*365 -> 3.8173639 | H9: =Inputs!H73 -> 4 | I9: =Inputs!I73 -> 4 | J9: =Inputs!J73 -> 4 | K9: =Inputs!K73 -> 4 | L9: =Inputs!L73 -> 4
A10: Payable days (on COGS) | B10: days | C10: =C13/C7*365 -> 21.824777 | D10: =D13/D7*365 -> 14.597595 | E10: =E13/E7*365 -> 13.051582 | F10: =F13/F7*365 -> 15.098091 | G10: =G13/G7*365 -> 14.868505 | H10: =Inputs!H56 -> 15 | I10: =Inputs!I56 -> 15 | J10: =Inputs!J56 -> 15 | K10: =Inputs!K56 -> 15 | L10: =Inputs!L56 -> 15
A11: Inventories | C11: =BS!C13 -> 13609 | D11: =BS!D13 -> 16584 | E11: =BS!E13 -> 19051 | F11: =BS!F13 -> 28184 | G11: =BS!G13 -> 42743 | H11: =H7*H8/365 -> 50020.974 | I11: =I7*I8/365 -> 57452.484 | J11: =J7*J8/365 -> 64840.357 | K11: =K7*K8/365 -> 72530.537 | L11: =L7*L8/365 -> 80508.896
A12: Trade receivables | C12: =BS!C14 -> 565 | D12: =BS!D14 -> 674 | E12: =BS!E14 -> 1018 | F12: =BS!F14 -> 1068 | G12: =BS!G14 -> 916 | H12: =H6*H9/365 -> 1132.5931 | I12: =I6*I9/365 -> 1302.4821 | J12: =J6*J9/365 -> 1471.8047 | K12: =K6*K9/365 -> 1648.4213 | L12: =L6*L9/365 -> 1829.7476
A13: Trade payables | C13: =BS!C28 -> 1294 | D13: =BS!D28 -> 1214 | E13: =BS!E28 -> 1410 | F13: =BS!F28 -> 1963 | G13: =BS!G28 -> 2864 | H13: =H7*H10/365 -> 3410.521 | I13: =I7*I10/365 -> 3917.2148 | J13: =J7*J10/365 -> 4420.9335 | K13: =K7*K10/365 -> 4945.2639 | L13: =L7*L10/365 -> 5489.2429
A14: Other current assets % revenue | B14: % | C14: =BS!C15/C6 -> 0.05875204 | D14: =BS!D15/D6 -> 0.040468269 | E14: =BS!E15/E6 -> 0.045943935 | F14: =BS!F15/F6 -> 0.0373991 | G14: =BS!G15/G6 -> 0.033750457 | H14: =Inputs!H74 -> 0.034 | I14: =Inputs!I74 -> 0.034 | J14: =Inputs!J74 -> 0.034 | K14: =Inputs!K74 -> 0.034 | L14: =Inputs!L74 -> 0.034
A15: Other current assets | C15: =BS!C15 -> 1692 | D15: =BS!D15 -> 1642 | E15: =BS!E15 -> 2347 | F15: =BS!F15 -> 2261 | G15: =BS!G15 -> 2956 | H15: =H6*H14 -> 3513.8701 | I15: =I6*I14 -> 4040.9506 | J15: =J6*J14 -> 4566.2742 | K15: =K6*K14 -> 5114.2271 | L15: =L6*L14 -> 5676.792
A16: Other current liabilities % revenue | B16: % | C16: =BS!C30/C6 -> 0.087607209 | D16: =BS!D30/D6 -> 0.08667899 | E16: =BS!E30/E6 -> 0.080103359 | F16: =BS!F30/F6 -> 0.073458383 | G16: =BS!G30/G6 -> 0.071165966 | H16: =Inputs!H75 -> 0.071 | I16: =Inputs!I75 -> 0.071 | J16: =Inputs!J75 -> 0.071 | K16: =Inputs!K75 -> 0.071 | L16: =Inputs!L75 -> 0.071
A17: Other current liabilities | C17: =BS!C30 -> 2523 | D17: =BS!D30 -> 3517 | E17: =BS!E30 -> 4092 | F17: =BS!F30 -> 4441 | G17: =BS!G30 -> 6233 | H17: =H6*H16 -> 7337.7875 | I17: =I6*I16 -> 8438.4556 | J17: =J6*J16 -> 9535.4549 | K17: =K6*K16 -> 10679.709 | L17: =L6*L16 -> 11854.478
A18: Other financial liabilities % revenue | B18: % | C18: =BS!C29/C6 -> 0.015417202 | D18: =BS!D29/D6 -> 0.014097351 | E18: =BS!E29/E6 -> 0.013272257 | F18: =BS!F29/F6 -> 0.022098716 | G18: =BS!G29/G6 -> 0.050305992 | H18: =Inputs!H76 -> 0.046 | I18: =Inputs!I76 -> 0.046 | J18: =Inputs!J76 -> 0.046 | K18: =Inputs!K76 -> 0.046 | L18: =Inputs!L76 -> 0.046
A19: Other financial liabilities | C19: =BS!C29 -> 444 | D19: =BS!D29 -> 572 | E19: =BS!E29 -> 678 | F19: =BS!F29 -> 1336 | G19: =BS!G29 -> 4406 | H19: =H6*H18 -> 4754.0595 | I19: =I6*I18 -> 5467.1684 | J19: =J6*J18 -> 6177.9003 | K19: =K6*K18 -> 6919.2484 | L19: =L6*L18 -> 7680.3657
A20: Provisions % revenue | B20: % | C20: =BS!C31/C6 -> 0.008194729 | D20: =BS!D31/D6 -> 0.009168207 | E20: =BS!E31/E6 -> 0.0073212748 | F20: =BS!F31/F6 -> 0.0075095938 | G20: =BS!G31/G6 -> 0.0080151626 | H20: =Inputs!H77 -> 0.008 | I20: =Inputs!I77 -> 0.008 | J20: =Inputs!J77 -> 0.008 | K20: =Inputs!K77 -> 0.008 | L20: =Inputs!L77 -> 0.008
A21: Provisions | C21: =BS!C31 -> 236 | D21: =BS!D31 -> 372 | E21: =BS!E31 -> 374 | F21: =BS!F31 -> 454 | G21: =BS!G31 -> 702 | H21: =H6*H20 -> 826.79296 | I21: =I6*I20 -> 950.8119 | J21: =J6*J20 -> 1074.4175 | K21: =K6*K20 -> 1203.3475 | L21: =L6*L20 -> 1335.7158
A22: Gold on loan % of inventories | B22: % | C22: =BS!C26/C11 -> 0.39664928 | D22: =BS!D26/D11 -> 0.31952484 | E22: =BS!E26/E11 -> 0.28035274 | F22: =BS!F26/F11 -> 0.27710758 | G22: =BS!G26/G11 -> 0.37596799 | H22: =Inputs!H61 -> 0.37 | I22: =Inputs!I61 -> 0.37 | J22: =Inputs!J61 -> 0.37 | K22: =Inputs!K61 -> 0.37 | L22: =Inputs!L61 -> 0.37
A23: Gold on loan | C23: =BS!C26 -> 5398 | D23: =BS!D26 -> 5299 | E23: =BS!E26 -> 5341 | F23: =BS!F26 -> 7810 | G23: =BS!G26 -> 16070 | H23: =H11*H22 -> 18507.76 | I23: =I11*I22 -> 21257.419 | J23: =J11*J22 -> 23990.932 | K23: =K11*K22 -> 26836.299 | L23: =L11*L22 -> 29788.292
A24: Operating NWC (excluding Gold on Loan) | C24: =C11+C12+C15-C13-C17-C19-C21 -> 11369 | D24: =D11+D12+D15-D13-D17-D19-D21 -> 13225 | E24: =E11+E12+E15-E13-E17-E19-E21 -> 15862 | F24: =F11+F12+F15-F13-F17-F19-F21 -> 23319 | G24: =G11+G12+G15-G13-G17-G19-G21 -> 32410 | H24: =H11+H12+H15-H13-H17-H19-H21 -> 38338.276 | I24: =I11+I12+I15-I13-I17-I19-I21 -> 44022.266 | J24: =J11+J12+J15-J13-J17-J19-J21 -> 49669.73 | ... L24: =L11+L12+L15-L13-L17-L19-L21 -> 61655.634
A25: Operating NWC (net of Gold on Loan) | C25: =C24-C23 -> 5971 | D25: =D24-D23 -> 7926 | E25: =E24-E23 -> 10521 | F25: =F24-F23 -> 15509 | G25: =G24-G23 -> 16340 | H25: =H24-H23 -> 19830.516 | I25: =I24-I23 -> 22764.847 | J25: =J24-J23 -> 25678.798 | ... L25: =L24-L23 -> 31867.342
A26: Change in NWC (excluding GoL) | D26: =D24-C24 -> 1856 | E26: =E24-D24 -> 2637 | F26: =F24-E24 -> 7457 | G26: =G24-F24 -> 9091 | H26: =H24-G24 -> 5928.2763 | I26: =I24-H24 -> 5683.9892 | J26: =J24-I24 -> 5647.4645 | K26: =K24-J24 -> 5875.886 | L26: =L24-K24 -> 6110.0178
A27: Change in NWC (net of GoL) | D27: =D25-C25 -> 1955 | E27: =E25-D25 -> 2595 | F27: =F25-E25 -> 4988 | G27: =G25-F25 -> 831 | H27: =H25-G25 -> 3490.5159 | I27: =I25-H25 -> 2934.3307 | J27: =J25-I25 -> 2913.9513 | K27: =K25-J25 -> 3030.5195 | L27: =L25-K25 -> 3158.0249
A29: B. TANGIBLE, INTANGIBLE & IND AS 116 ROU LEASE SCHEDULE
A30: Capex % revenue | B30: % | C30: =C32/C6 -> 0.0077780478 | D30: =D32/D6 -> 0.01064695 | E30: =E32/E6 -> 0.01352674 | F30: =F32/F6 -> 0.008171232 | G30: =G32/G6 -> 0.010298685 | H30: =Inputs!H46 -> 0.012 | I30: =Inputs!I46 -> 0.012 | J30: =Inputs!J46 -> 0.012 | K30: =Inputs!K46 -> 0.012 | L30: =Inputs!L46 -> 0.012
A31: intangible share of capex | B31: % | H31: =Inputs!H85 -> 0.15 | I31: =Inputs!I85 -> 0.15 | J31: =Inputs!J85 -> 0.15 | K31: =Inputs!K85 -> 0.15 | L31: =Inputs!L85 -> 0.15
A32: Total capex (PP&E + Intangibles) | C32: =-CF!C19 -> 224 | D32: =-CF!D19 -> 432 | E32: =-CF!E19 -> 691 | F32: =-CF!F19 -> 494 | G32: =-CF!G19 -> 902 | H32: =H6*H30 -> 1240.1894 | I32: =I6*I30 -> 1426.2179 | J32: =J6*J30 -> 1611.6262 | K32: =K6*K30 -> 1805.0213 | L32: =L6*L30 -> 2003.5737
A33: capex - intangibles | H33: =H32*H31 -> 186.02842 | I33: =I32*I31 -> 213.93268 | J33: =J32*J31 -> 241.74393 | K33: =K32*K31 -> 270.7532 | L33: =L32*L31 -> 300.53605
A34: capex - tangible PP&E | H34: =H32-H33 -> 1054.161 | I34: =I32-I33 -> 1212.2852 | J34: =J32-J33 -> 1369.8823 | K34: =K32-K33 -> 1534.2681 | L34: =L32-L33 -> 1703.0376
A35: PP&E depreciation % opening balance | B35: % | F35: =Hist_Data!F113/BS!E6 -> 0.14895947 | G35: =Hist_Data!G113/BS!F6 -> 0.16940452 | H35: =Inputs!H82 -> 0.16 | I35: =Inputs!I82 -> 0.16 | J35: =Inputs!J82 -> 0.16 | K35: =Inputs!K82 -> 0.16 | L35: =Inputs!L82 -> 0.16
A36: PP&E: Opening balance | H36: =G39 -> 2955 | I36: =H39 -> 3536.361 | J36: =I39 -> 4182.8284 | K36: =J39 -> 4883.4581 | L36: =K39 -> 5636.373
A37: + PP&E additions | H37: =H34 -> 1054.161 | I37: =I34 -> 1212.2852 | J37: =J34 -> 1369.8823 | K37: =K34 -> 1534.2681 | L37: =L34 -> 1703.0376
A38: - depreciation expense | F38: =Hist_Data!F113 -> 272 | G38: =Hist_Data!G113 -> 330 | H38: =H36*H35 -> 472.8 | I38: =I36*I35 -> 565.81776 | J38: =J36*J35 -> 669.25255 | K38: =K36*K35 -> 781.3533 | L38: =L36*L35 -> 901.81967
A39: PP&E: Closing balance | C39: =BS!C6 -> 1288 | D39: =BS!D6 -> 1477 | E39: =BS!E6 -> 1826 | F39: =BS!F6 -> 1948 | G39: =BS!G6 -> 2955 | H39: =H36+H37-H38 -> 3536.361 | I39: =I36+I37-I38 -> 4182.8284 | J39: =J36+J37-J38 -> 4883.4581 | K39: =K36+K37-K38 -> 5636.373 | L39: =L36+L37-L38 -> 6437.5909
A40: ROU new lease additions % revenue | B40: % | F40: =(F70-E70+F69-F68)/F6 -> 0.013398174 | G40: =(G70-F70+G69-G68)/G6 -> 0.012673548 | H40: =Inputs!H86 -> 0.01 | I40: =Inputs!I86 -> 0.01 | J40: =Inputs!J86 -> 0.01 | K40: =Inputs!K86 -> 0.01 | L40: =Inputs!L86 -> 0.01
A41: ROU depreciation % opening balance | B41: % | F41: =Hist_Data!F114/BS!E7 -> 0.23331173 | G41: =Hist_Data!G114/BS!F7 -> 0.24069899 | H41: =Inputs!H83 -> 0.24 | I41: =Inputs!I83 -> 0.24 | J41: =Inputs!J83 -> 0.24 | K41: =Inputs!K83 -> 0.24 | L41: =Inputs!L83 -> 0.24
A42: ROU Assets: Opening balance | H42: =G45 -> 2195 | I42: =H45 -> 2701.6912 | J42: =I45 -> 3241.8002 | K42: =J45 -> 3806.79 | L42: =K45 -> 4397.3448
A43: + new leases entered (non-cash) | H43: =H67 -> 1033.4912 | I43: =I67 -> 1188.5149 | J43: =J67 -> 1343.0218 | K43: =K67 -> 1504.1844 | L43: =L67 -> 1669.6447
A44: - ROU depreciation expense | F44: =Hist_Data!F114 -> 360 | G44: =Hist_Data!G114 -> 427 | H44: =H42*H41 -> 526.8 | I44: =I42*I41 -> 648.40589 | J44: =J42*J41 -> 778.03205 | K44: =K42*K41 -> 913.62959 | L44: =L42*L41 -> 1055.3628
A45: ROU Assets: Closing balance | C45: =BS!C7 -> 973 | D45: =BS!D7 -> 1285 | E45: =BS!E7 -> 1543 | F45: =BS!F7 -> 1774 | G45: =BS!G7 -> 2195 | H45: =H42+H43-H44 -> 2701.6912 | I45: =I42+I43-I44 -> 3241.8002 | J45: =J42+J43-J44 -> 3806.79 | K45: =K42+K43-K44 -> 4397.3448 | L45: =L42+L43-L44 -> 5011.6268
A46: Intangible amortisation % opening balance | B46: % | F46: =Hist_Data!F115/BS!E9 -> 0.19426752 | G46: =Hist_Data!G115/BS!F9 -> 0.21428571 | H46: =Inputs!H84 -> 0.12 | I46: =Inputs!I84 -> 0.12 | J46: =Inputs!J84 -> 0.12 | K46: =Inputs!K84 -> 0.12 | L46: =Inputs!L84 -> 0.12
A47: Intangibles: Opening balance | H47: =G50 -> 1133 | I47: =H50 -> 1183.0684 | J47: =I50 -> 1255.0329 | K47: =J50 -> 1346.1729 | L47: =K50 -> 1455.3853
A48: + intangible additions | H48: =H33 -> 186.02842 | I48: =I33 -> 213.93268 | J48: =J33 -> 241.74393 | K48: =K33 -> 270.7532 | L48: =L33 -> 300.53605
A49: - amortisation expense | F49: =Hist_Data!F115 -> 61 | G49: =Hist_Data!G115 -> 69 | H49: =H47*H46 -> 135.96 | I49: =I47*I46 -> 141.96821 | J49: =J47*J46 -> 150.60395 | K49: =K47*K46 -> 161.54074 | L49: =L47*L46 -> 174.64624
A50: Intangibles: Closing balance | C50: =BS!C9 -> 245 | D50: =BS!D9 -> 257 | E50: =BS!E9 -> 314 | F50: =BS!F9 -> 322 | G50: =BS!G9 -> 1133 | H50: =H47+H48-H49 -> 1183.0684 | I50: =I47+I48-I49 -> 1255.0329 | J50: =J47+J48-J49 -> 1346.1729 | K50: =K47+K48-K49 -> 1455.3853 | L50: =L47+L48-L49 -> 1581.2751
A51: Total Depreciation & Amortisation | C51: =IS!C16 -> 399 | D51: =IS!D16 -> 441 | E51: =IS!E16 -> 584 | F51: =IS!F16 -> 693 | G51: =IS!G16 -> 826 | H51: =H38+H44+H49 -> 1135.56 | I51: =I38+I44+I49 -> 1356.1919 | J51: =J38+J44+J49 -> 1597.8885 | K51: =K38+K44+K49 -> 1856.5236 | L51: =L38+L44+L49 -> 2131.8287
A53: C. DEBT, REVOLVER, GOLD-ON-LOAN & LEASES (Zero Circularity)
A54: Term debt: Opening balance | H54: =G56 -> 93 | I54: =H56 -> 0 | J54: =I56 -> 0 | K54: =J56 -> 0 | L54: =K56 -> 0
A55: - scheduled term debt repayment | H55: =MIN(H54,Inputs!H91) -> 93 | I55: =MIN(I54,Inputs!I91) -> 0 | J55: =MIN(J54,Inputs!J91) -> 0 | K55: =MIN(K54,Inputs!K91) -> 0 | L55: =MIN(L54,Inputs!L91) -> 0
A56: Term debt: Closing balance | C56: =Hist_Data!C54 -> 2 | D56: =Hist_Data!D54 -> 0 | E56: =Hist_Data!E54 -> 3302 | F56: =Hist_Data!F54 -> 595 | G56: =Hist_Data!G54 -> 93 | H56: =H54-H55 -> 0 | I56: =I54-I55 -> 0 | J56: =J54-J55 -> 0 | K56: =K54-K55 -> 0 | L56: =L54-L55 -> 0
A57: Minimum operating cash % revenue | B57: % | C57: =BS!C17/C6 -> 0.0076044307 | D57: =BS!D17/D6 -> 0.0057178065 | E57: =BS!E17/E6 -> 0.0080064208 | F57: =BS!F17/F6 -> 0.0067321689 | G57: =BS!G17/G6 -> 0.009967574 | H57: =Inputs!H79 -> 0.01 | I57: =Inputs!I79 -> 0.01 | J57: =Inputs!J79 -> 0.01 | K57: =Inputs!K79 -> 0.01 | L57: =Inputs!L79 -> 0.01
A58: Required minimum cash threshold | H58: =H6*H57 -> 1033.4912 | I58: =I6*I57 -> 1188.5149 | J58: =J6*J57 -> 1343.0218 | K58: =K6*K57 -> 1504.1844 | L58: =L6*L57 -> 1669.6447
A59: Operational cash before revolver activity | H59: =BS!G17+CF!H17+CF!H21+CF!H23+CF!H25+CF!H26+CF!H27+CF!H28 -> 626.56161 | I59: =BS!H17+CF!I17+CF!I21+CF!I23+CF!I25+CF!I26+CF!I27+CF!I28 -> 2037.4554 | J59: =BS!I17+CF!J17+CF!J21+CF!J23+CF!J25+CF!J26+CF!J27+CF!J28 -> 3040.5595 | K59: =BS!J17+CF!K17+CF!K21+CF!K23+CF!K25+CF!K26+CF!K27+CF!K28 -> 3858.24 | L59: =BS!K17+CF!L17+CF!L21+CF!L23+CF!L25+CF!L26+CF!L27+CF!L28 -> 4745.6495
A60: Revolver / Short-term debt: Opening | H60: =G62 -> 11285 | I60: =H62 -> 11691.93 | J60: =I62 -> 10842.989 | K60: =J62 -> 9145.4514 | L60: =K62 -> 6791.3958
A61: drawdown / (repayment) to hold minimum cash | H61: =MAX(H58-H59,-H60) -> 406.92959 | I61: =MAX(I58-I59,-I60) -> -848.94054 | J61: =MAX(J58-J59,-J60) -> -1697.5377 | K61: =MAX(K58-K59,-K60) -> -2354.0556 | L61: =MAX(L58-L59,-L60) -> -3076.0048
A62: Revolver / Short-term debt: Closing | C62: =Hist_Data!C60 -> 516 | D62: =Hist_Data!D60 -> 2195 | E62: =Hist_Data!E60 -> 4536 | F62: =Hist_Data!F60 -> 9691 | G62: =Hist_Data!G60 -> 11285 | H62: =H60+H61 -> 11691.93 | I62: =I60+I61 -> 10842.989 | J62: =J60+J61 -> 9145.4514 | K62: =K60+K61 -> 6791.3958 | L62: =L60+L61 -> 3715.391
A63: Total Borrowings (Term Debt + Revolver) | C63: =C56+C62 -> 518 | D63: =D56+D62 -> 2195 | E63: =E56+E62 -> 7838 | F63: =F56+F62 -> 10286 | G63: =G56+G62 -> 11378 | H63: =H56+H62 -> 11691.93 | I63: =I56+I62 -> 10842.989 | J63: =J56+J62 -> 9145.4514 | ... L63: =L56+L62 -> 3715.391
A64: Lease interest rate (on opening balance) | B64: % | F64: =Hist_Data!F110/E70 -> 0.094508301 | G64: =Hist_Data!G110/F70 -> 0.092129802 | H64: =Inputs!H88 -> 0.09 | I64: =Inputs!I88 -> 0.09 | J64: =Inputs!J88 -> 0.09 | K64: =Inputs!K88 -> 0.09 | L64: =Inputs!L88 -> 0.09
A65: Lease payments % opening liability | B65: % | D65: =-CF!D26/C70 -> 0.18690213 | E65: =-CF!E26/D70 -> 0.1697811 | F65: =-CF!F26/E70 -> 0.29799915 | G65: =-CF!G26/F70 -> 0.32264081 | H65: =Inputs!H87 -> 0.32 | I65: =Inputs!I87 -> 0.32 | J65: =Inputs!J87 -> 0.32 | K65: =Inputs!K87 -> 0.32 | L65: =Inputs!L87 -> 0.32
A66: Lease liabilities: Opening balance | H66: =G70 -> 3173 | I66: =H70 -> 3476.7012 | J66: =I70 -> 3865.5748 | K66: =J70 -> 4319.5144 | L66: =K70 -> 4830.2105
A67: + new lease liabilities entered | H67: =H6*H40 -> 1033.4912 | I67: =I6*I40 -> 1188.5149 | J67: =J6*J40 -> 1343.0218 | K67: =K6*K40 -> 1504.1844 | L67: =L6*L40 -> 1669.6447
A68: + interest accretion on leases | F68: =Hist_Data!F110 -> 222 | G68: =Hist_Data!G110 -> 247 | H68: =H66*H64 -> 285.57 | I68: =I66*I64 -> 312.90311 | J68: =J66*J64 -> 347.90173 | K68: =K66*K64 -> 388.7563 | L68: =L66*L64 -> 434.71895
A69: - lease cash payments | C69: =-CF!C26 -> 172 | D69: =-CF!D26 -> 254 | E69: =-CF!E26 -> 318 | F69: =-CF!F26 -> 700 | G69: =-CF!G26 -> 865 | H69: =H66*H65 -> 1015.36 | I69: =I66*I65 -> 1112.5444 | J69: =J66*J65 -> 1236.9839 | K69: =K66*K65 -> 1382.2446 | L69: =L66*L65 -> 1545.6674
A70: Lease liabilities: Closing balance | C70: =BS!C27 -> 1359 | D70: =BS!D27 -> 1873 | E70: =BS!E27 -> 2349 | F70: =BS!F27 -> 2681 | G70: =BS!G27 -> 3173 | H70: =H66+H67+H68-H69 -> 3476.7012 | I70: =I66+I67+I68-I69 -> 3865.5748 | J70: =J66+J67+J68-J69 -> 4319.5144 | K70: =K66+K67+K68-K69 -> 4830.2105 | L70: =L66+L67+L68-L69 -> 5388.9068
A71: Effective interest rate on borrowings | B71: % | F71: =Hist_Data!F109/E63 -> 0.070298546 | G71: =Hist_Data!G109/F63 -> 0.059303908 | H71: =Inputs!H66 -> 0.058 | I71: =Inputs!I66 -> 0.058 | J71: =Inputs!J66 -> 0.058 | K71: =Inputs!K66 -> 0.058 | L71: =Inputs!L66 -> 0.058
A72: Gold-on-loan interest rate | B72: % | F72: =Hist_Data!F111/E23 -> 0.032578169 | G72: =Hist_Data!G111/F23 -> 0.040973111 | H72: =Inputs!H89 -> 0.029 | I72: =Inputs!I89 -> 0.029 | J72: =Inputs!J89 -> 0.029 | K72: =Inputs!K89 -> 0.029 | L72: =Inputs!L89 -> 0.029
A73: Interest on borrowings | F73: =Hist_Data!F109+Hist_Data!F112 -> 557 | G73: =Hist_Data!G109+Hist_Data!G112 -> 613 | H73: =G63*H71 -> 659.924 | I73: =H63*I71 -> 678.13192 | J73: =I63*J71 -> 628.89336 | K73: =J63*K71 -> 530.43618 | L73: =K63*L71 -> 393.90096
A74: Interest on gold on loan | F74: =Hist_Data!F111 -> 174 | G74: =Hist_Data!G111 -> 320 | H74: =G23*H72 -> 466.03 | I74: =H23*I72 -> 536.72505 | J74: =I23*J72 -> 616.46515 | K74: =J23*K72 -> 695.73703 | L74: =K23*L72 -> 778.25266
A75: Total finance costs (IS) | C75: =IS!C21 -> 218 | D75: =IS!D21 -> 300 | E75: =IS!E21 -> 619 | F75: =IS!F21 -> 953 | G75: =IS!G21 -> 1180 | H75: =H73+H74+H68 -> 1411.524 | I75: =I73+I74+I68 -> 1527.7601 | J75: =J73+J74+J68 -> 1593.2602 | K75: =K73+K74+K68 -> 1614.9295 | L75: =L73+L74+L68 -> 1606.8726
A76: Cash finance costs paid (excl. non-cash lease interest) | H76: =H73+H74 -> 1125.954 | I76: =I73+I74 -> 1214.857 | J76: =J73+J74 -> 1245.3585 | K76: =K73+K74 -> 1226.1732 | L76: =L73+L74 -> 1172.1536
A78: D. TREASURY INVESTMENTS & OTHER INCOME
A79: Treasury investments % revenue | B79: % | C79: =BS!C16/C6 -> 0.047536373 | D79: =BS!D16/D6 -> 0.080714726 | E79: =BS!E16/E6 -> 0.054478898 | F79: =BS!F16/F6 -> 0.041583962 | G79: =BS!G16/G6 -> 0.037598191 | H79: =Inputs!H78 -> 0.035 | I79: =Inputs!I78 -> 0.035 | J79: =Inputs!J78 -> 0.035 | K79: =Inputs!K78 -> 0.035 | L79: =Inputs!L78 -> 0.035
A80: Treasury investments & bank deposits | C80: =BS!C16 -> 1369 | D80: =BS!D16 -> 3275 | E80: =BS!E16 -> 2783 | F80: =BS!F16 -> 2514 | G80: =BS!G16 -> 3293 | H80: =H6*H79 -> 3617.2192 | I80: =I6*I79 -> 4159.8021 | J80: =J6*J79 -> 4700.5764 | K80: =K6*K79 -> 5264.6455 | L80: =L6*L79 -> 5843.7565
A81: Other income portfolio yield | B81: % | D81: =IS!D20/D82 -> 0.16497054 | E81: =IS!E20/E82 -> 0.13815448 | F81: =IS!F20/F82 -> 0.12554895 | G81: =IS!G20/G82 -> 0.15453527 | H81: =Inputs!H90 -> 0.09 | I81: =Inputs!I90 -> 0.09 | J81: =Inputs!J90 -> 0.09 | K81: =Inputs!K90 -> 0.09 | L81: =Inputs!L90 -> 0.09
A82: Yield portfolio base (Cash + Treasury + NC Inv) | D82: =BS!C17+BS!C16+BS!C10 -> 1867 | E82: =BS!D17+BS!D16+BS!D10 -> 3858 | F82: =BS!E17+BS!E16+BS!E10 -> 3871 | G82: =BS!F17+BS!F16+BS!F10 -> 3572 | H82: =BS!G17+BS!G16+BS!G10 -> 5423 | I82: =BS!H17+BS!H16+BS!H10 -> 5907.7104 | J82: =BS!I17+BS!I16+BS!I10 -> 6605.317 | K82: =BS!J17+BS!J16+BS!J10 -> 7300.5982 | L82: =BS!K17+BS!K16+BS!K10 -> 8025.8299
A83: Other income | C83: =IS!C20 -> 234 | D83: =IS!D20 -> 308 | E83: =IS!E20 -> 533 | F83: =IS!F20 -> 486 | G83: =IS!G20 -> 552 | H83: =H82*H81 -> 488.07 | I83: =I82*I81 -> 531.69394 | J83: =J82*J81 -> 594.47853 | K83: =K82*K81 -> 657.05383 | L83: =L82*L81 -> 722.3247
A85: E. SHAREHOLDERS' EQUITY ROLL-FORWARD
A86: Dividend payout % prior-year PAT | B86: % | D86: =-CF!D25/IS!C27 -> 0.30300273 | E86: =-CF!E25/IS!D27 -> 0.27122786 | F86: =-CF!F25/IS!E27 -> 0.2791762 | G86: =-CF!G25/IS!F27 -> 0.29247827 | H86: =Inputs!H81 -> 0.27 | I86: =Inputs!I81 -> 0.27 | J86: =Inputs!J81 -> 0.27 | K86: =Inputs!K81 -> 0.27 | L86: =Inputs!L81 -> 0.27
A87: Other equity: Opening balance | H87: =G90 -> 15614 | I87: =H90 -> 20109.716 | J87: =I90 -> 25460.261 | K87: =J90 -> 31669.851 | L87: =K90 -> 38721.644
A88: + Profit for the year (PAT) | H88: =IS!H27 -> 5865.4261 | I88: =IS!I27 -> 6934.2101 | J88: =IS!J27 -> 8081.8267 | K88: =IS!K27 -> 9233.8861 | L88: =IS!L27 -> 10454.444
A89: - Dividends paid | C89: =-CF!C25 -> 355 | D89: =-CF!D25 -> 666 | E89: =-CF!E25 -> 888 | F89: =-CF!F25 -> 976 | G89: =-CF!G25 -> 976 | H89: =IS!G27*H86 -> 1369.71 | I89: =IS!H27*I86 -> 1583.6651 | J89: =IS!I27*J86 -> 1872.2367 | K89: =IS!J27*K86 -> 2182.0932 | L89: =IS!K27*L86 -> 2493.1493
A90: Other equity: Closing balance | C90: =BS!C23 -> 9244 | D90: =BS!D23 -> 11815 | E90: =BS!E23 -> 9304 | F90: =BS!F23 -> 11535 | G90: =BS!G23 -> 15614 | H90: =H87+H88-H89 -> 20109.716 | I90: =I87+I88-I89 -> 25460.261 | J90: =J87+J88-J89 -> 31669.851 | K90: =K87+K88-K89 -> 38721.644 | L90: =L87+L88-L89 -> 46682.939
A92: F. INTEGRATED CREDIT & OPERATING RATIOS
A93: Return on Equity (ROE: PAT / Avg Equity) | B93: % | D93: =IS!D27/AVERAGE(BS!C24,BS!D24) -> 0.3083298 | E93: =IS!E27/AVERAGE(BS!D24,BS!E24) -> 0.32830915 | F93: =IS!F27/AVERAGE(BS!E24,BS!F24) -> 0.31755246 | G93: =IS!G27/AVERAGE(BS!F24,BS!G24) -> 0.37128115 | H93: =IS!H27/AVERAGE(BS!G24,BS!H24) -> 0.32674907 | I93: =IS!I27/AVERAGE(BS!H24,BS!I24) -> 0.30314827 | J93: =IS!J27/AVERAGE(BS!I24,BS!J24) -> 0.28204826 | K93: =IS!K27/AVERAGE(BS!J24,BS!K24) -> 0.26169625 | L93: =IS!L27/AVERAGE(BS!K24,BS!L24) -> 0.24431241
A94: Return on Invested Capital (ROIC) | B94: % | D94: =IS!D17*(1-IS!D26)/AVERAGE((BS!C24+BS!C25+BS!C27+BS!C26-BS!C17-BS!C16),(BS!D24+BS!D25+BS!D27+BS!D26-BS!D17-BS!D16)) -> 0.19932735 | E94: =IS!E17*(1-IS!E26)/AVERAGE((BS!D24+BS!D25+BS!D27+BS!D26-BS!D17-BS!D16),(BS!E24+BS!E25+BS!E27+BS!E26-BS!E17-BS!E16)) -> 0.18029922 | F94: =IS!F17*(1-IS!F26)/AVERAGE((BS!E24+BS!E25+BS!E27+BS!E26-BS!E17-BS!E16),(BS!F24+BS!F25+BS!F27+BS!F26-BS!F17-BS!F16)) -> 0.14372075 | G94: =IS!G17*(1-IS!G26)/AVERAGE((BS!F24+BS!F25+BS!F27+BS!F26-BS!F17-BS!F16),(BS!G24+BS!G25+BS!G27+BS!G26-BS!G17-BS!G16)) -> 0.15678912 | H94: =IS!H17*(1-IS!H26)/AVERAGE((BS!G24+BS!G25+BS!G27+BS!G26-BS!G17-BS!G16),(BS!H24+BS!H25+BS!H27+BS!H26-BS!H17-BS!H16)) -> 0.14344826 | I94: =IS!I17*(1-IS!I26)/AVERAGE((BS!H24+BS!H25+BS!H27+BS!H26-BS!H17-BS!H16),(BS!I24+BS!I25+BS!I27+BS!I26-BS!I17-BS!I16)) -> 0.14569084 | J94: =IS!J17*(1-IS!J26)/AVERAGE((BS!I24+BS!I25+BS!I27+BS!I26-BS!I17-BS!I16),(BS!J24+BS!J25+BS!J27+BS!J26-BS!J17-BS!J16)) -> 0.14793129 | K94: =IS!K17*(1-IS!K26)/AVERAGE((BS!J24+BS!J25+BS!J27+BS!J26-BS!J17-BS!J16),(BS!K24+BS!K25+BS!K27+BS!K26-BS!K17-BS!K16)) -> 0.1488501 | L94: =IS!L17*(1-IS!L26)/AVERAGE((BS!K24+BS!K25+BS!K27+BS!K26-BS!K17-BS!K16),(BS!L24+BS!L25+BS!L27+BS!L26-BS!L17-BS!L16)) -> 0.14953587
A95: Net debt (Borrowings + GoL + Leases - Cash - Treasury) | C95: =BS!C25+BS!C26+BS!C27-BS!C17-BS!C16 -> 5687 | D95: =BS!D25+BS!D26+BS!D27-BS!D17-BS!D16 -> 5860 | E95: =BS!E25+BS!E26+BS!E27-BS!E17-BS!E16 -> 12336 | F95: =BS!F25+BS!F26+BS!F27-BS!F17-BS!F16 -> 17856 | G95: =BS!G25+BS!G26+BS!G27-BS!G17-BS!G16 -> 26455 | H95: =BS!H25+BS!H26+BS!H27-BS!H17-BS!H16 -> 29025.681 | I95: =BS!I25+BS!I26+BS!I27-BS!I17-BS!I16 -> 30617.666 | J95: =BS!J25+BS!J26+BS!J27-BS!J17-BS!J16 -> 31412.3 | ... L95: =BS!L25+BS!L26+BS!L27-BS!L17-BS!L16 -> 31379.188
A96: Net debt / EBITDA | B96: x | C96: =C95/IS!C14 -> 1.702185 | D96: =D95/IS!D14 -> 1.2010658 | E96: =E95/IS!E14 -> 2.3310658 | F96: =F95/IS!F14 -> 3.1359326 | G96: =G95/IS!G14 -> 3.1663674 | H96: =H95/IS!H14 -> 2.9255289 | I96: =I95/IS!I14 -> 2.6287021 | J96: =J95/IS!J14 -> 2.338927 | ... L96: =L95/IS!L14 -> 1.8425423
A97: Interest coverage (EBIT / Finance costs) | B97: x | C97: =IS!C17/IS!C21 -> 13.495413 | D97: =IS!D17/IS!D21 -> 14.793333 | E97: =IS!E17/IS!E21 -> 7.6058158 | F97: =IS!F17/IS!F21 -> 5.247639 | G97: =IS!G17/IS!G21 -> 6.3805085 | H97: =IS!H17/IS!H21 -> 6.2244464 | I97: =IS!I17/IS!I21 -> 6.7361716 | J97: =IS!J17/IS!J21 -> 7.4264889 | ... L97: =IS!L17/IS!L21 -> 9.2717667
A98: Cash conversion ratio (CFO / EBITDA) | B98: % | C98: =CF!C17/IS!C14 -> -0.21670159 | D98: =CF!D17/IS!D14 -> 0.28079524 | E98: =CF!E17/IS!E14 -> 0.32029478 | F98: =CF!F17/IS!F14 -> -0.095012294 | G98: =CF!G17/IS!G14 -> 0.66906044 | H98: =CF!H17/IS!H14 -> 0.4468999 | I98: =CF!I17/IS!I14 -> 0.54536742 | J98: =CF!J17/IS!J14 -> 0.57813995 | ... L98: =CF!L17/IS!L14 -> 0.605553

Sheet Earnings_Quality
A1: EARNINGS QUALITY & DUPONT ANALYSIS
A2: Forensic accounting audit: Sloan accruals, DuPont 3-stage, cash conversion cycle & Altman Z
A4: Line Item (INR crore unless stated) | B4: Unit | C4: FY22A | D4: FY23A | E4: FY24A | F4: FY25A | G4: FY26A | H4: FY27E | I4: FY28E | J4: FY29E | K4: FY30E | L4: FY31E
A5: 1. ACCRUAL METRICS & EARNINGS QUALITY AUDIT
A6: Reported Profit After Tax (PAT) | C6: =IS!C27 -> 2198 | D6: =IS!D27 -> 3274 | E6: =IS!E27 -> 3496 | F6: =IS!F27 -> 3337 | G6: =IS!G27 -> 5073 | H6: =IS!H27 -> 5865.4261 | I6: =IS!I27 -> 6934.2101 | J6: =IS!J27 -> 8081.8267 | ... L6: =IS!L27 -> 10454.444
A7: Cash Flow from Operations (CFO) | C7: =CF!C17 -> -724 | D7: =CF!D17 -> 1370 | E7: =CF!E17 -> 1695 | F7: =CF!F17 -> -541 | G7: =CF!G17 -> 5590 | H7: =CF!H17 -> 4433.9242 | I7: =CF!I17 -> 6352.1374 | J7: =CF!J17 -> 7764.5457 | ... L7: =CF!L17 -> 10312.795
A8: Total Accounting Accruals (PAT - CFO) | C8: =C6-C7 -> 2922 | D8: =D6-D7 -> 1904 | E8: =E6-E7 -> 1801 | F8: =F6-F7 -> 3878 | G8: =G6-G7 -> -517 | H8: =H6-H7 -> 1431.5019 | I8: =I6-I7 -> 582.07269 | J8: =J6-J7 -> 317.28103 | ... L8: =L6-L7 -> 141.64838
A9: Sloan Accrual Ratio ((PAT - CFO) / Avg Total Assets) | B9: % | D9: =D8/AVERAGE(BS!C19,BS!D19) -> 0.078976295 | E9: =E8/AVERAGE(BS!D19,BS!E19) -> 0.061495911 | F9: =F8/AVERAGE(BS!E19,BS!F19) -> 0.10742829 | G9: =G8/AVERAGE(BS!F19,BS!G19) -> -0.010216584 | H9: =H8/AVERAGE(BS!G19,BS!H19) -> 0.021888865 | I9: =I8/AVERAGE(BS!H19,BS!I19) -> 0.0077322483 | J9: =J8/AVERAGE(BS!I19,BS!J19) -> 0.003715749 | K9: =K8/AVERAGE(BS!J19,BS!K19) -> 0.002257088 | L9: =L8/AVERAGE(BS!K19,BS!L19) -> 0.0013293798
A10: Cash Generation Ratio (CFO / PAT > 1.0x indicates healthy quality) | B10: x | C10: =C7/C6 -> -0.32939035 | D10: =D7/D6 -> 0.41844838 | E10: =E7/E6 -> 0.48483982 | F10: =F7/F6 -> -0.16212167 | G10: =G7/G6 -> 1.1019121 | H10: =H7/H6 -> 0.75594239 | I10: =I7/I6 -> 0.91605782 | J10: =J7/J6 -> 0.96074142 | ... L10: =L7/L6 -> 0.98645089
A11: Operating Cash Conversion (CFO / EBITDA) | B11: % | C11: =C7/IS!C14 -> -0.21670159 | D11: =D7/IS!D14 -> 0.28079524 | E11: =E7/IS!E14 -> 0.32029478 | F11: =F7/IS!F14 -> -0.095012294 | G11: =G7/IS!G14 -> 0.66906044 | H11: =H7/IS!H14 -> 0.4468999 | I11: =I7/IS!I14 -> 0.54536742 | J11: =J7/IS!J14 -> 0.57813995 | ... L11: =L7/IS!L14 -> 0.605553
A13: 2. WORKING CAPITAL EFFICIENCY & CASH CONVERSION CYCLE
A14: Days Inventory Outstanding (DIO) | B14: days | C14: =Schedules!C8 -> 229.53121 | D14: =Schedules!D8 -> 199.41229 | E14: =Schedules!E8 -> 176.34447 | F14: =Schedules!F8 -> 216.77259 | G14: =Schedules!G8 -> 221.90102 | H14: =Schedules!H8 -> 220 | I14: =Schedules!I8 -> 220 | J14: =Schedules!J8 -> 220 | ... L14: =Schedules!L8 -> 220
A15: Days Sales Outstanding (DSO) | B15: days | C15: =Schedules!C9 -> 7.1608389 | D15: =Schedules!D9 -> 6.063093 | E15: =Schedules!E9 -> 7.2737061 | F15: =Schedules!F9 -> 6.4479952 | G15: =Schedules!G9 -> 3.8173639 | H15: =Schedules!H9 -> 4 | I15: =Schedules!I9 -> 4 | J15: =Schedules!J9 -> 4 | ... L15: =Schedules!L9 -> 4
A16: Days Payables Outstanding (DPO) | B16: days | C16: =Schedules!C10 -> 21.824777 | D16: =Schedules!D10 -> 14.597595 | E16: =Schedules!E10 -> 13.051582 | F16: =Schedules!F10 -> 15.098091 | G16: =Schedules!G10 -> 14.868505 | H16: =Schedules!H10 -> 15 | I16: =Schedules!I10 -> 15 | J16: =Schedules!J10 -> 15 | ... L16: =Schedules!L10 -> 15
A17: Net Cash Conversion Cycle (DIO + DSO - DPO) | B17: days | C17: =C14+C15-C16 -> 214.86728 | D17: =D14+D15-D16 -> 190.87779 | E17: =E14+E15-E16 -> 170.56659 | F17: =F14+F15-F16 -> 208.12249 | G17: =G14+G15-G16 -> 210.84988 | H17: =H14+H15-H16 -> 209 | I17: =I14+I15-I16 -> 209 | J17: =J14+J15-J16 -> 209 | ... L17: =L14+L15-L16 -> 209
A19: 3. DUPONT 3-STAGE ROE DECOMPOSITION
A20: Net Profit Margin (PAT / Revenue) | B20: % | C20: =IS!C28 -> 0.076322095 | D20: =IS!D28 -> 0.08069008 | E20: =IS!E28 -> 0.068436301 | F20: =IS!F28 -> 0.055197168 | G20: =IS!G28 -> 0.057921538 | H20: =IS!H28 -> 0.056753518 | I20: =IS!I28 -> 0.058343486 | J20: =IS!J28 -> 0.060176437 | ... L20: =IS!L28 -> 0.06261478
A21: Asset Turnover (Revenue / Avg Total Assets) | B21: x | D21: =IS!D5/AVERAGE(BS!C19,BS!D19) -> 1.6830164 | E21: =IS!E5/AVERAGE(BS!D19,BS!E19) -> 1.7442849 | F21: =IS!F5/AVERAGE(BS!E19,BS!F19) -> 1.674751 | G21: =IS!G5/AVERAGE(BS!F19,BS!G19) -> 1.7307723 | H21: =IS!H5/AVERAGE(BS!G19,BS!H19) -> 1.5802948 | I21: =IS!I5/AVERAGE(BS!H19,BS!I19) -> 1.5788221 | J21: =IS!J5/AVERAGE(BS!I19,BS!J19) -> 1.5728429 | K21: =IS!K5/AVERAGE(BS!J19,BS!K19) -> 1.5709205 | L21: =IS!L5/AVERAGE(BS!K19,BS!L19) -> 1.5669731
A22: Financial Leverage Multiplier (Avg Total Assets / Avg Equity) | B22: x | D22: =AVERAGE(BS!C19,BS!D19)/AVERAGE(BS!C24,BS!D24) -> 2.2704243 | E22: =AVERAGE(BS!D19,BS!E19)/AVERAGE(BS!D24,BS!E24) -> 2.7502935 | F22: =AVERAGE(BS!E19,BS!F19)/AVERAGE(BS!E24,BS!F24) -> 3.4351715 | G22: =AVERAGE(BS!F19,BS!G19)/AVERAGE(BS!F24,BS!G24) -> 3.7035899 | H22: =AVERAGE(BS!G19,BS!H19)/AVERAGE(BS!G24,BS!H24) -> 3.6432038 | I22: =AVERAGE(BS!H19,BS!I19)/AVERAGE(BS!H24,BS!I24) -> 3.2910125 | J22: =AVERAGE(BS!I19,BS!J19)/AVERAGE(BS!I24,BS!J24) -> 2.9799682 | K22: =AVERAGE(BS!J19,BS!K19)/AVERAGE(BS!J24,BS!K24) -> 2.7136877 | L22: =AVERAGE(BS!K19,BS!L19)/AVERAGE(BS!K24,BS!L24) -> 2.4900446
A23: Decomposed ROE (Margin x Turnover x Leverage) | B23: % | D23: =D20*D21*D22 -> 0.3083298 | E23: =E20*E21*E22 -> 0.32830915 | F23: =F20*F21*F22 -> 0.31755246 | G23: =G20*G21*G22 -> 0.37128115 | H23: =H20*H21*H22 -> 0.32674907 | I23: =I20*I21*I22 -> 0.30314827 | J23: =J20*J21*J22 -> 0.28204826 | K23: =K20*K21*K22 -> 0.26169625 | L23: =L20*L21*L22 -> 0.24431241
A25: 4. BALANCE SHEET RESILIENCE & SOLVENCY METRICS
A26: Total Borrowings (Excl. Leases) | C26: =Schedules!C63 -> 518 | D26: =Schedules!D63 -> 2195 | E26: =Schedules!E63 -> 7838 | F26: =Schedules!F63 -> 10286 | G26: =Schedules!G63 -> 11378 | H26: =Schedules!H63 -> 11691.93 | I26: =Schedules!I63 -> 10842.989 | J26: =Schedules!J63 -> 9145.4514 | ... L26: =Schedules!L63 -> 3715.391
A27: Net Debt (incl. GoL & Leases) | C27: =Schedules!C95 -> 5687 | D27: =Schedules!D95 -> 5860 | E27: =Schedules!E95 -> 12336 | F27: =Schedules!F95 -> 17856 | G27: =Schedules!G95 -> 26455 | H27: =Schedules!H95 -> 29025.681 | I27: =Schedules!I95 -> 30617.666 | J27: =Schedules!J95 -> 31412.3 | ... L27: =Schedules!L95 -> 31379.188
A28: EBITDA | C28: =IS!C14 -> 3341 | D28: =IS!D14 -> 4879 | E28: =IS!E14 -> 5292 | F28: =IS!F14 -> 5694 | G28: =IS!G14 -> 8355 | H28: =IS!H14 -> 9921.5155 | I28: =IS!I14 -> 11647.446 | J28: =IS!J14 -> 13430.218 | ... L28: =IS!L14 -> 17030.376
A29: Net Debt / EBITDA | B29: x | C29: =Schedules!C96 -> 1.702185 | D29: =Schedules!D96 -> 1.2010658 | E29: =Schedules!E96 -> 2.3310658 | F29: =Schedules!F96 -> 3.1359326 | G29: =Schedules!G96 -> 3.1663674 | H29: =Schedules!H96 -> 2.9255289 | I29: =Schedules!I96 -> 2.6287021 | J29: =Schedules!J96 -> 2.338927 | ... L29: =Schedules!L96 -> 1.8425423
A30: Operating EBIT | C30: =IS!C17 -> 2942 | D30: =IS!D17 -> 4438 | E30: =IS!E17 -> 4708 | F30: =IS!F17 -> 5001 | G30: =IS!G17 -> 7529 | H30: =IS!H17 -> 8785.9555 | I30: =IS!I17 -> 10291.254 | J30: =IS!J17 -> 11832.33 | ... L30: =IS!L17 -> 14898.547
A31: Finance Costs | C31: =IS!C21 -> 218 | D31: =IS!D21 -> 300 | E31: =IS!E21 -> 619 | F31: =IS!F21 -> 953 | G31: =IS!G21 -> 1180 | H31: =IS!H21 -> 1411.524 | I31: =IS!I21 -> 1527.7601 | J31: =IS!J21 -> 1593.2602 | ... L31: =IS!L21 -> 1606.8726
A32: Interest Coverage (EBIT / Finance costs) | B32: x | C32: =Schedules!C97 -> 13.495413 | D32: =Schedules!D97 -> 14.793333 | E32: =Schedules!E97 -> 7.6058158 | F32: =Schedules!F97 -> 5.247639 | G32: =Schedules!G97 -> 6.3805085 | H32: =Schedules!H97 -> 6.2244464 | I32: =Schedules!I97 -> 6.7361716 | J32: =Schedules!J97 -> 7.4264889 | ... L32: =Schedules!L97 -> 9.2717667
A33: Altman Z''-Score Proxy (Emerging Markets) | B33: pts | C33: =3.25 + 6.56*(BS!C18-BS!C25-BS!C28)/BS!C19 + 3.26*(IS!C17/BS!C19) + 6.72*(IS!C27/BS!C19) + 1.05*(BS!C24/BS!C33) -> 10.067196 | D33: =3.25 + 6.56*(BS!D18-BS!D25-BS!D28)/BS!D19 + 3.26*(IS!D17/BS!D19) + 6.72*(IS!D27/BS!D19) + 1.05*(BS!D24/BS!D33) -> 10.038163 | E33: =3.25 + 6.56*(BS!E18-BS!E25-BS!E28)/BS!E19 + 3.26*(IS!E17/BS!E19) + 6.72*(IS!E27/BS!E19) + 1.05*(BS!E24/BS!E33) -> 8.327861 | F33: =3.25 + 6.56*(BS!F18-BS!F25-BS!F28)/BS!F19 + 3.26*(IS!F17/BS!F19) + 6.72*(IS!F27/BS!F19) + 1.05*(BS!F24/BS!F33) -> 8.2037482 | G33: =3.25 + 6.56*(BS!G18-BS!G25-BS!G28)/BS!G19 + 3.26*(IS!G17/BS!G19) + 6.72*(IS!G27/BS!G19) + 1.05*(BS!G24/BS!G33) -> 8.5436863 | H33: =3.25 + 6.56*(BS!H18-BS!H25-BS!H28)/BS!H19 + 3.26*(IS!H17/BS!H19) + 6.72*(IS!H27/BS!H19) + 1.05*(BS!H24/BS!H33) -> 8.7725432 | I33: =3.25 + 6.56*(BS!I18-BS!I25-BS!I28)/BS!I19 + 3.26*(IS!I17/BS!I19) + 6.72*(IS!I27/BS!I19) + 1.05*(BS!I24/BS!I33) -> 9.0976337 | J33: =3.25 + 6.56*(BS!J18-BS!J25-BS!J28)/BS!J19 + 3.26*(IS!J17/BS!J19) + 6.72*(IS!J27/BS!J19) + 1.05*(BS!J24/BS!J33) -> 9.4396323 | ... L33: =3.25 + 6.56*(BS!L18-BS!L25-BS!L28)/BS!L19 + 3.26*(IS!L17/BS!L19) + 6.72*(IS!L27/BS!L19) + 1.05*(BS!L24/BS!L33) -> 10.116233
A35: 5. CAPITAL ALLOCATION & REINVESTMENT EFFICIENCY
A36: Total Capital Expenditure | C36: =Schedules!C32 -> 224 | D36: =Schedules!D32 -> 432 | E36: =Schedules!E32 -> 691 | F36: =Schedules!F32 -> 494 | G36: =Schedules!G32 -> 902 | H36: =Schedules!H32 -> 1240.1894 | I36: =Schedules!I32 -> 1426.2179 | J36: =Schedules!J32 -> 1611.6262 | ... L36: =Schedules!L32 -> 2003.5737
A37: Depreciation & Amortisation | C37: =IS!C16 -> 399 | D37: =IS!D16 -> 441 | E37: =IS!E16 -> 584 | F37: =IS!F16 -> 693 | G37: =IS!G16 -> 826 | H37: =IS!H16 -> 1135.56 | I37: =IS!I16 -> 1356.1919 | J37: =IS!J16 -> 1597.8885 | ... L37: =IS!L16 -> 2131.8287
A38: Capex / Depreciation (Capacity Expansion Multiple) | B38: x | C38: =C36/C37 -> 0.56140351 | D38: =D36/D37 -> 0.97959184 | E38: =E36/E37 -> 1.1832192 | F38: =F36/F37 -> 0.71284271 | G38: =G36/G37 -> 1.0920097 | H38: =H36/H37 -> 1.0921391 | I38: =I36/I37 -> 1.0516343 | J38: =J36/J37 -> 1.0085974 | ... L38: =L36/L37 -> 0.93983804
A39: Free Cash Flow to Firm (CFO - Capex) | C39: =CF!C37 -> -948 | D39: =CF!D37 -> 938 | E39: =CF!E37 -> 1004 | F39: =CF!F37 -> -1035 | G39: =CF!G37 -> 4688 | H39: =CF!H37 -> 3193.7348 | I39: =CF!I37 -> 4925.9196 | J39: =CF!J37 -> 6152.9195 | ... L39: =CF!L37 -> 8309.2217

Sheet DCF
A1: DISCOUNTED CASH FLOW (DCF) VALUATION ENGINE
A2: 10-Year Integrated Framework: 5-Year Explicit Forecast + 5-Year Value-Driver Fade + Dual Terminal Value Approaches
A3: ="Active Scenario: "&Inputs!$C$6&" | Gold-on-Loan Accounting Mode: "&IF(Inputs!$C$7=1,"Operating (NWC)","Debt-Like (Deducted in Bridge)") -> Active Scenario: Base | Gold-on-Loan Accounting Mode: Operating (NWC)
A5: 1. WEIGHTED AVERAGE COST OF CAPITAL (WACC)
A6: Risk-free rate (10Y G-Sec) | B6: % | C6: =Inputs!$C$13 -> 0.065
A7: Equity risk premium | B7: % | C7: =Inputs!$C$14 -> 0.06
A8: Equity beta | B8: x | C8: =Inputs!$C$15 -> 0.9
A9: Cost of equity (CAPM: Rf + Beta * ERP) | B9: % | C9: =C6+C8*C7 -> 0.119
A10: Pre-tax marginal cost of debt | B10: % | C10: =Inputs!$C$16 -> 0.075
A11: Marginal corporate tax rate | B11: % | C11: =Inputs!L80 -> 0.254
A12: After-tax cost of debt (Kd * (1 - t)) | B12: % | C12: =C10*(1-C11) -> 0.05595
A13: Debt capital weighting (D / (D + E)) | B13: % | C13: =Inputs!$C$17 -> 0.1
A14: Equity capital weighting (E / (D + E)) | B14: % | C14: =1-C13 -> 0.9
A15: Weighted Average Cost of Capital (WACC) | B15: % | C15: =C14*C9+C13*C12 -> 0.112695
A17: 2. UNLEVERED FREE CASH FLOW (UFCF) - 5-YEAR EXPLICIT FORECAST | H17: FY27E | I17: FY28E | J17: FY29E | K17: FY30E | L17: FY31E
A18: Revenue from operations | H18: =IS!H5 -> 103349.12 | I18: =IS!I5 -> 118851.49 | J18: =IS!J5 -> 134302.18 | K18: =IS!K5 -> 150418.44 | L18: =IS!L5 -> 166964.47
A19: Operating EBITDA | H19: =IS!H14 -> 9921.5155 | I19: =IS!I14 -> 11647.446 | J19: =IS!J14 -> 13430.218 | K19: =IS!K14 -> 15192.263 | L19: =IS!L14 -> 17030.376
A20: Operating EBIT | H20: =IS!H17 -> 8785.9555 | I20: =IS!I17 -> 10291.254 | J20: =IS!J17 -> 11832.33 | K20: =IS!K17 -> 13335.739 | L20: =IS!L17 -> 14898.547
A21: Less: Gold-on-loan financing cost (deducted only if operating) | H21: =IF(Inputs!$C$7=1,Schedules!H74,0) -> 466.03 | I21: =IF(Inputs!$C$7=1,Schedules!I74,0) -> 536.72505 | J21: =IF(Inputs!$C$7=1,Schedules!J74,0) -> 616.46515 | K21: =IF(Inputs!$C$7=1,Schedules!K74,0) -> 695.73703 | L21: =IF(Inputs!$C$7=1,Schedules!L74,0) -> 778.25266
A22: Adjusted Operating EBIT | H22: =H20-H21 -> 8319.9255 | I22: =I20-I21 -> 9754.5289 | J22: =J20-J21 -> 11215.864 | K22: =K20-K21 -> 12640.002 | L22: =L20-L21 -> 14120.295
A23: Taxes on Adjusted EBIT (EBIT * t) | H23: =MAX(0,H22)*Inputs!H80 -> 2113.2611 | I23: =MAX(0,I22)*Inputs!I80 -> 2477.6503 | J23: =MAX(0,J22)*Inputs!J80 -> 2848.8296 | K23: =MAX(0,K22)*Inputs!K80 -> 3210.5605 | L23: =MAX(0,L22)*Inputs!L80 -> 3586.5549
A24: Net Operating Profit After Tax (NOPAT) | H24: =H22-H23 -> 6206.6644 | I24: =I22-I23 -> 7276.8786 | J24: =J22-J23 -> 8367.0349 | K24: =K22-K23 -> 9429.4416 | L24: =L22-L23 -> 10533.74
A25: Add: Depreciation & amortisation | H25: =IS!H16 -> 1135.56 | I25: =IS!I16 -> 1356.1919 | J25: =IS!J16 -> 1597.8885 | K25: =IS!K16 -> 1856.5236 | L25: =IS!L16 -> 2131.8287
A26: Less: Capital expenditure | H26: =Schedules!H32 -> 1240.1894 | I26: =Schedules!I32 -> 1426.2179 | J26: =Schedules!J32 -> 1611.6262 | K26: =Schedules!K32 -> 1805.0213 | L26: =Schedules!L32 -> 2003.5737
A27: Less: Ind AS 116 ROU new lease additions | H27: =Schedules!H43 -> 1033.4912 | I27: =Schedules!I43 -> 1188.5149 | J27: =Schedules!J43 -> 1343.0218 | K27: =Schedules!K43 -> 1504.1844 | L27: =Schedules!L43 -> 1669.6447
A28: Less: Change in Net Working Capital | H28: =Schedules!H26-IF(Inputs!$C$7=1,Schedules!H23-Schedules!G23,0) -> 3490.5159 | I28: =Schedules!I26-IF(Inputs!$C$7=1,Schedules!I23-Schedules!H23,0) -> 2934.3307 | J28: =Schedules!J26-IF(Inputs!$C$7=1,Schedules!J23-Schedules!I23,0) -> 2913.9513 | K28: =Schedules!K26-IF(Inputs!$C$7=1,Schedules!K23-Schedules!J23,0) -> 3030.5195 | L28: =Schedules!L26-IF(Inputs!$C$7=1,Schedules!L23-Schedules!K23,0) -> 3158.0249
A29: Unlevered Free Cash Flow (UFCF) | H29: =H24+H25-H26-H27-H28 -> 1578.0279 | I29: =I24+I25-I26-I27-I28 -> 3084.007 | J29: =J24+J25-J26-J27-J28 -> 4096.3241 | K29: =K24+K25-K26-K27-K28 -> 4946.2399 | L29: =L24+L25-L26-L27-L28 -> 5834.3253
A30: Discount period (years) | H30: =COLUMNS($H:H) -> 1 | I30: =COLUMNS($H:I) -> 2 | J30: =COLUMNS($H:J) -> 3 | K30: =COLUMNS($H:K) -> 4 | L30: =COLUMNS($H:L) -> 5
A31: Discount factor | H31: =1/(1+$C$15)^H30 -> 0.89871888 | I31: =1/(1+$C$15)^I30 -> 0.80769562 | J31: =1/(1+$C$15)^J30 -> 0.7258913 | K31: =1/(1+$C$15)^K30 -> 0.65237221 | L31: =1/(1+$C$15)^L30 -> 0.58629922
A32: Present Value of UFCF | H32: =H29*H31 -> 1418.2035 | I32: =I29*I31 -> 2490.9389 | J32: =J29*J31 -> 2973.4861 | K32: =K29*K31 -> 3226.7895 | L32: =L29*L31 -> 3420.6604
A34: 3. FADE PERIOD UFCF - VALUE-DRIVER FADE (Reinvestment = g / RONIC) | H34: FY32E | I34: FY33E | J34: FY34E | K34: FY35E | L34: FY36E
A35: Fade period year index | H35: =COLUMNS($H:H) -> 1 | I35: =COLUMNS($H:I) -> 2 | J35: =COLUMNS($H:J) -> 3 | K35: =COLUMNS($H:K) -> 4 | L35: =COLUMNS($H:L) -> 5
A36: NOPAT growth rate (fades to terminal g) | H36: =IS!$L$6+($C$45-IS!$L$6)*H35/6 -> 0.1 | I36: =IS!$L$6+($C$45-IS!$L$6)*I35/6 -> 0.09 | J36: =IS!$L$6+($C$45-IS!$L$6)*J35/6 -> 0.08 | K36: =IS!$L$6+($C$45-IS!$L$6)*K35/6 -> 0.07 | L36: =IS!$L$6+($C$45-IS!$L$6)*L35/6 -> 0.06
A37: Projected NOPAT | H37: =$L$24*(1+H36) -> 11587.114 | I37: =H37*(1+I36) -> 12629.954 | J37: =I37*(1+J36) -> 13640.351 | K37: =J37*(1+K36) -> 14595.175 | L37: =K37*(1+L36) -> 15470.886
A38: Reinvestment rate (g / RONIC) | H38: =H36/$C$46 -> 0.5 | I38: =I36/$C$46 -> 0.45 | J38: =J36/$C$46 -> 0.4 | K38: =K36/$C$46 -> 0.35 | L38: =L36/$C$46 -> 0.3
A39: Fade period Unlevered FCF | H39: =H37*(1-H38) -> 5793.557 | I39: =I37*(1-I38) -> 6946.4748 | J39: =J37*(1-J38) -> 8184.2103 | K39: =K37*(1-K38) -> 9486.8638 | L39: =L37*(1-L38) -> 10829.62
A40: Discount period (cumulative years) | H40: =$L$30+H35 -> 6 | I40: =$L$30+I35 -> 7 | J40: =$L$30+J35 -> 8 | K40: =$L$30+K35 -> 9 | L40: =$L$30+L35 -> 10
A41: Discount factor | H41: =1/(1+$C$15)^H40 -> 0.52691818 | I41: =1/(1+$C$15)^I40 -> 0.47355131 | J41: =1/(1+$C$15)^J40 -> 0.4255895 | K41: =1/(1+$C$15)^K40 -> 0.38248532 | L41: =1/(1+$C$15)^L40 -> 0.34374678
A42: Present Value of fade FCF | H42: =H39*H41 -> 3052.7305 | I42: =I39*I41 -> 3289.5123 | J42: =J39*J41 -> 3483.114 | K42: =K39*K41 -> 3628.5861 | L42: =L39*L41 -> 3722.6469
A44: 4. ENTERPRISE VALUE, EQUITY BRIDGE & GORDON GROWTH VALUE PER SHARE
A45: Terminal perpetual growth rate (g) | B45: % | C45: =Inputs!$C$18 -> 0.05
A46: Terminal RONIC | B46: % | C46: =Inputs!$C$19 -> 0.2
A47: Terminal year normalized NOPAT (FY37E) | C47: =$L$37*(1+C45) -> 16244.43
A48: Terminal Value at FY36E (Gordon Growth) | C48: =C47*(1-C45/C46)/($C$15-C45) -> 194326.86
A49: Present Value of Terminal Value | C49: =C48*$L$41 -> 66799.231
A50: Cumulative PV of 5-year explicit cash flows | C50: =SUM(H32:L32) -> 13530.078
A51: Cumulative PV of 5-year fade cash flows | C51: =SUM(H42:L42) -> 17176.59
A52: Enterprise Value (Gordon Growth) | C52: =C50+C51+C49 -> 97505.899
A53: Add: Cash & cash equivalents (FY26A) | C53: =BS!G17 -> 873
A54: Add: Treasury investments & deposits (FY26A) | C54: =BS!G16 -> 3293
A55: Add: Non-current investments at book (FY26A) | C55: =BS!G10 -> 1257
A56: Less: Total borrowings (FY26A) | C56: =-BS!G25 -> -11378
A57: Less: Lease liabilities (FY26A) | C57: =-BS!G27 -> -3173
A58: Less: Gold on loan (deducted if debt-like) | C58: =-IF(Inputs!$C$7=2,BS!G26,0) -> 0
A59: Less: Non-controlling interest (FY26A) | C59: =-Hist_Data!G53 -> 0
A60: Equity Value (Gordon Growth) | C60: =C52+SUM(C53:C59) -> 88377.899
A61: Diluted shares outstanding (crore) | B61: cr | C61: =Inputs!$C$10 -> 88.78
A62: Intrinsic Value per Share (Gordon Growth, INR) | B62: INR | C62: =C60/C61 -> 995.47082
A63: Current Market Price (CMP, INR) | B63: INR | C63: =Inputs!$C$9 -> 4798.5
A64: DCF Upside / (Downside) vs Market | B64: % | C64: =C62/C63-1 -> -0.79254542
A66: 5. EXIT MULTIPLE CROSS-CHECK (5-Year Explicit Horizon)
A67: Exit EV / EBITDA Multiple (FY31E) | B67: x | C67: =Inputs!$F$22 -> 25
A68: FY31E Operating EBITDA | C68: =$L$19 -> 17030.376
A69: Terminal Value at FY31E (Exit Multiple) | C69: =C67*C68 -> 425759.4
A70: Present Value of Exit TV | C70: =C69*$L$31 -> 249622.41
A71: Enterprise Value (Exit Multiple) | C71: =C50+C70 -> 263152.49
A72: Equity Value (Exit Multiple) | C72: =C71+SUM(C53:C59) -> 254024.49
A73: Value per Share (Exit Multiple, INR) | B73: INR | C73: =C72/C61 -> 2861.2805
A74: Multiple Upside / (Downside) vs Market | B74: % | C74: =C73/C63-1 -> -0.40371355
A76: 6. VALUATION DIAGNOSTICS & REVERSE DCF
A77: PV of Terminal Value % Enterprise Value | B77: % | C77: =C49/C52 -> 0.68507887
A78: Implied EV / FY27E EBITDA | B78: x | C78: =C52/$H$19 -> 9.8277223
A79: Implied P/E on FY27E EPS | B79: x | C79: =C62/IS!H31 -> 15.067601
A80: Implied EV / FY27E Revenue | B80: x | C80: =C52/$H$18 -> 0.94346134
A81: Net Bridge Items (Cash less Debt/Leases) | C81: =SUM(C53:C59) -> -9128
A82: Current Market Enterprise Value | C82: =C63*C61-C81 -> 435138.83
A83: Market-Implied EV / FY27E EBITDA | B83: x | C83: =C82/$H$19 -> 43.858101
A84: Reverse DCF: FY31E Exit Multiple implied by CMP | B84: x | C84: =(C82-C50)/$L$31/C68 -> 42.22465

Sheet Sensitivity
A1: VALUATION SENSITIVITY GRIDS (LIVE 2D MATRICES)
A2: Native formulas without Excel data tables. Center cells tie directly to the DCF sheet.
A3: WACC Step Increments | C3: 0.005
A4: Terminal Growth Step | C4: 0.005
A5: Exit Multiple Step | C5: 2.5
A8: A. Gordon Growth Value per Share (INR): WACC (down) vs Terminal Growth g (across)
A9: Offset from Center -> | C9: -2 | D9: -1 | E9: 0 | F9: 1 | G9: 2
B10: WACC \ g | C10: =DCF!$C$45+C9*$C$4 -> 0.04 | D10: =DCF!$C$45+D9*$C$4 -> 0.045 | E10: =DCF!$C$45+E9*$C$4 -> 0.05 | F10: =DCF!$C$45+F9*$C$4 -> 0.055 | G10: =DCF!$C$45+G9*$C$4 -> 0.06
A11: WACC Offset (rows) -> | B11: =DCF!$C$15+(-2)*$C$3 -> 0.102695 | C11: =(SUMPRODUCT(DCF!$H$29:$L$29/(1+$B11)^DCF!$H$30:$L$30)+SUMPRODUCT($H$33:$L$33/(1+$B11)^DCF!$H$40:$L$40)+$C$33/($B11-C$10)/(1+$B11)^DCF!$L$40+DCF!$C$81)/DCF!$C$61 -> 1118.4635 | D11: =(SUMPRODUCT(DCF!$H$29:$L$29/(1+$B11)^DCF!$H$30:$L$30)+SUMPRODUCT($H$36:$L$36/(1+$B11)^DCF!$H$40:$L$40)+$C$36/($B11-D$10)/(1+$B11)^DCF!$L$40+DCF!$C$81)/DCF!$C$61 -> 1175.126 | E11: =(SUMPRODUCT(DCF!$H$29:$L$29/(1+$B11)^DCF!$H$30:$L$30)+SUMPRODUCT($H$39:$L$39/(1+$B11)^DCF!$H$40:$L$40)+$C$39/($B11-E$10)/(1+$B11)^DCF!$L$40+DCF!$C$81)/DCF!$C$61 -> 1242.216 | F11: =(SUMPRODUCT(DCF!$H$29:$L$29/(1+$B11)^DCF!$H$30:$L$30)+SUMPRODUCT($H$42:$L$42/(1+$B11)^DCF!$H$40:$L$40)+$C$42/($B11-F$10)/(1+$B11)^DCF!$L$40+DCF!$C$81)/DCF!$C$61 -> 1323.0086 | G11: =(SUMPRODUCT(DCF!$H$29:$L$29/(1+$B11)^DCF!$H$30:$L$30)+SUMPRODUCT($H$45:$L$45/(1+$B11)^DCF!$H$40:$L$40)+$C$45/($B11-G$10)/(1+$B11)^DCF!$L$40+DCF!$C$81)/DCF!$C$61 -> 1422.3125
B12: =DCF!$C$15+(-1)*$C$3 -> 0.107695 | C12: =(SUMPRODUCT(DCF!$H$29:$L$29/(1+$B12)^DCF!$H$30:$L$30)+SUMPRODUCT($H$33:$L$33/(1+$B12)^DCF!$H$40:$L$40)+$C$33/($B12-C$10)/(1+$B12)^DCF!$L$40+DCF!$C$81)/DCF!$C$61 -> 1010.7683 | D12: =(SUMPRODUCT(DCF!$H$29:$L$29/(1+$B12)^DCF!$H$30:$L$30)+SUMPRODUCT($H$36:$L$36/(1+$B12)^DCF!$H$40:$L$40)+$C$36/($B12-D$10)/(1+$B12)^DCF!$L$40+DCF!$C$81)/DCF!$C$61 -> 1055.57 | E12: =(SUMPRODUCT(DCF!$H$29:$L$29/(1+$B12)^DCF!$H$30:$L$30)+SUMPRODUCT($H$39:$L$39/(1+$B12)^DCF!$H$40:$L$40)+$C$39/($B12-E$10)/(1+$B12)^DCF!$L$40+DCF!$C$81)/DCF!$C$61 -> 1107.852 | F12: =(SUMPRODUCT(DCF!$H$29:$L$29/(1+$B12)^DCF!$H$30:$L$30)+SUMPRODUCT($H$42:$L$42/(1+$B12)^DCF!$H$40:$L$40)+$C$42/($B12-F$10)/(1+$B12)^DCF!$L$40+DCF!$C$81)/DCF!$C$61 -> 1169.7396 | G12: =(SUMPRODUCT(DCF!$H$29:$L$29/(1+$B12)^DCF!$H$30:$L$30)+SUMPRODUCT($H$45:$L$45/(1+$B12)^DCF!$H$40:$L$40)+$C$45/($B12-G$10)/(1+$B12)^DCF!$L$40+DCF!$C$81)/DCF!$C$61 -> 1244.2495
B13: =DCF!$C$15+(0)*$C$3 -> 0.112695 | C13: =(SUMPRODUCT(DCF!$H$29:$L$29/(1+$B13)^DCF!$H$30:$L$30)+SUMPRODUCT($H$33:$L$33/(1+$B13)^DCF!$H$40:$L$40)+$C$33/($B13-C$10)/(1+$B13)^DCF!$L$40+DCF!$C$81)/DCF!$C$61 -> 918.4403 | D13: =(SUMPRODUCT(DCF!$H$29:$L$29/(1+$B13)^DCF!$H$30:$L$30)+SUMPRODUCT($H$36:$L$36/(1+$B13)^DCF!$H$40:$L$40)+$C$36/($B13-D$10)/(1+$B13)^DCF!$L$40+DCF!$C$81)/DCF!$C$61 -> 954.22729 | E13: =(SUMPRODUCT(DCF!$H$29:$L$29/(1+$B13)^DCF!$H$30:$L$30)+SUMPRODUCT($H$39:$L$39/(1+$B13)^DCF!$H$40:$L$40)+$C$39/($B13-E$10)/(1+$B13)^DCF!$L$40+DCF!$C$81)/DCF!$C$61 -> 995.47082 | F13: =(SUMPRODUCT(DCF!$H$29:$L$29/(1+$B13)^DCF!$H$30:$L$30)+SUMPRODUCT($H$42:$L$42/(1+$B13)^DCF!$H$40:$L$40)+$C$42/($B13-F$10)/(1+$B13)^DCF!$L$40+DCF!$C$81)/DCF!$C$61 -> 1043.5861 | G13: =(SUMPRODUCT(DCF!$H$29:$L$29/(1+$B13)^DCF!$H$30:$L$30)+SUMPRODUCT($H$45:$L$45/(1+$B13)^DCF!$H$40:$L$40)+$C$45/($B13-G$10)/(1+$B13)^DCF!$L$40+DCF!$C$81)/DCF!$C$61 -> 1100.5252
B14: =DCF!$C$15+(1)*$C$3 -> 0.117695 | C14: =(SUMPRODUCT(DCF!$H$29:$L$29/(1+$B14)^DCF!$H$30:$L$30)+SUMPRODUCT($H$33:$L$33/(1+$B14)^DCF!$H$40:$L$40)+$C$33/($B14-C$10)/(1+$B14)^DCF!$L$40+DCF!$C$81)/DCF!$C$61 -> 838.49088 | D14: =(SUMPRODUCT(DCF!$H$29:$L$29/(1+$B14)^DCF!$H$30:$L$30)+SUMPRODUCT($H$36:$L$36/(1+$B14)^DCF!$H$40:$L$40)+$C$36/($B14-D$10)/(1+$B14)^DCF!$L$40+DCF!$C$81)/DCF!$C$61 -> 867.31797 | E14: =(SUMPRODUCT(DCF!$H$29:$L$29/(1+$B14)^DCF!$H$30:$L$30)+SUMPRODUCT($H$39:$L$39/(1+$B14)^DCF!$H$40:$L$40)+$C$39/($B14-E$10)/(1+$B14)^DCF!$L$40+DCF!$C$81)/DCF!$C$61 -> 900.17989 | F14: =(SUMPRODUCT(DCF!$H$29:$L$29/(1+$B14)^DCF!$H$30:$L$30)+SUMPRODUCT($H$42:$L$42/(1+$B14)^DCF!$H$40:$L$40)+$C$42/($B14-F$10)/(1+$B14)^DCF!$L$40+DCF!$C$81)/DCF!$C$61 -> 938.03894 | G14: =(SUMPRODUCT(DCF!$H$29:$L$29/(1+$B14)^DCF!$H$30:$L$30)+SUMPRODUCT($H$45:$L$45/(1+$B14)^DCF!$H$40:$L$40)+$C$45/($B14-G$10)/(1+$B14)^DCF!$L$40+DCF!$C$81)/DCF!$C$61 -> 982.19093
B15: =DCF!$C$15+(2)*$C$3 -> 0.122695 | C15: =(SUMPRODUCT(DCF!$H$29:$L$29/(1+$B15)^DCF!$H$30:$L$30)+SUMPRODUCT($H$33:$L$33/(1+$B15)^DCF!$H$40:$L$40)+$C$33/($B15-C$10)/(1+$B15)^DCF!$L$40+DCF!$C$81)/DCF!$C$61 -> 768.65509 | D15: =(SUMPRODUCT(DCF!$H$29:$L$29/(1+$B15)^DCF!$H$30:$L$30)+SUMPRODUCT($H$36:$L$36/(1+$B15)^DCF!$H$40:$L$40)+$C$36/($B15-D$10)/(1+$B15)^DCF!$L$40+DCF!$C$81)/DCF!$C$61 -> 792.03608 | E15: =(SUMPRODUCT(DCF!$H$29:$L$29/(1+$B15)^DCF!$H$30:$L$30)+SUMPRODUCT($H$39:$L$39/(1+$B15)^DCF!$H$40:$L$40)+$C$39/($B15-E$10)/(1+$B15)^DCF!$L$40+DCF!$C$81)/DCF!$C$61 -> 818.43359 | F15: =(SUMPRODUCT(DCF!$H$29:$L$29/(1+$B15)^DCF!$H$30:$L$30)+SUMPRODUCT($H$42:$L$42/(1+$B15)^DCF!$H$40:$L$40)+$C$42/($B15-F$10)/(1+$B15)^DCF!$L$40+DCF!$C$81)/DCF!$C$61 -> 848.51334 | G15: =(SUMPRODUCT(DCF!$H$29:$L$29/(1+$B15)^DCF!$H$30:$L$30)+SUMPRODUCT($H$45:$L$45/(1+$B15)^DCF!$H$40:$L$40)+$C$45/($B15-G$10)/(1+$B15)^DCF!$L$40+DCF!$C$81)/DCF!$C$61 -> 883.15333
A18: B. Exit Multiple Value per Share (INR): WACC (down) vs FY31E EV/EBITDA (across)
A19: Offset from Center -> | C19: -2 | D19: -1 | E19: 0 | F19: 1 | G19: 2
B20: WACC \ Mult | C20: =DCF!$C$67+C19*$C$5 -> 20 | D20: =DCF!$C$67+D19*$C$5 -> 22.5 | E20: =DCF!$C$67+E19*$C$5 -> 25 | F20: =DCF!$C$67+F19*$C$5 -> 27.5 | G20: =DCF!$C$67+G19*$C$5 -> 30
A21: WACC Offset (rows) -> | B21: =DCF!$C$15+(-2)*$C$3 -> 0.102695 | C21: =(SUMPRODUCT(DCF!$H$29:$L$29/(1+$B21)^DCF!$H$30:$L$30)+DCF!$C$68*C$20/(1+$B21)^DCF!$L$30+DCF!$C$81)/DCF!$C$61 -> 2407.4927 | D21: =(SUMPRODUCT(DCF!$H$29:$L$29/(1+$B21)^DCF!$H$30:$L$30)+DCF!$C$68*D$20/(1+$B21)^DCF!$L$30+DCF!$C$81)/DCF!$C$61 -> 2701.6449 | E21: =(SUMPRODUCT(DCF!$H$29:$L$29/(1+$B21)^DCF!$H$30:$L$30)+DCF!$C$68*E$20/(1+$B21)^DCF!$L$30+DCF!$C$81)/DCF!$C$61 -> 2995.7971 | F21: =(SUMPRODUCT(DCF!$H$29:$L$29/(1+$B21)^DCF!$H$30:$L$30)+DCF!$C$68*F$20/(1+$B21)^DCF!$L$30+DCF!$C$81)/DCF!$C$61 -> 3289.9493 | G21: =(SUMPRODUCT(DCF!$H$29:$L$29/(1+$B21)^DCF!$H$30:$L$30)+DCF!$C$68*G$20/(1+$B21)^DCF!$L$30+DCF!$C$81)/DCF!$C$61 -> 3584.1014
B22: =DCF!$C$15+(-1)*$C$3 -> 0.107695 | C22: =(SUMPRODUCT(DCF!$H$29:$L$29/(1+$B22)^DCF!$H$30:$L$30)+DCF!$C$68*C$20/(1+$B22)^DCF!$L$30+DCF!$C$81)/DCF!$C$61 -> 2352.488 | D22: =(SUMPRODUCT(DCF!$H$29:$L$29/(1+$B22)^DCF!$H$30:$L$30)+DCF!$C$68*D$20/(1+$B22)^DCF!$L$30+DCF!$C$81)/DCF!$C$61 -> 2640.061 | E22: =(SUMPRODUCT(DCF!$H$29:$L$29/(1+$B22)^DCF!$H$30:$L$30)+DCF!$C$68*E$20/(1+$B22)^DCF!$L$30+DCF!$C$81)/DCF!$C$61 -> 2927.634 | F22: =(SUMPRODUCT(DCF!$H$29:$L$29/(1+$B22)^DCF!$H$30:$L$30)+DCF!$C$68*F$20/(1+$B22)^DCF!$L$30+DCF!$C$81)/DCF!$C$61 -> 3215.207 | G22: =(SUMPRODUCT(DCF!$H$29:$L$29/(1+$B22)^DCF!$H$30:$L$30)+DCF!$C$68*G$20/(1+$B22)^DCF!$L$30+DCF!$C$81)/DCF!$C$61 -> 3502.7801
B23: =DCF!$C$15+(0)*$C$3 -> 0.112695 | C23: =(SUMPRODUCT(DCF!$H$29:$L$29/(1+$B23)^DCF!$H$30:$L$30)+DCF!$C$68*C$20/(1+$B23)^DCF!$L$30+DCF!$C$81)/DCF!$C$61 -> 2298.9412 | D23: =(SUMPRODUCT(DCF!$H$29:$L$29/(1+$B23)^DCF!$H$30:$L$30)+DCF!$C$68*D$20/(1+$B23)^DCF!$L$30+DCF!$C$81)/DCF!$C$61 -> 2580.1109 | E23: =(SUMPRODUCT(DCF!$H$29:$L$29/(1+$B23)^DCF!$H$30:$L$30)+DCF!$C$68*E$20/(1+$B23)^DCF!$L$30+DCF!$C$81)/DCF!$C$61 -> 2861.2805 | F23: =(SUMPRODUCT(DCF!$H$29:$L$29/(1+$B23)^DCF!$H$30:$L$30)+DCF!$C$68*F$20/(1+$B23)^DCF!$L$30+DCF!$C$81)/DCF!$C$61 -> 3142.4502 | G23: =(SUMPRODUCT(DCF!$H$29:$L$29/(1+$B23)^DCF!$H$30:$L$30)+DCF!$C$68*G$20/(1+$B23)^DCF!$L$30+DCF!$C$81)/DCF!$C$61 -> 3423.6198
B24: =DCF!$C$15+(1)*$C$3 -> 0.117695 | C24: =(SUMPRODUCT(DCF!$H$29:$L$29/(1+$B24)^DCF!$H$30:$L$30)+DCF!$C$68*C$20/(1+$B24)^DCF!$L$30+DCF!$C$81)/DCF!$C$61 -> 2246.8074 | D24: =(SUMPRODUCT(DCF!$H$29:$L$29/(1+$B24)^DCF!$H$30:$L$30)+DCF!$C$68*D$20/(1+$B24)^DCF!$L$30+DCF!$C$81)/DCF!$C$61 -> 2521.744 | E24: =(SUMPRODUCT(DCF!$H$29:$L$29/(1+$B24)^DCF!$H$30:$L$30)+DCF!$C$68*E$20/(1+$B24)^DCF!$L$30+DCF!$C$81)/DCF!$C$61 -> 2796.6806 | F24: =(SUMPRODUCT(DCF!$H$29:$L$29/(1+$B24)^DCF!$H$30:$L$30)+DCF!$C$68*F$20/(1+$B24)^DCF!$L$30+DCF!$C$81)/DCF!$C$61 -> 3071.6172 | G24: =(SUMPRODUCT(DCF!$H$29:$L$29/(1+$B24)^DCF!$H$30:$L$30)+DCF!$C$68*G$20/(1+$B24)^DCF!$L$30+DCF!$C$81)/DCF!$C$61 -> 3346.5538
B25: =DCF!$C$15+(2)*$C$3 -> 0.122695 | C25: =(SUMPRODUCT(DCF!$H$29:$L$29/(1+$B25)^DCF!$H$30:$L$30)+DCF!$C$68*C$20/(1+$B25)^DCF!$L$30+DCF!$C$81)/DCF!$C$61 -> 2196.043 | D25: =(SUMPRODUCT(DCF!$H$29:$L$29/(1+$B25)^DCF!$H$30:$L$30)+DCF!$C$68*D$20/(1+$B25)^DCF!$L$30+DCF!$C$81)/DCF!$C$61 -> 2464.9117 | E25: =(SUMPRODUCT(DCF!$H$29:$L$29/(1+$B25)^DCF!$H$30:$L$30)+DCF!$C$68*E$20/(1+$B25)^DCF!$L$30+DCF!$C$81)/DCF!$C$61 -> 2733.7803 | F25: =(SUMPRODUCT(DCF!$H$29:$L$29/(1+$B25)^DCF!$H$30:$L$30)+DCF!$C$68*F$20/(1+$B25)^DCF!$L$30+DCF!$C$81)/DCF!$C$61 -> 3002.649 | G25: =(SUMPRODUCT(DCF!$H$29:$L$29/(1+$B25)^DCF!$H$30:$L$30)+DCF!$C$68*G$20/(1+$B25)^DCF!$L$30+DCF!$C$81)/DCF!$C$61 -> 3271.5176
A26: Market Reference Price (CMP, INR) | C26: =Inputs!$C$9 -> 4798.5
A29: CALCULATION ENGINE: Fade Period Cash Flows for Terminal Growth Variations
C30: Terminal Cash Flow | H30: FY32E | I30: FY33E | J30: FY34E | K30: FY35E | L30: FY36E
A31: ="g = "&TEXT($C$10,"0.0%")&": NOPAT growth" -> g = 4.0%: NOPAT growth | H31: =IS!$L$6+($C$10-IS!$L$6)*1/6 -> 0.098333333 | I31: =IS!$L$6+($C$10-IS!$L$6)*2/6 -> 0.086666667 | J31: =IS!$L$6+($C$10-IS!$L$6)*3/6 -> 0.075 | K31: =IS!$L$6+($C$10-IS!$L$6)*4/6 -> 0.063333333 | L31: =IS!$L$6+($C$10-IS!$L$6)*5/6 -> 0.051666667
A32: NOPAT | H32: =DCF!$L$24*(1+H31) -> 11569.558 | I32: =H32*(1+I31) -> 12572.253 | J32: =I32*(1+J31) -> 13515.172 | K32: =J32*(1+K31) -> 14371.133 | L32: =K32*(1+L31) -> 15113.641
A33: Unlevered Free Cash Flow | C33: =L32*(1+$C$10)*(1-$C$10/DCF!$C$46) -> 12574.549 | H33: =H32*(1-H31/DCF!$C$46) -> 5881.1918 | I33: =I32*(1-I31/DCF!$C$46) -> 7124.2765 | J33: =J32*(1-J31/DCF!$C$46) -> 8446.9823 | K33: =K32*(1-K31/DCF!$C$46) -> 9820.2739 | L33: =L32*(1-L31/DCF!$C$46) -> 11209.284
A34: ="g = "&TEXT($D$10,"0.0%")&": NOPAT growth" -> g = 4.5%: NOPAT growth | H34: =IS!$L$6+($D$10-IS!$L$6)*1/6 -> 0.099166667 | I34: =IS!$L$6+($D$10-IS!$L$6)*2/6 -> 0.088333333 | J34: =IS!$L$6+($D$10-IS!$L$6)*3/6 -> 0.0775 | K34: =IS!$L$6+($D$10-IS!$L$6)*4/6 -> 0.066666667 | L34: =IS!$L$6+($D$10-IS!$L$6)*5/6 -> 0.055833333
A35: NOPAT | H35: =DCF!$L$24*(1+H34) -> 11578.336 | I35: =H35*(1+I34) -> 12601.089 | J35: =I35*(1+J34) -> 13577.673 | K35: =J35*(1+K34) -> 14482.851 | L35: =K35*(1+L34) -> 15291.477
A36: Unlevered Free Cash Flow | C36: =L35*(1+$D$10)*(1-$D$10/DCF!$C$46) -> 12384.185 | H36: =H35*(1-H34/DCF!$C$46) -> 5837.411 | I36: =I35*(1-I34/DCF!$C$46) -> 7035.6079 | J36: =J35*(1-J34/DCF!$C$46) -> 8316.3248 | K36: =K35*(1-K34/DCF!$C$46) -> 9655.2343 | L36: =L35*(1-L34/DCF!$C$46) -> 11022.607
A37: ="g = "&TEXT($E$10,"0.0%")&": NOPAT growth" -> g = 5.0%: NOPAT growth | H37: =IS!$L$6+($E$10-IS!$L$6)*1/6 -> 0.1 | I37: =IS!$L$6+($E$10-IS!$L$6)*2/6 -> 0.09 | J37: =IS!$L$6+($E$10-IS!$L$6)*3/6 -> 0.08 | K37: =IS!$L$6+($E$10-IS!$L$6)*4/6 -> 0.07 | L37: =IS!$L$6+($E$10-IS!$L$6)*5/6 -> 0.06
A38: NOPAT | H38: =DCF!$L$24*(1+H37) -> 11587.114 | I38: =H38*(1+I37) -> 12629.954 | J38: =I38*(1+J37) -> 13640.351 | K38: =J38*(1+K37) -> 14595.175 | L38: =K38*(1+L37) -> 15470.886
A39: Unlevered Free Cash Flow | C39: =L38*(1+$E$10)*(1-$E$10/DCF!$C$46) -> 12183.322 | H39: =H38*(1-H37/DCF!$C$46) -> 5793.557 | I39: =I38*(1-I37/DCF!$C$46) -> 6946.4748 | J39: =J38*(1-J37/DCF!$C$46) -> 8184.2103 | K39: =K38*(1-K37/DCF!$C$46) -> 9486.8638 | L39: =L38*(1-L37/DCF!$C$46) -> 10829.62
A40: ="g = "&TEXT($F$10,"0.0%")&": NOPAT growth" -> g = 5.5%: NOPAT growth | H40: =IS!$L$6+($F$10-IS!$L$6)*1/6 -> 0.10083333 | I40: =IS!$L$6+($F$10-IS!$L$6)*2/6 -> 0.091666667 | J40: =IS!$L$6+($F$10-IS!$L$6)*3/6 -> 0.0825 | K40: =IS!$L$6+($F$10-IS!$L$6)*4/6 -> 0.073333333 | L40: =IS!$L$6+($F$10-IS!$L$6)*5/6 -> 0.064166667
A41: NOPAT | H41: =DCF!$L$24*(1+H40) -> 11595.892 | I41: =H41*(1+I40) -> 12658.849 | J41: =I41*(1+J40) -> 13703.204 | K41: =J41*(1+K40) -> 14708.105 | L41: =K41*(1+L40) -> 15651.876
A42: Unlevered Free Cash Flow | C42: =L41*(1+$F$10)*(1-$F$10/DCF!$C$46) -> 11971.728 | H42: =H41*(1-H40/DCF!$C$46) -> 5749.6298 | I42: =I41*(1-I40/DCF!$C$46) -> 6856.8764 | J42: =J41*(1-J40/DCF!$C$46) -> 8050.6323 | K42: =K41*(1-K40/DCF!$C$46) -> 9315.1335 | L42: =L41*(1-L40/DCF!$C$46) -> 10630.232
A43: ="g = "&TEXT($G$10,"0.0%")&": NOPAT growth" -> g = 6.0%: NOPAT growth | H43: =IS!$L$6+($G$10-IS!$L$6)*1/6 -> 0.10166667 | I43: =IS!$L$6+($G$10-IS!$L$6)*2/6 -> 0.093333333 | J43: =IS!$L$6+($G$10-IS!$L$6)*3/6 -> 0.085 | K43: =IS!$L$6+($G$10-IS!$L$6)*4/6 -> 0.076666667 | L43: =IS!$L$6+($G$10-IS!$L$6)*5/6 -> 0.068333333
A44: NOPAT | H44: =DCF!$L$24*(1+H43) -> 11604.67 | I44: =H44*(1+I43) -> 12687.773 | J44: =I44*(1+J43) -> 13766.233 | K44: =J44*(1+K43) -> 14821.645 | L44: =K44*(1+L43) -> 15834.457
A45: Unlevered Free Cash Flow | C45: =L44*(1+$G$10)*(1-$G$10/DCF!$C$46) -> 11749.167 | H45: =H44*(1-H43/DCF!$C$46) -> 5705.6295 | I45: =I44*(1-I43/DCF!$C$46) -> 6766.8121 | J45: =J44*(1-J43/DCF!$C$46) -> 7915.5842 | K45: =K44*(1-K43/DCF!$C$46) -> 9140.0142 | L45: =L44*(1-L43/DCF!$C$46) -> 10424.351

Sheet Scenarios
A1: SCENARIO OUTPUT COMPARISON (BEAR / BASE / BULL)
A2: Real-time scenario engine summary. Columns update dynamically based on model runs.
A4: Metric | B4: Unit | C4: Bear Case | D4: Base Case | E4: Bull Case | F4: Active Live Model
A5: FY31E Revenue | B5: INR cr | F5: =IS!L5 -> 166964.47
A6: FY26A-FY31E Revenue CAGR | B6: % | F6: =(IS!L5/IS!G5)^(1/5)-1 -> 0.1377317
A7: FY31E EBITDA Margin | B7: % | F7: =IS!L15 -> 0.102
A8: FY31E EBIT Margin | B8: % | F8: =IS!L18 -> 0.089231843
A9: FY31E Profit After Tax | B9: INR cr | F9: =IS!L27 -> 10454.444
A10: FY31E Basic EPS | B10: INR | F10: =IS!L31 -> 117.75674
A11: Cumulative CFO (FY27E-FY31E) | B11: INR cr | F11: =SUM(CF!H17:L17) -> 37881.169
A12: Cumulative Free Cash Flow (FY27E-FY31E) | B12: INR cr | F12: =SUM(CF!H37:L37) -> 29794.54
A13: FY31E Net Debt (incl. GoL & Leases) | B13: INR cr | F13: =Schedules!L95 -> 31379.188
A14: Cost of Capital (WACC) | B14: % | F14: =DCF!$C$15 -> 0.112695
A15: Enterprise Value (Gordon Growth) | B15: INR cr | F15: =DCF!$C$52 -> 97505.899
A16: Intrinsic Value per Share (Gordon) | B16: INR | F16: =DCF!$C$62 -> 995.47082
A17: Intrinsic Value per Share (Exit Multiple) | B17: INR | F17: =DCF!$C$73 -> 2861.2805
A18: DCF Upside / (Downside) vs Market | B18: % | F18: =DCF!$C$64 -> -0.79254542
A19: Exit Multiple Upside vs Market | B19: % | F19: =DCF!$C$74 -> -0.40371355

Sheet Checks
A1: MODEL AUDIT, BALANCE & INTEGRITY TESTS
A2: Institutional Self-Testing Suite. Absolute variance shown (zero = pass). Conditional formatting flags errors.
A4: Audit Check Description | B4: Tolerance | C4: FY22A | D4: FY23A | E4: FY24A | F4: FY25A | G4: FY26A | H4: FY27E | I4: FY28E | J4: FY29E | K4: FY30E | L4: FY31E | M4: Audit Result
A5: Balance Sheet Balances: Assets - Liabilities & Equity = 0 | B5: 0.05 | C5: =BS!C36 -> 0 | D5: =BS!D36 -> 0 | E5: =BS!E36 -> 0 | F5: =BS!F36 -> 0 | G5: =BS!G36 -> 0 | H5: =BS!H36 -> 0 | I5: =BS!I36 -> 0 | J5: =BS!J36 -> 0 | ... L5: =BS!L36 -> 0 | M5: =IF(SUMPRODUCT(ABS(C5:L5))<=B5,"OK","ERROR") -> OK
A6: Cash Flow Closing Cash = Balance Sheet Cash | B6: 0.05 | C6: =CF!C35 -> 0 | D6: =CF!D35 -> 0 | E6: =CF!E35 -> 0 | F6: =CF!F35 -> 0 | G6: =CF!G35 -> 0 | H6: =CF!H35 -> 0 | I6: =CF!I35 -> 0 | J6: =CF!J35 -> 0 | ... L6: =CF!L35 -> 0 | M6: =IF(SUMPRODUCT(ABS(C6:L6))<=B6,"OK","ERROR") -> OK
A7: Historical IS PAT = Reported Statutory PAT | B7: 0.05 | C7: =IS!C27-Hist_Data!C25 -> 0 | D7: =IS!D27-Hist_Data!D25 -> 0 | E7: =IS!E27-Hist_Data!E25 -> 0 | F7: =IS!F27-Hist_Data!F25 -> 0 | G7: =IS!G27-Hist_Data!G25 -> 0 | M7: =IF(SUMPRODUCT(ABS(C7:L7))<=B7,"OK","ERROR") -> OK
A8: Historical IS PBT = Reported Statutory PBT | B8: 0.05 | C8: =IS!C24-Hist_Data!C21 -> 0 | D8: =IS!D24-Hist_Data!D21 -> 0 | E8: =IS!E24-Hist_Data!E21 -> 0 | F8: =IS!F24-Hist_Data!F21 -> 0 | G8: =IS!G24-Hist_Data!G21 -> 0 | M8: =IF(SUMPRODUCT(ABS(C8:L8))<=B8,"OK","ERROR") -> OK
A9: Historical BS Assets = Reported Statutory Assets | B9: 0.05 | C9: =BS!C19-Hist_Data!C72 -> 0 | D9: =BS!D19-Hist_Data!D72 -> 0 | E9: =BS!E19-Hist_Data!E72 -> 0 | F9: =BS!F19-Hist_Data!F72 -> 0 | G9: =BS!G19-Hist_Data!G72 -> 0 | M9: =IF(SUMPRODUCT(ABS(C9:L9))<=B9,"OK","ERROR") -> OK
A10: Historical BS Liabilities = Reported Statutory Liabilities | B10: 0.05 | C10: =BS!C33-Hist_Data!C76 -> 0 | D10: =BS!D33-Hist_Data!D76 -> 0 | E10: =BS!E33-Hist_Data!E76 -> 0 | F10: =BS!F33-Hist_Data!F76 -> 0 | G10: =BS!G33-Hist_Data!G76 -> 0 | M10: =IF(SUMPRODUCT(ABS(C10:L10))<=B10,"OK","ERROR") -> OK
A11: Historical CF CFO = Reported Statutory CFO | B11: 0.05 | C11: =CF!C17-Hist_Data!C94 -> 0 | D11: =CF!D17-Hist_Data!D94 -> 0 | E11: =CF!E17-Hist_Data!E94 -> 0 | F11: =CF!F17-Hist_Data!F94 -> 0 | G11: =CF!G17-Hist_Data!G94 -> 0 | M11: =IF(SUMPRODUCT(ABS(C11:L11))<=B11,"OK","ERROR") -> OK
A12: Historical Net Cash Delta = Reported Net Cash Delta | B12: 0.05 | C12: =CF!C31-Hist_Data!C98 -> 0 | D12: =CF!D31-Hist_Data!D98 -> 0 | E12: =CF!E31-Hist_Data!E98 -> 0 | F12: =CF!F31-Hist_Data!F98 -> 0 | G12: =CF!G31-Hist_Data!G98 -> 0 | M12: =IF(SUMPRODUCT(ABS(C12:L12))<=B12,"OK","ERROR") -> OK
A13: PP&E Schedule Closing Balance = Balance Sheet PP&E | B13: 0.05 | H13: =Schedules!H39-BS!H6 -> 0 | I13: =Schedules!I39-BS!I6 -> 0 | J13: =Schedules!J39-BS!J6 -> 0 | K13: =Schedules!K39-BS!K6 -> 0 | L13: =Schedules!L39-BS!L6 -> 0 | M13: =IF(SUMPRODUCT(ABS(C13:L13))<=B13,"OK","ERROR") -> OK
A14: Equity Schedule Closing Balance = Balance Sheet Other Equity | B14: 0.05 | H14: =Schedules!H90-BS!H23 -> 0 | I14: =Schedules!I90-BS!I23 -> 0 | J14: =Schedules!J90-BS!J23 -> 0 | K14: =Schedules!K90-BS!K23 -> 0 | L14: =Schedules!L90-BS!L23 -> 0 | M14: =IF(SUMPRODUCT(ABS(C14:L14))<=B14,"OK","ERROR") -> OK
A15: Lease Schedule Closing = Balance Sheet Lease Liabilities | B15: 0.05 | H15: =Schedules!H70-BS!H27 -> 0 | I15: =Schedules!I70-BS!I27 -> 0 | J15: =Schedules!J70-BS!J27 -> 0 | K15: =Schedules!K70-BS!K27 -> 0 | L15: =Schedules!L70-BS!L27 -> 0 | M15: =IF(SUMPRODUCT(ABS(C15:L15))<=B15,"OK","ERROR") -> OK
A16: Debt Schedule Total = Balance Sheet Borrowings | B16: 0.05 | H16: =Schedules!H63-BS!H25 -> 0 | I16: =Schedules!I63-BS!I25 -> 0 | J16: =Schedules!J63-BS!J25 -> 0 | K16: =Schedules!K63-BS!K25 -> 0 | L16: =Schedules!L63-BS!L25 -> 0 | M16: =IF(SUMPRODUCT(ABS(C16:L16))<=B16,"OK","ERROR") -> OK
A17: Gold on Loan Schedule = Balance Sheet Gold on Loan | B17: 0.05 | H17: =Schedules!H23-BS!H26 -> 0 | I17: =Schedules!I23-BS!I26 -> 0 | J17: =Schedules!J23-BS!J26 -> 0 | K17: =Schedules!K23-BS!K26 -> 0 | L17: =Schedules!L23-BS!L26 -> 0 | M17: =IF(SUMPRODUCT(ABS(C17:L17))<=B17,"OK","ERROR") -> OK
A18: Minimum Operational Cash Requirement Maintained | B18: 0.05 | H18: =MIN(0,BS!H17-Schedules!H58) -> 0 | I18: =MIN(0,BS!I17-Schedules!I58) -> 0 | J18: =MIN(0,BS!J17-Schedules!J58) -> 0 | K18: =MIN(0,BS!K17-Schedules!K58) -> -1.8189894e-12 | L18: =MIN(0,BS!L17-Schedules!L58) -> 0 | M18: =IF(SUMPRODUCT(ABS(C18:L18))<=B18,"OK","ERROR") -> OK
A19: Revolver Short-Term Debt Non-Negative | B19: 0.05 | H19: =MIN(0,Schedules!H62) -> 0 | I19: =MIN(0,Schedules!I62) -> 0 | J19: =MIN(0,Schedules!J62) -> 0 | K19: =MIN(0,Schedules!K62) -> 0 | L19: =MIN(0,Schedules!L62) -> 0 | M19: =IF(SUMPRODUCT(ABS(C19:L19))<=B19,"OK","ERROR") -> OK
A20: Operating EBIT Positive | B20: 0.05 | H20: =MIN(0,IS!H17) -> 0 | I20: =MIN(0,IS!I17) -> 0 | J20: =MIN(0,IS!J17) -> 0 | K20: =MIN(0,IS!K17) -> 0 | L20: =MIN(0,IS!L17) -> 0 | M20: =IF(SUMPRODUCT(ABS(C20:L20))<=B20,"OK","ERROR") -> OK
A21: Finance Costs Forecast Sanity (0.5x to 3.0x FY26A) | B21: 0.05 | H21: =IF(AND(IS!H21>0.5*IS!G21,IS!H21<3*IS!G21),0,1) -> 0 | I21: =IF(AND(IS!I21>0.5*IS!G21,IS!I21<3*IS!G21),0,1) -> 0 | J21: =IF(AND(IS!J21>0.5*IS!G21,IS!J21<3*IS!G21),0,1) -> 0 | K21: =IF(AND(IS!K21>0.5*IS!G21,IS!K21<3*IS!G21),0,1) -> 0 | L21: =IF(AND(IS!L21>0.5*IS!G21,IS!L21<3*IS!G21),0,1) -> 0 | M21: =IF(SUMPRODUCT(ABS(C21:L21))<=B21,"OK","ERROR") -> OK
A23: SINGLE-POINT SYSTEM LOGIC CHECKS
A24: Scenario Switch Valid (1 = Bear, 2 = Base, 3 = Bull) | B24: 0.01 | C24: =IF(OR(Inputs!$C$5=1,Inputs!$C$5=2,Inputs!$C$5=3),0,1) -> 0 | M24: =IF(ABS(C24)<=B24,"OK","ERROR") -> OK
A25: Gold-on-Loan Switch Valid (1 = Operating, 2 = Debt-like) | B25: 0.01 | C25: =IF(OR(Inputs!$C$7=1,Inputs!$C$7=2),0,1) -> 0 | M25: =IF(ABS(C25)<=B25,"OK","ERROR") -> OK
A26: WACC strictly exceeds Terminal Growth Rate g | B26: 0.01 | C26: =IF(DCF!$C$15>Inputs!$C$18,0,1) -> 0 | M26: =IF(ABS(C26)<=B26,"OK","ERROR") -> OK
A27: Sensitivity Grid A Center = Gordon Growth DCF Value | B27: 0.01 | C27: =ROUND(Sensitivity!$E$13-DCF!$C$62,2) -> 0 | M27: =IF(ABS(C27)<=B27,"OK","ERROR") -> OK
A28: Sensitivity Grid B Center = Exit Multiple DCF Value | B28: 0.01 | C28: =ROUND(Sensitivity!$E$23-DCF!$C$73,2) -> 0 | M28: =IF(ABS(C28)<=B28,"OK","ERROR") -> OK
A29: Enterprise Value Bridge Consistency | B29: 0.01 | C29: =ROUND(DCF!$C$60-DCF!$C$52-DCF!$C$81,2) -> 0 | M29: =IF(ABS(C29)<=B29,"OK","ERROR") -> OK
A31: Total Failed Integrity Checks | C31: =COUNTIF(M5:M29,"ERROR") -> 0
A32: OVERALL WORKBOOK INTEGRITY STATUS | C32: =IF(C31=0,"ALL CHECKS PASSED","INTEGRITY COMPROMISED") -> ALL CHECKS PASSED

Sheet PowerBI_Export
A1: FLAT TABULAR EXPORT (POWER BI / PYTHON READY)
A2: Clean unpivoted dataset with uniform headers for direct ingestion into Power BI or Python pandas.
A4: Fiscal_Year | B4: Period_Type | C4: Revenue_Cr | D4: EBITDA_Cr | E4: EBIT_Cr | F4: PAT_Cr | G4: EPS_INR | H4: Gross_Margin | I4: EBITDA_Margin | J4: EBIT_Margin | K4: PAT_Margin | L4: CFO_Cr | M4: Capex_Cr | N4: FCF_Cr | O4: UFCF_Cr | P4: Cash_Cr | Q4: Borrowings_Cr | R4: Gold_Loan_Cr | S4: Lease_Cr | T4: Net_Debt_Cr | U4: Inventory_Days | V4: ROE | W4: ROIC
A5: FY22A | B5: Historical | C5: =IS!C5 -> 28799 | D5: =IS!C14 -> 3341 | E5: =IS!C17 -> 2942 | F5: =IS!C27 -> 2198 | G5: =IS!C31 -> 24.757828 | H5: =IS!C9 -> 0.2485503 | I5: =IS!C15 -> 0.11601097 | J5: =IS!C18 -> 0.10215632 | K5: =IS!C28 -> 0.076322095 | L5: =CF!C17 -> -724 | M5: =-CF!C19 -> 224 | N5: =CF!C37 -> -948 | P5: =BS!C17 -> 219 | Q5: =BS!C25 -> 518 | R5: =BS!C26 -> 5398 | S5: =BS!C27 -> 1359 | T5: =Schedules!C95 -> 5687 | U5: =Schedules!C8 -> 229.53121
A6: FY23A | B6: Historical | C6: =IS!D5 -> 40575 | D6: =IS!D14 -> 4879 | E6: =IS!D17 -> 4438 | F6: =IS!D27 -> 3274 | G6: =IS!D31 -> 36.877675 | H6: =IS!D9 -> 0.25187924 | I6: =IS!D15 -> 0.12024646 | J6: =IS!D18 -> 0.1093777 | K6: =IS!D28 -> 0.08069008 | L6: =CF!D17 -> 1370 | M6: =-CF!D19 -> 432 | N6: =CF!D37 -> 938 | P6: =BS!D17 -> 232 | Q6: =BS!D25 -> 2195 | R6: =BS!D26 -> 5299 | S6: =BS!D27 -> 1873 | T6: =Schedules!D95 -> 5860 | U6: =Schedules!D8 -> 199.41229 | V6: =Schedules!D93 -> 0.3083298 | W6: =Schedules!D94 -> 0.19932735
A7: FY24A | B7: Historical | C7: =IS!E5 -> 51084 | D7: =IS!E14 -> 5292 | E7: =IS!E17 -> 4708 | F7: =IS!E27 -> 3496 | G7: =IS!E31 -> 39.378238 | H7: =IS!E9 -> 0.2280949 | I7: =IS!E15 -> 0.10359408 | J7: =IS!E18 -> 0.092161929 | K7: =IS!E28 -> 0.068436301 | L7: =CF!E17 -> 1695 | M7: =-CF!E19 -> 691 | N7: =CF!E37 -> 1004 | P7: =BS!E17 -> 409 | Q7: =BS!E25 -> 7838 | R7: =BS!E26 -> 5341 | S7: =BS!E27 -> 2349 | T7: =Schedules!E95 -> 12336 | U7: =Schedules!E8 -> 176.34447 | V7: =Schedules!E93 -> 0.32830915 | W7: =Schedules!E94 -> 0.18029922
A8: FY25A | B8: Historical | C8: =IS!F5 -> 60456 | D8: =IS!F14 -> 5694 | E8: =IS!F17 -> 5001 | F8: =IS!F27 -> 3337 | G8: =IS!F31 -> 37.587294 | H8: =IS!F9 -> 0.21503242 | I8: =IS!F15 -> 0.0941842 | J8: =IS!F18 -> 0.082721318 | K8: =IS!F28 -> 0.055197168 | L8: =CF!F17 -> -541 | M8: =-CF!F19 -> 494 | N8: =CF!F37 -> -1035 | P8: =BS!F17 -> 407 | Q8: =BS!F25 -> 10286 | R8: =BS!F26 -> 7810 | S8: =BS!F27 -> 2681 | T8: =Schedules!F95 -> 17856 | U8: =Schedules!F8 -> 216.77259 | V8: =Schedules!F93 -> 0.31755246 | W8: =Schedules!F94 -> 0.14372075
A9: FY26A | B9: Historical | C9: =IS!G5 -> 87584 | D9: =IS!G14 -> 8355 | E9: =IS!G17 -> 7529 | F9: =IS!G27 -> 5073 | G9: =IS!G31 -> 57.141248 | H9: =IS!G9 -> 0.19726206 | I9: =IS!G15 -> 0.095394136 | J9: =IS!G18 -> 0.08596319 | K9: =IS!G28 -> 0.057921538 | L9: =CF!G17 -> 5590 | M9: =-CF!G19 -> 902 | N9: =CF!G37 -> 4688 | P9: =BS!G17 -> 873 | Q9: =BS!G25 -> 11378 | R9: =BS!G26 -> 16070 | S9: =BS!G27 -> 3173 | T9: =Schedules!G95 -> 26455 | U9: =Schedules!G8 -> 221.90102 | V9: =Schedules!G93 -> 0.37128115 | W9: =Schedules!G94 -> 0.15678912
A10: FY27E | B10: Forecast | C10: =IS!H5 -> 103349.12 | D10: =IS!H14 -> 9921.5155 | E10: =IS!H17 -> 8785.9555 | F10: =IS!H27 -> 5865.4261 | G10: =IS!H31 -> 66.066976 | H10: =IS!H9 -> 0.197 | I10: =IS!H15 -> 0.096 | J10: =IS!H18 -> 0.085012388 | K10: =IS!H28 -> 0.056753518 | L10: =CF!H17 -> 4433.9242 | M10: =-CF!H19 -> 1240.1894 | N10: =CF!H37 -> 3193.7348 | O10: =DCF!H29 -> 1578.0279 | P10: =BS!H17 -> 1033.4912 | Q10: =BS!H25 -> 11691.93 | R10: =BS!H26 -> 18507.76 | S10: =BS!H27 -> 3476.7012 | T10: =Schedules!H95 -> 29025.681 | U10: =Schedules!H8 -> 220 | V10: =Schedules!H93 -> 0.32674907 | W10: =Schedules!H94 -> 0.14344826
A11: FY28E | B11: Forecast | C11: =IS!I5 -> 118851.49 | D11: =IS!I14 -> 11647.446 | E11: =IS!I17 -> 10291.254 | F11: =IS!I27 -> 6934.2101 | G11: =IS!I31 -> 78.105543 | H11: =IS!I9 -> 0.198 | I11: =IS!I15 -> 0.098 | J11: =IS!I18 -> 0.086589189 | K11: =IS!I28 -> 0.058343486 | L11: =CF!I17 -> 6352.1374 | M11: =-CF!I19 -> 1426.2179 | N11: =CF!I37 -> 4925.9196 | O11: =DCF!I29 -> 3084.007 | P11: =BS!I17 -> 1188.5149 | Q11: =BS!I25 -> 10842.989 | R11: =BS!I26 -> 21257.419 | S11: =BS!I27 -> 3865.5748 | T11: =Schedules!I95 -> 30617.666 | U11: =Schedules!I8 -> 220 | V11: =Schedules!I93 -> 0.30314827 | W11: =Schedules!I94 -> 0.14569084
A12: FY29E | B12: Forecast | C12: =IS!J5 -> 134302.18 | D12: =IS!J14 -> 13430.218 | E12: =IS!J17 -> 11832.33 | F12: =IS!J27 -> 8081.8267 | G12: =IS!J31 -> 91.032065 | H12: =IS!J9 -> 0.199 | I12: =IS!J15 -> 0.1 | J12: =IS!J18 -> 0.088102289 | K12: =IS!J28 -> 0.060176437 | L12: =CF!J17 -> 7764.5457 | M12: =-CF!J19 -> 1611.6262 | N12: =CF!J37 -> 6152.9195 | O12: =DCF!J29 -> 4096.3241 | P12: =BS!J17 -> 1343.0218 | Q12: =BS!J25 -> 9145.4514 | R12: =BS!J26 -> 23990.932 | S12: =BS!J27 -> 4319.5144 | T12: =Schedules!J95 -> 31412.3 | U12: =Schedules!J8 -> 220 | V12: =Schedules!J93 -> 0.28204826 | W12: =Schedules!J94 -> 0.14793129
A13: FY30E | B13: Forecast | C13: =IS!K5 -> 150418.44 | D13: =IS!K14 -> 15192.263 | E13: =IS!K17 -> 13335.739 | F13: =IS!K27 -> 9233.8861 | G13: =IS!K31 -> 104.00863 | H13: =IS!K9 -> 0.2 | I13: =IS!K15 -> 0.101 | J13: =IS!K18 -> 0.088657606 | K13: =IS!K28 -> 0.061387992 | L13: =CF!K17 -> 9017.7659 | M13: =-CF!K19 -> 1805.0213 | N13: =CF!K37 -> 7212.7446 | O13: =DCF!K29 -> 4946.2399 | P13: =BS!K17 -> 1504.1844 | Q13: =BS!K25 -> 6791.3958 | R13: =BS!K26 -> 26836.299 | S13: =BS!K27 -> 4830.2105 | T13: =Schedules!K95 -> 31689.075 | U13: =Schedules!K8 -> 220 | V13: =Schedules!K93 -> 0.26169625 | W13: =Schedules!K94 -> 0.1488501
A14: FY31E | B14: Forecast | C14: =IS!L5 -> 166964.47 | D14: =IS!L14 -> 17030.376 | E14: =IS!L17 -> 14898.547 | F14: =IS!L27 -> 10454.444 | G14: =IS!L31 -> 117.75674 | H14: =IS!L9 -> 0.2 | I14: =IS!L15 -> 0.102 | J14: =IS!L18 -> 0.089231843 | K14: =IS!L28 -> 0.06261478 | L14: =CF!L17 -> 10312.795 | M14: =-CF!L19 -> 2003.5737 | N14: =CF!L37 -> 8309.2217 | O14: =DCF!L29 -> 5834.3253 | P14: =BS!L17 -> 1669.6447 | Q14: =BS!L25 -> 3715.391 | R14: =BS!L26 -> 29788.292 | S14: =BS!L27 -> 5388.9068 | T14: =Schedules!L95 -> 31379.188 | U14: =Schedules!L8 -> 220 | V14: =Schedules!L93 -> 0.24431241 | W14: =Schedules!L94 -> 0.14953587

Sheet Hist_Data
A1: HISTORICAL AUDITED SOURCE DATA (AS REPORTED)
A2: Reported numbers verified line-by-line against Titan Company Ltd Annual Reports (FY22 to FY26)
A4: Financial Statement Line | C4: FY22A | D4: FY23A | E4: FY24A | F4: FY25A | G4: FY26A | H4: Statutory Filing Reference
A5: I. CONSOLIDATED STATEMENT OF PROFIT & LOSS
A6: Revenue from operations | C6: 28799 | D6: 40575 | E6: 51084 | F6: 60456 | G6: 87584 | H6: Audited Consolidated P&L
A7: Other income | C7: 234 | D7: 308 | E7: 533 | F7: 486 | G7: 552 | H7: Audited Consolidated P&L
A8: Total income | C8: 29033 | D8: 40883 | E8: 51617 | F8: 60942 | G8: 88136 | H8: Audited Consolidated P&L
A9: Cost of materials and components consumed | C9: 22108 | D9: 26891 | E9: 36104 | F9: 47708 | G9: 69212 | H9: Audited Consolidated P&L
A10: Purchase of stock-in-trade | C10: 4328 | D10: 5698 | E10: 5999 | F10: 7563 | G10: 11031 | H10: Audited Consolidated P&L
A11: Changes in inventories | C11: -4795 | D11: -2234 | E11: -2671 | F11: -7815 | G11: -9936 | H11: Audited Consolidated P&L
A12: Employee benefits expense | C12: 1349 | D12: 1647 | E12: 1864 | F12: 2156 | G12: 2681 | H12: Audited Consolidated P&L
A13: Finance costs | C13: 218 | D13: 300 | E13: 619 | F13: 953 | G13: 1180 | H13: Audited Consolidated P&L
A14: Depreciation & amortisation | C14: 399 | D14: 441 | E14: 584 | F14: 693 | G14: 826 | H14: Audited Consolidated P&L
A15: Other expenses | C15: 2468 | D15: 3694 | E15: 4496 | F15: 5150 | G15: 6241 | H15: Audited Consolidated P&L
A16: Total expenses | C16: 26075 | D16: 36437 | E16: 46995 | F16: 56408 | G16: 81235 | H16: Audited Consolidated P&L
A17: Profit before share of associate/JV, exceptional item & tax | C17: 2958 | D17: 4446 | E17: 4622 | F17: 4534 | G17: 6901 | H17: Audited Consolidated P&L
... A25: Profit for the year | C25: 2198 | D25: 3274 | E25: 3496 | F25: 3337 | G25: 5073 | H25: Audited Consolidated P&L
A27: II. CONSOLIDATED BALANCE SHEET
A28: PPE | C28: 1218 | D28: 1343 | E28: 1737 | F28: 1854 | G28: 2684 | H28: Audited Consolidated Balance Sheet
A29: Capital work-in-progress | C29: 69 | D29: 133 | E29: 88 | F29: 93 | G29: 135 | H29: Audited Consolidated Balance Sheet
A30: Right-of-use assets | C30: 973 | D30: 1285 | E30: 1543 | F30: 1774 | G30: 2195 | H30: Audited Consolidated Balance Sheet
A31: Investment property | C31: 1 | D31: 1 | E31: 1 | F31: 1 | G31: 136 | H31: Audited Consolidated Balance Sheet
A32: Goodwill | C32: 123 | D32: 123 | E32: 123 | F32: 123 | G32: 758 | H32: Audited Consolidated Balance Sheet
A33: Other intangible assets | C33: 229 | D33: 246 | E33: 305 | F33: 310 | G33: 1105 | H33: Audited Consolidated Balance Sheet
A34: Intangible assets under development | C34: 16 | D34: 11 | E34: 9 | F34: 12 | G34: 28 | H34: Audited Consolidated Balance Sheet
A35: Investments accounted for using equity method | C35: 0 | D35: 0 | E35: 0 | F35: 0 | G35: 152 | H35: Audited Consolidated Balance Sheet
A36: Non-current investments | C36: 279 | D36: 351 | E36: 679 | F36: 651 | G36: 1105 | H36: Audited Consolidated Balance Sheet
A37: Non-current loans | C37: 42 | D37: 54 | E37: 72 | F37: 62 | G37: 66 | H37: Audited Consolidated Balance Sheet
A38: Other non-current financial assets | C38: 382 | D38: 595 | E38: 788 | F38: 868 | G38: 982 | H38: Audited Consolidated Balance Sheet
A39: Deferred tax assets | C39: 187 | D39: 158 | E39: 187 | F39: 170 | G39: 173 | H39: Audited Consolidated Balance Sheet
... A77: Total equity & liabilities | C77: 21194 | D77: 27023 | E77: 31550 | F77: 40647 | G77: 60561 | H77: Audited Consolidated Balance Sheet
A79: III. CONSOLIDATED CASH FLOW STATEMENT
A80: Net profit before tax | C80: 2904 | D80: 4447 | E80: 4623 | F80: 4535 | G80: 6801 | H80: Audited Consolidated Cash Flow Statement
A81: D&A | C81: 399 | D81: 441 | E81: 584 | F81: 693 | G81: 826 | H81: Audited Consolidated Cash Flow Statement
A82: Finance costs | C82: 218 | D82: 300 | E82: 619 | F82: 953 | G82: 1180 | H82: Audited Consolidated Cash Flow Statement
A83: Change in trade receivables | C83: -207 | D83: -112 | E83: -348 | F83: -95 | G83: 210 | H83: Audited Consolidated Cash Flow Statement
A84: Change in inventories | C84: -5199 | D84: -2977 | E84: -2462 | F84: -9072 | G84: -11592 | H84: Audited Consolidated Cash Flow Statement
A85: Change in financial-assets loans | C85: -3 | D85: -18 | E85: -21 | F85: 4 | G85: -8 | H85: Audited Consolidated Cash Flow Statement
A86: Change in other financial assets | C86: -29 | D86: 74 | E86: -130 | F86: 75 | G86: -244 | H86: Audited Consolidated Cash Flow Statement
A87: Change in other assets | C87: -223 | D87: -363 | E87: -481 | F87: -235 | G87: -217 | H87: Audited Consolidated Cash Flow Statement
A88: Change in gold on loan | C88: 1188 | D88: -99 | E88: 42 | F88: 2468 | G88: 7304 | H88: Audited Consolidated Cash Flow Statement
A89: Change in trade payables | C89: 504 | D89: -89 | E89: 196 | F89: 564 | G89: 472 | H89: Audited Consolidated Cash Flow Statement
A90: Change in other financial liabilities | C90: 179 | D90: 108 | E90: 91 | F90: 663 | G90: 1138 | H90: Audited Consolidated Cash Flow Statement
A91: Change in other liabilities | C91: 510 | D91: 994 | E91: 582 | F91: 350 | G91: 1773 | H91: Audited Consolidated Cash Flow Statement
... A106: Finance costs paid | C106: -218 | D106: -300 | E106: -619 | F106: -538 | G106: -1000 | H106: Audited Consolidated Cash Flow Statement
A108: IV. STATUTORY NOTES CALIBRATION DATA (FY25-FY26)
A109: Finance cost: interest on borrowings | F109: 551 | G109: 610 | H109: AR FY26 Note 24
A110: Finance cost: interest on lease liabilities | F110: 222 | G110: 247 | H110: AR FY26 Note 24
A111: Finance cost: interest on gold on loan | F111: 174 | G111: 320 | H111: AR FY26 Note 24
A112: Finance cost: others | F112: 6 | G112: 3 | H112: AR FY26 Note 24
A113: Depreciation: PP&E & investment property | F113: 272 | G113: 330 | H113: AR FY26 Note 25
A114: Depreciation: right-of-use assets (ROU) | F114: 360 | G114: 427 | H114: AR FY26 Note 25
A115: Amortisation: intangible assets | F115: 61 | G115: 69 | H115: AR FY26 Note 25
A116: Basic reported EPS (INR) | F116: 37.62 | G116: 57.19 | H116: Consolidated P&L

Sheet Notes
A1: METHODOLOGY, IND AS POLICIES & MODEL DOCUMENTATION
A3: MODEL ARCHITECTURE & FLOW
A4: Core Flow | B4: Inputs -> IS Drivers -> Supporting Schedules -> Cash Flow Statement -> Balance Sheet (Cash ties to CF) -> DCF Engine -> Earnings Quality -> Sensitivity / Scenarios -> Checks.
A5: Self-Balancing Identity | B5: Assets strictly equal Liabilities + Equity across every year. Cash on the balance sheet is directly derived from the cash flow statement; short-term debt functions as an automated credit line holding minimum operational cash.
A6: Circularity Prevention | B6: Finance costs and lease interests are calculated strictly on OPENING balances. This eliminates iterative calculation loops while maintaining full Ind AS accuracy.
A8: IND AS RETAIL ACCOUNTING NUANCES
A9: Gold on Loan (GoL) | B9: Procurement of gold under metal loan agreements is accounted under current financial liabilities. On the cash flow statement, movement in GoL is included within operating cash flows. The model provides a dual switch (Inputs!C7) allowing analysts to treat GoL as operating working capital or as debt-like.
A10: Ind AS 116 Leases | B10: Titan operates a vast retail store network (Tanishq, Mia, Fastrack, Eyeplus). Lease liabilities and ROU assets are modeled via explicit roll-forwards, separating lease capex from tangible capex.
A12: VALUATION FRAMEWORK
A13: Two-Stage Fade DCF | B13: To prevent a growth cliff between the 5-year explicit horizon and perpetuity, a 5-year fade period is implemented where NOPAT growth fades linearly to terminal growth g, and reinvestment rate converges to g / RONIC.
A14: Terminal Value Cross-Check | B14: Dual valuation methodology: Gordon Growth Model vs Exit EV/EBITDA multiple applied to FY31E EBITDA.
